Workbook
Name A: #REF!
Name BaseTHF: #REF!
Name boxsections: '[1]NOT ANNEALED'!$A$11:$IV$13
Name CICCIO: '[2]NOT ANNEALED'!$A$14:$IV$14
Name extrapercTHF: #REF!
Name FissoTHF: #REF!
Name kg.mtTHF: #REF!
Name LegaTHF: #REF!
Name Misura: #REF!
Name ScontoTHF: #REF!
Name ValutaTHF: #REF!

Sheet BUSINESS
A1: N | C1: Descrizione | D1: Cod.Altern. | E1: U.M. | F1: NON A LISTINO | G1: DA LISTINI TUBO | H1: PREZZO MANUALE O EXTRA | I1: BUSINESS | J1: RIF
A2: 1 | B2: ANELLO304-KG | C2: ANELLO TAGL. DA LAM. ACC. AISI 304 | E2: KG | F2: KZ | I2: =IF(F2="KZ",0,G2+H2) -> 0
A3: 2 | B3: ANELLO304-PZ | C3: ANELLO TAGL. DA LAM. ACC. AISI 304 | E3: PZ | F3: KZ | I3: =IF(F3="KZ",0,G3+H3) -> 0
A4: 3 | B4: ANELLO316-KG | C4: ANELLO TAGL. DA LAM. ACC. AISI 316 | E4: KG | F4: KZ | I4: =IF(F4="KZ",0,G4+H4) -> 0
A5: 4 | B5: ANELLO316-PZ | C5: ANELLO TAGL. DA LAM. ACC. AISI 316 | E5: PZ | F5: KZ | I5: =IF(F5="KZ",0,G5+H5) -> 0
A6: 5 | B6: ANELLO316-PZ-SP.08 | C6: ANELLO TAGL.DA LAM.ACC. AISI 316L SP.8 | E6: PZ | F6: KZ | I6: =IF(F6="KZ",0,G6+H6) -> 0
A7: 6 | B7: ANELLO316-PZ-SP.30 | C7: ANELLO TAGL.DA LAM.ACC. AISI 316L SP.30 | E7: PZ | F7: KZ | I7: =IF(F7="KZ",0,G7+H7) -> 0
A8: 7 | B8: ANG INOX DA LAM. | C8: ANG. ACC. AISI 304 DA LAMIERA | E8: KG | F8: KZ | I8: =IF(F8="KZ",0,G8+H8) -> 0
A9: 8 | B9: ANG304 | C9: ANG. ACC. AISI 304 LAM. | E9: KG | F9: KZ | I9: =IF(F9="KZ",0,G9+H9) -> 0
A10: 9 | B10: ANG304-100X100X10 | C10: ANG. ACC. AISI 304 LAM. | D10: 100 X 100 X 10 | E10: KG | G10: =ANG!D32 -> 3.36 | I10: =IF(F10="KZ",0,G10+H10) -> 3.36
A11: 10 | B11: ANG304-20X20X3 | C11: ANG. ACC. AISI 304 LAM. | D11: 20 X 20 X 3 | E11: KG | G11: =ANG!D8 -> 3.76 | I11: =IF(F11="KZ",0,G11+H11) -> 3.76
A12: 11 | B12: ANG304-25X25X3 | C12: ANG. ACC. AISI 304 LAM. | D12: 25 X 25 X 3 | E12: KG | G12: =ANG!D10 -> 3.59 | I12: =IF(F12="KZ",0,G12+H12) -> 3.59
A13: 12 | B13: ANG304-25X25X4 | C13: ANG. ACC. AISI 304 LAM. | D13: 25 X 25 X 4 | E13: KG | G13: =ANG!D11 -> 3.59 | I13: =IF(F13="KZ",0,G13+H13) -> 3.59
A14: 13 | B14: ANG304-25X25X5 | C14: ANG. ACC. AISI 304 LAM | D14: 25 X 25 X 5 | E14: KG | G14: =ANG!D12 -> 3.59 | I14: =IF(F14="KZ",0,G14+H14) -> 3.59
A15: 14 | B15: ANG304-30X30X3 | C15: ANG. ACC. AISI 304 LAM. | D15: 30 X 30 X 3 | E15: KG | G15: =ANG!D14 -> 3.46 | I15: =IF(F15="KZ",0,G15+H15) -> 3.46
A16: 15 | B16: ANG304-30X30X4 | C16: ANG. ACC. AISI 304 LAM. | D16: 30 X 30 X 4 | E16: KG | G16: =ANG!D15 -> 3.46 | H16: 0.31 | I16: =IF(F16="KZ",0,G16+H16) -> 3.77
A17: 16 | B17: ANG304-30X30X5 | C17: ANG. ACC. AISI 304 LAM. | D17: 30 X 30 X 5 | E17: KG | G17: =ANG!D16 -> 3.36 | H17: 0.41 | I17: =IF(F17="KZ",0,G17+H17) -> 3.77
A18: 17 | B18: ANG304-35X35X3 | C18: ANG. ACC. AISI 304 LAM | D18: 35 X 35 X 3 | E18: KG | F18: KZ | G18: =ANG!B18 -> 3 | H18: 0.4 | I18: =IF(F18="KZ",0,G18+H18) -> 0
A19: 18 | B19: ANG304-35X35X4 | C19: ANG. ACC. AISI 304 LAM. | D19: 35 X 35 X 4 | E19: KG | G19: =ANG!D19 -> 3.36 | I19: =IF(F19="KZ",0,G19+H19) -> 3.36
A20: 19 | B20: ANG304-40X40X3 | C20: ANG. ACC. AISI 304 LAM. | D20: 40 X 40 X 3 | E20: KG | G20: =ANG!D21 -> 3.36 | I20: =IF(F20="KZ",0,G20+H20) -> 3.36
A21: 20 | B21: ANG304-40X40X4,0 | C21: ANG. ACC. AISI 304 LAM. | D21: 40 X 40 X 4 | E21: KG | G21: =ANG!D22 -> 3.36 | I21: =IF(F21="KZ",0,G21+H21) -> 3.36
A22: 21 | B22: ANG304-40X40X5 | C22: ANG. ACC. AISI 304 LAM. | D22: 40 X 40 X 5 | E22: KG | G22: =ANG!D23 -> 3.36 | H22: 0.11 | I22: =IF(F22="KZ",0,G22+H22) -> 3.47
A23: 22 | B23: ANG304-40X40X6 | C23: ANG. ACC. AISI 304 LAM. | D23: 40 X 40 X 6 | E23: KG | F23: KZ | I23: =IF(F23="KZ",0,G23+H23) -> 0
B24: ANG304-50X50X4 | C24: ANG. ACC. AISI 304 LAM. | D24: 50 X 50 X 4 | E24: KG | F24: KZ | G24: =ANG!D25 -> 3.36 | I24: =IF(F24="KZ",0,G24+H24) -> 0
A25: 23 | B25: ANG304-50X50X5 | C25: ANG. ACC. AISI 304 LAM. | D25: 50 X 50 X 5 | E25: KG | G25: =ANG!D26 -> 3.36 | I25: =IF(F25="KZ",0,G25+H25) -> 3.36
A26: 24 | B26: ANG304-60X60X6 | C26: ANG. ACC. AISI 304 LAM. | D26: 60 X 60 X 6 | E26: KG | G26: =ANG!D28 -> 3.36 | I26: =IF(F26="KZ",0,G26+H26) -> 3.36
A27: 25 | B27: ANG304-70X70X7 | C27: ANG. ACC. AISI 304 LAM. | D27: 70 X 70 X 7 | E27: KG | F27: KZ | I27: =IF(F27="KZ",0,G27+H27) -> 0
A28: 26 | B28: ANG304-80X80X8 | C28: ANG. ACC. AISI 304 LAM. | D28: 80 X 80 X 8 | E28: KG | G28: =ANG!D30 -> 3.36 | I28: =IF(F28="KZ",0,G28+H28) -> 3.36
A29: 27 | B29: ANG310 | C29: ANG. ACC. AISI 310 LAM. | E29: KG | F29: KZ | I29: =IF(F29="KZ",0,G29+H29) -> 0
A30: 28 | B30: ANG316 | C30: ANG. ACC. AISI 316 LAM. | E30: KG | F30: KZ | I30: =IF(F30="KZ",0,G30+H30) -> 0
A31: 29 | B31: ANG316-020X20X3 | C31: ANG. ACC. AISI 316 LAM. | D31: 20 X 20 X 3 | E31: KG | F31: KZ | G31: =ANG!H8 -> 0 | I31: =IF(F31="KZ",0,G31+H31) -> 0
A32: 30 | B32: ANG316-025X25X3 | C32: ANG. ACC. AISI 316 LAM. | D32: 25 X 25 X 3 | E32: KG | F32: KZ | G32: =ANG!H10 -> 0 | I32: =IF(F32="KZ",0,G32+H32) -> 0
A33: 31 | B33: ANG316-030X30X3 | C33: ANG. ACC. AISI 316 LAM. | D33: 30 X 30 X 3 | E33: KG | F33: KZ | G33: =ANG!H14 -> 0 | I33: =IF(F33="KZ",0,G33+H33) -> 0
A34: 32 | B34: ANG316-030X30X4 | C34: ANG. ACC. AISI 316 LAM. | D34: 30 X 30 X 4 | E34: KG | F34: KZ | G34: =ANG!H15 -> 0 | I34: =IF(F34="KZ",0,G34+H34) -> 0
A35: 33 | B35: ANG316-035X35X4,0 | C35: ANG. ACC. AISI 316 LAM. | D35: 35 X 35 X 4 | E35: KG | F35: KZ | G35: =ANG!H19 -> 0 | I35: =IF(F35="KZ",0,G35+H35) -> 0
A36: 34 | B36: ANG316-040X40X4,0 | C36: ANG. ACC. AISI 316 LAM. | D36: 40 X 40 X 4 | E36: KG | F36: KZ | G36: =ANG!H22 -> 0 | I36: =IF(F36="KZ",0,G36+H36) -> 0
A37: 35 | B37: ANG316-040X40X5,0 | C37: ANG. ACC. AISI 316 LAM. | D37: 40 X 40 X 5 | E37: KG | F37: KZ | G37: =ANG!H23 -> 0 | I37: =IF(F37="KZ",0,G37+H37) -> 0
A38: 36 | B38: ANG316-50X50X5 | C38: ANG. ACC. AISI 316 LAM. | D38: 50 X 50 X 5 | E38: KG | F38: KZ | G38: =ANG!H26 -> 6.05 | I38: =IF(F38="KZ",0,G38+H38) -> 0
A39: 37 | B39: ANG316-60X60X6 | C39: ANG. ACC. AISI 316 LAM. | D39: 60 X 60 X 6 | E39: KG | F39: KZ | G39: =ANG!H28 -> 6.05 | I39: =IF(F39="KZ",0,G39+H39) -> 0
A40: 38 | B40: ANG316-75X75X10 | C40: ANG. ACC. AISI 316 LAM. | D40: 75 X 75 X 10 | E40: KG | F40: KZ | I40: =IF(F40="KZ",0,G40+H40) -> 0
A41: 39 | B41: ANG316-80X80X8 | C41: ANG. ACC. AISI 316 LAM. | D41: 80 X 80 X 8 | E41: KG | F41: KZ | G41: =ANG!H30 -> 6.15 | I41: =IF(F41="KZ",0,G41+H41) -> 0
A42: 40 | B42: AVP* | C42: BARRA ACCIAIO AVP | E42: KG | F42: KZ | I42: =IF(F42="KZ",0,G42+H42) -> 0
A43: 41 | B43: BANC | C43: BANCALE IN LEGNO IN ADD.TO | E43: PZ | F43: KZ | I43: =IF(F43="KZ",0,G43+H43) -> 0
A44: 42 | B44: BANC1000 | C44: BANCALE IN LEGNO H. 1000 | E44: PZ | H44: 50 | I44: =IF(F44="KZ",0,G44+H44) -> 50
A45: 43 | B45: BANC1250 | C45: BANCALE IN LEGNO H. 1250 | E45: PZ | H45: 60 | I45: =IF(F45="KZ",0,G45+H45) -> 60
A46: 44 | B46: BANC1500 | C46: BANCALE IN LEGNO H. 1500 | E46: PZ | H46: 60 | I46: =IF(F46="KZ",0,G46+H46) -> 60
A47: 45 | B47: BANC2000 | C47: BANCALE IN LEGNO H. 2000 | E47: PZ | H47: 100 | I47: =IF(F47="KZ",0,G47+H47) -> 100
A48: 46 | B48: BCA304-050X10L=6 | C48: BARRA ACC. AISI 304 L=6000 | D48: 50 X 10 | E48: KG | F48: KZ | I48: =IF(F48="KZ",0,G48+H48) -> 0
A49: 47 | B49: BCE304 | C49: BARRA ACC. AISI 304 CES. | E49: KG | F49: KZ | I49: =IF(F49="KZ",0,G49+H49) -> 0
A50: 48 | B50: BCE304-010X03 | C50: BARRA ACC. AISI 304 CES. | D50: 10 X 3 | E50: KG | G50: =CESOIATI!$C$9 -> 3.5 | I50: =IF(F50="KZ",0,G50+H50) -> 3.5
A51: 49 | B51: BCE304-010X04 | C51: BARRA ACC. AISI 304 CES. | D51: 10 X 4 | E51: KG | G51: =CESOIATI!$C$9 -> 3.5 | I51: =IF(F51="KZ",0,G51+H51) -> 3.5
A52: 50 | B52: BCE304-010X05 | C52: BARRA ACC. AISI 304 CES. | D52: 10 X 5 | E52: KG | G52: =CESOIATI!$C$9 -> 3.5 | I52: =IF(F52="KZ",0,G52+H52) -> 3.5
A53: 51 | B53: BCE304-012X03 | C53: BARRA ACC. AISI 304 CES. | D53: 12 X 3 | E53: KG | G53: =CESOIATI!$C$9 -> 3.5 | I53: =IF(F53="KZ",0,G53+H53) -> 3.5
A54: 52 | B54: BCE304-012X04 | C54: BARRA ACC. AISI 304 CES. | D54: 12 X 4 | E54: KG | G54: =CESOIATI!$C$9 -> 3.5 | I54: =IF(F54="KZ",0,G54+H54) -> 3.5
A55: 53 | B55: BCE304-012X05 | C55: BARRA ACC. AISI 304 CES. | D55: 12 X 5 | E55: KG | G55: =CESOIATI!$C$9 -> 3.5 | I55: =IF(F55="KZ",0,G55+H55) -> 3.5
A56: 54 | B56: BCE304-012X06 | C56: BARRA ACC. AISI 304 CES. | D56: 12 X 6 | E56: KG | G56: =CESOIATI!$C$9 -> 3.5 | I56: =IF(F56="KZ",0,G56+H56) -> 3.5
A57: 55 | B57: BCE304-015X02 | C57: BARRA ACC. AISI 304 CES. | D57: 15 X 2 | E57: KG | F57: KZ | G57: =CESOIATI!$C$9 -> 3.5 | I57: =IF(F57="KZ",0,G57+H57) -> 0
A58: 56 | B58: BCE304-015X03 | C58: BARRA ACC. AISI 304 CES. | D58: 15 X 3 | E58: KG | G58: =CESOIATI!$C$9 -> 3.5 | I58: =IF(F58="KZ",0,G58+H58) -> 3.5
A59: 57 | B59: BCE304-015X04 | C59: BARRA ACC. AISI 304 CES. | D59: 15 X 4 | E59: KG | G59: =CESOIATI!$C$9 -> 3.5 | I59: =IF(F59="KZ",0,G59+H59) -> 3.5
A60: 58 | B60: BCE304-015X05 | C60: BARRA ACC. AISI 304 CES. | D60: 15 X 5 | E60: KG | G60: =CESOIATI!$C$9 -> 3.5 | I60: =IF(F60="KZ",0,G60+H60) -> 3.5
A61: 59 | B61: BCE304-015X06 | C61: BARRA ACC. AISI 304 CES. | D61: 15 X 6 | E61: KG | G61: =CESOIATI!$C$9 -> 3.5 | I61: =IF(F61="KZ",0,G61+H61) -> 3.5
A62: 60 | B62: BCE304-020X02 | C62: BARRA ACC. AISI 304 CES. | D62: 20 X 2 | E62: KG | F62: KZ | G62: =CESOIATI!$C$11 -> 2.65 | I62: =IF(F62="KZ",0,G62+H62) -> 0
A63: 61 | B63: BCE304-020X03 | C63: BARRA ACC. AISI 304 CES. | D63: 20 X 3 | E63: KG | G63: =CESOIATI!$C$11 -> 2.65 | I63: =IF(F63="KZ",0,G63+H63) -> 2.65
A64: 62 | B64: BCE304-020X04 | C64: BARRA ACC. AISI 304 CES. | D64: 20 X 4 | E64: KG | G64: =CESOIATI!$C$11 -> 2.65 | I64: =IF(F64="KZ",0,G64+H64) -> 2.65
A65: 63 | B65: BCE304-020X04X5200 | C65: BARRA ACC. AISI 304 CES. L=5200 | D65: 20 X 4 | E65: KG | G65: =CESOIATI!$C$11 -> 2.65 | I65: =IF(F65="KZ",0,G65+H65) -> 2.65
A66: 64 | B66: BCE304-020X04X6000 | C66: BARRA ACC. AISI 304 CES. L=6000 | D66: 20 X 4 | E66: KG | G66: =CESOIATI!$C$11 -> 2.65 | I66: =IF(F66="KZ",0,G66+H66) -> 2.65
A67: 65 | B67: BCE304-020X05 | C67: BARRA ACC. AISI 304 CES. | D67: 20 X 5 | E67: KG | G67: =CESOIATI!$C$11 -> 2.65 | I67: =IF(F67="KZ",0,G67+H67) -> 2.65
A68: 66 | B68: BCE304-020X05X5200 | C68: BARRA ACC. AISI 304 CES. L=5200 | D68: 20 X 5 | E68: KG | F68: KZ | G68: =CESOIATI!$C$11 -> 2.65 | I68: =IF(F68="KZ",0,G68+H68) -> 0
A69: 67 | B69: BCE304-020X05X6000 | C69: BARRA ACC. AISI 304 CES. L=6000 | D69: 20 X 5 | E69: KG | G69: =CESOIATI!$C$11 -> 2.65 | I69: =IF(F69="KZ",0,G69+H69) -> 2.65
A70: 68 | B70: BCE304-020X06 | C70: BARRA ACC. AISI 304 CES. | D70: 20 X 6 | E70: KG | G70: =CESOIATI!$C$11 -> 2.65 | I70: =IF(F70="KZ",0,G70+H70) -> 2.65
A71: 69 | B71: BCE304-020X08 | C71: BARRA ACC. AISI 304 CES. | D71: 20 X 8 | E71: KG | G71: =CESOIATI!$C$11 -> 2.65 | I71: =IF(F71="KZ",0,G71+H71) -> 2.65
A72: 70 | B72: BCE304-020X10 | C72: BARRA ACC. AISI 304 CES. | D72: 20 X 10 | E72: KG | G72: =CESOIATI!$C$13 -> 2.7 | I72: =IF(F72="KZ",0,G72+H72) -> 2.7
A73: 71 | B73: BCE304-020X10X6000 | C73: BARRA ACC. AISI 304 CES. L=6000 | D73: 20 X 10 | E73: KG | G73: =CESOIATI!$C$13 -> 2.7 | I73: =IF(F73="KZ",0,G73+H73) -> 2.7
A74: 72 | B74: BCE304-020X12 | C74: BARRA ACC. AISI 304 CES. | D74: 20 X 12 | E74: KG | F74: KZ | G74: =CESOIATI!$C$11 -> 2.65 | I74: =IF(F74="KZ",0,G74+H74) -> 0
A75: 73 | B75: BCE304-025X03 | C75: BARRA ACC. AISI 304 CES. | D75: 25 X 3 | E75: KG | G75: =CESOIATI!$C$11 -> 2.65 | I75: =IF(F75="KZ",0,G75+H75) -> 2.65
A76: 74 | B76: BCE304-025X04 | C76: BARRA ACC. AISI 304 CES. | D76: 25 X 4 | E76: KG | G76: =CESOIATI!$C$11 -> 2.65 | I76: =IF(F76="KZ",0,G76+H76) -> 2.65
A77: 75 | B77: BCE304-025X05 | C77: BARRA ACC. AISI 304 CES. | D77: 25 X 5 | E77: KG | G77: =CESOIATI!$C$11 -> 2.65 | I77: =IF(F77="KZ",0,G77+H77) -> 2.65
A78: 76 | B78: BCE304-025X05X6000 | C78: BARRA ACC. AISI 304 CES. L=6000 | D78: 25 X 5 | E78: KG | G78: =CESOIATI!$C$11 -> 2.65 | I78: =IF(F78="KZ",0,G78+H78) -> 2.65
A79: 77 | B79: BCE304-025X06 | C79: BARRA ACC. AISI 304 CES. | D79: 25 X 6 | E79: KG | G79: =CESOIATI!$C$11 -> 2.65 | I79: =IF(F79="KZ",0,G79+H79) -> 2.65
A80: 78 | B80: BCE304-025X08 | C80: BARRA ACC. AISI 304 CES. | D80: 25 X 8 | E80: KG | G80: =CESOIATI!$C$11 -> 2.65 | I80: =IF(F80="KZ",0,G80+H80) -> 2.65
A81: 79 | B81: BCE304-025X08SAT | C81: BARRA ACC. AISI 304 CES. SATINATO | D81: 25 X 8 | E81: KG | F81: KZ | G81: =CESOIATI!$C$11 -> 2.65 | I81: =IF(F81="KZ",0,G81+H81) -> 0
A82: 80 | B82: BCE304-025X10 | C82: BARRA ACC. AISI 304 CES. | D82: 25 X 10 | E82: KG | G82: =CESOIATI!$C$13 -> 2.7 | I82: =IF(F82="KZ",0,G82+H82) -> 2.7
A83: 81 | B83: BCE304-030X03 | C83: BARRA ACC. AISI 304 CES. | D83: 30 X 3 | E83: KG | G83: =CESOIATI!$C$11 -> 2.65 | I83: =IF(F83="KZ",0,G83+H83) -> 2.65
B84: BCE304-030X03X6000 | C84: BARRA ACC. AISI 304 CES. L=6000 | D84: 30 X 3 | E84: KG | G84: =CESOIATI!$C$11 -> 2.65 | I84: =IF(F84="KZ",0,G84+H84) -> 2.65
A85: 82 | B85: BCE304-030X04 | C85: BARRA ACC. AISI 304 CES. | D85: 30 X 4 | E85: KG | G85: =CESOIATI!$C$11 -> 2.65 | I85: =IF(F85="KZ",0,G85+H85) -> 2.65
A86: 83 | B86: BCE304-030X05 | C86: BARRA ACC. AISI 304 CES. | D86: 30 X 5 | E86: KG | G86: =CESOIATI!$C$11 -> 2.65 | I86: =IF(F86="KZ",0,G86+H86) -> 2.65
A87: 84 | B87: BCE304-030X05X6000 | C87: BARRA ACC. AISI 304 CES. L=6000 | D87: 30 X 5 | E87: KG | G87: =CESOIATI!$C$11 -> 2.65 | I87: =IF(F87="KZ",0,G87+H87) -> 2.65
A88: 85 | B88: BCE304-030X06 | C88: BARRA ACC. AISI 304 CES. | D88: 30 X 6 | E88: KG | G88: =CESOIATI!$C$11 -> 2.65 | I88: =IF(F88="KZ",0,G88+H88) -> 2.65
A89: 86 | B89: BCE304-030X06 SATI | C89: BARRA ACC. AISI 304 CES. SATINATA | D89: 30 X 6 | E89: KG | F89: KZ | G89: =CESOIATI!$C$11 -> 2.65 | I89: =IF(F89="KZ",0,G89+H89) -> 0
A90: 87 | B90: BCE304-030X08 | C90: BARRA ACC. AISI 304 CES. | D90: 30 X 8 | E90: KG | G90: =CESOIATI!$C$11 -> 2.65 | I90: =IF(F90="KZ",0,G90+H90) -> 2.65
A91: 88 | B91: BCE304-030X08X6000 | C91: BARRA ACC. AISI 304 CES. L=6000 | D91: 30 X 8 | E91: KG | G91: =CESOIATI!$C$11 -> 2.65 | I91: =IF(F91="KZ",0,G91+H91) -> 2.65
A92: 89 | B92: BCE304-030X10 | C92: BARRA ACC. AISI 304 CES. | D92: 30 X 10 | E92: KG | G92: =CESOIATI!$C$13 -> 2.7 | I92: =IF(F92="KZ",0,G92+H92) -> 2.7
A93: 90 | B93: BCE304-030X10L6000 | C93: BARRA ACC. AISI 304 CES. L=6000 | D93: 30 X 10 | E93: KG | G93: =CESOIATI!$C$13 -> 2.7 | I93: =IF(F93="KZ",0,G93+H93) -> 2.7
A94: 91 | B94: BCE304-030X12 | C94: BARRA ACC. AISI 304 CES. | D94: 30 X 12 | E94: KG | G94: =CESOIATI!$C$13 -> 2.7 | I94: =IF(F94="KZ",0,G94+H94) -> 2.7
A95: 92 | B95: BCE304-035X03 | C95: BARRA ACC. AISI 304 CES. | D95: 35 X 3 | E95: KG | G95: =CESOIATI!$C$11 -> 2.65 | I95: =IF(F95="KZ",0,G95+H95) -> 2.65
A96: 93 | B96: BCE304-035X04 | C96: BARRA ACC. AISI 304 CES. | D96: 35 X 4 | E96: KG | G96: =CESOIATI!$C$11 -> 2.65 | I96: =IF(F96="KZ",0,G96+H96) -> 2.65
A97: 94 | B97: BCE304-035X05 | C97: BARRA ACC. AISI 304 CES. | D97: 35 X 5 | E97: KG | G97: =CESOIATI!$C$11 -> 2.65 | I97: =IF(F97="KZ",0,G97+H97) -> 2.65
A98: 95 | B98: BCE304-035X06 | C98: BARRA ACC. AISI 304 CES. | D98: 35 X 6 | E98: KG | G98: =CESOIATI!$C$11 -> 2.65 | I98: =IF(F98="KZ",0,G98+H98) -> 2.65
A99: 96 | B99: BCE304-035X08 | C99: BARRA ACC. AISI 304 CES. | D99: 35 X 8 | E99: KG | G99: =CESOIATI!$C$11 -> 2.65 | I99: =IF(F99="KZ",0,G99+H99) -> 2.65
A100: 97 | B100: BCE304-035X10 | C100: BARRA ACC. AISI 304 CES. | D100: 35 X 10 | E100: KG | G100: =CESOIATI!$C$13 -> 2.7 | I100: =IF(F100="KZ",0,G100+H100) -> 2.7
...

Sheet ROUND HF
A1: PRICE LIST MAY '26 | T1: DC 8.2_03
C2: DISCOUNT | M2: 0.52 | N2: 0.52
C3: Alloy Surcharge €/Kg | M3: 0 | N3: 0
C4: ROUND HF | M4: 304L | N4: 316L | V4: DKK | W4: 0
V5: EUR | W5: 1
V6: GBP | W6: 0.87
D7: EXTRA % | M7: 1 | V7: NOK | W7: 0
C8: Rate | M8: EUR | V8: SEK | W8: 0
V9: USD | W9: 1.16
M10: BRUSHED NOT ANNEALED | P10: O.D. POLISHED G.240/320 | S10: O.D. MIRROR POLISHED
B11: MT | C11: Dimension | F11: €/kg | M11: 1.4301 | N11: 1.4404 1.4571 | P11: 1.4301 | Q11: 1.4404 1.4571 | S11: 1.4301 | T11: 1.4404 1.4571 | V11: IN USO | W11: =VLOOKUP(M8,$V$4:$W$9,2) -> 1
B12: PACCO | C12: diam. | D12: Thk. | E12: kg/mt | F12: €/kg | H12: 304 | I12: ex 316 | J12: b 316 | K12: 316L | M12: 304 | N12: 316 J / Ti | O12: SAT | P12: 304 | Q12: 316 L / Ti | R12: LUC | S12: 304 | T12: 316 L / Ti | U12: Kg/Bdl
B13: 810 | C13: 12 | D13: 1 | E13: =(C13-D13)*D13*0.02504 -> 0.27544 | F13: 1 | G13: =CONCATENATE(C13,D13) -> 121 | H13: 2.85 | I13: 1.2 | J13: 3.65 | K13: =I13+J13 -> 4.85 | M13: =((F13*(1-$M$2)+H13+$M$3)*E13*$M$7)*$W$11 -> 0.9172152 | O13: 0.68904 | P13: =M13+O13*$W$11 -> 1.6062552 | R13: 1.2474 | S13: =M13+R13*$W$11 -> 2.1646152 | U13: =E13*B13 -> 223.1064
B14: 810 | C14: 12 | D14: 1.2 | E14: =(C14-D14)*D14*0.02504 -> 0.3245184 | F14: 1 | G14: =CONCATENATE(C14,D14) -> 121,2 | H14: 2.9 | I14: 1.2 | J14: 3.7 | K14: =I14+J14 -> 4.9 | M14: =((F14*(1-$M$2)+H14+$M$3)*E14*$M$7)*$W$11 -> 1.0968722 | O14: 0.69 | P14: =M14+O14*$W$11 -> 1.7868722 | R14: 1.2474 | S14: =M14+R14*$W$11 -> 2.3442722 | U14: =E14*B14 -> 262.8599
B15: 810 | C15: 12 | D15: 1.5 | E15: =(C15-D15)*D15*0.02504 -> 0.39438 | F15: 1 | G15: =CONCATENATE(C15,D15) -> 121,5 | H15: 2.77 | I15: 1.2 | J15: 3.57 | K15: =I15+J15 -> 4.77 | M15: =((F15*(1-$M$2)+H15+$M$3)*E15*$M$7)*$W$11 -> 1.281735 | N15: =((F15*(1-$N$2)+K15+$N$3)*E15*$M$7)*$W$11 -> 2.070495 | O15: 0.68904 | P15: =M15+O15*$W$11 -> 1.970775 | Q15: =N15+O15*$W$11 -> 2.759535 | R15: 1.2474 | S15: =M15+R15*$W$11 -> 2.529135 | T15: =N15+R15*$W$11 -> 3.317895 | U15: =E15*B15 -> 319.4478
B16: 678 | C16: 14 | D16: 1 | E16: =(C16-D16)*D16*0.02504 -> 0.32552 | F16: 1 | G16: =CONCATENATE(C16,D16) -> 141 | H16: 2.76 | I16: 1.2 | J16: 3.56 | K16: =I16+J16 -> 4.76 | M16: =((F16*(1-$M$2)+H16+$M$3)*E16*$M$7)*$W$11 -> 1.0546848 | O16: 0.68904 | P16: =M16+O16*$W$11 -> 1.7437248 | R16: 1.2474 | S16: =M16+R16*$W$11 -> 2.3020848 | U16: =E16*B16 -> 220.70256
B17: 679 | C17: 14 | D17: 1.2 | E17: =(C17-D17)*D17*0.02504 -> 0.3846144 | F17: 1 | G17: =CONCATENATE(C17,D17) -> 141,2 | H17: 2.8 | I17: 1.2 | J17: 3.6 | K17: =I17+J17 -> 4.8 | M17: =((F17*(1-$M$2)+H17+$M$3)*E17*$M$7)*$W$11 -> 1.2615352 | O17: 0.69 | P17: =M17+O17*$W$11 -> 1.9515352 | R17: 1.25 | S17: =M17+R17*$W$11 -> 2.5115352 | U17: =E17*B17 -> 261.15318
B18: 678 | C18: 14 | D18: 1.5 | E18: =(C18-D18)*D18*0.02504 -> 0.4695 | F18: 1 | G18: =CONCATENATE(C18,D18) -> 141,5 | H18: 2.7 | I18: 1.2 | J18: 3.5 | K18: =I18+J18 -> 4.7 | M18: =((F18*(1-$M$2)+H18+$M$3)*E18*$M$7)*$W$11 -> 1.49301 | N18: =((F18*(1-$N$2)+K18+$N$3)*E18*$M$7)*$W$11 -> 2.43201 | O18: 0.68904 | P18: =M18+O18*$W$11 -> 2.18205 | Q18: =N18+O18*$W$11 -> 3.12105 | R18: 1.2474 | S18: =M18+R18*$W$11 -> 2.74041 | T18: =N18+R18*$W$11 -> 3.67941 | U18: =E18*B18 -> 318.321
B19: 678 | C19: 14 | D19: 2 | E19: =(C19-D19)*D19*0.02504 -> 0.60096 | F19: 1 | G19: =CONCATENATE(C19,D19) -> 142 | H19: 2.43 | I19: 1.47 | J19: 3.08 | K19: =I19+J19 -> 4.55 | M19: =((F19*(1-$M$2)+H19+$M$3)*E19*$M$7)*$W$11 -> 1.7487936 | N19: =((F19*(1-$N$2)+K19+$N$3)*E19*$M$7)*$W$11 -> 3.0228288 | O19: 0.7128 | P19: =M19+O19*$W$11 -> 2.4615936 | Q19: =N19+O19*$W$11 -> 3.7356288 | R19: 1.2474 | S19: =M19+R19*$W$11 -> 2.9961936 | T19: =N19+R19*$W$11 -> 4.2702288 | U19: =E19*B19 -> 407.45088
B20: 678 | C20: 15 | D20: 1 | E20: =(C20-D20)*D20*0.02504 -> 0.35056 | F20: 1 | G20: =CONCATENATE(C20,D20) -> 151 | H20: 2.75 | I20: 1.2 | J20: 3.55 | K20: =I20+J20 -> 4.75 | M20: =((F20*(1-$M$2)+H20+$M$3)*E20*$M$7)*$W$11 -> 1.1323088 | O20: 0.68904 | P20: =M20+O20*$W$11 -> 1.8213488 | R20: 1.2474 | S20: =M20+R20*$W$11 -> 2.3797088 | U20: =E20*B20 -> 237.67968
B21: 678 | C21: 15 | D21: 1.5 | E21: =(C21-D21)*D21*0.02504 -> 0.50706 | F21: 1 | G21: =CONCATENATE(C21,D21) -> 151,5 | H21: 2.67 | I21: 1.2 | J21: 3.47 | K21: =I21+J21 -> 4.67 | M21: =((F21*(1-$M$2)+H21+$M$3)*E21*$M$7)*$W$11 -> 1.597239 | N21: =((F21*(1-$N$2)+K21+$N$3)*E21*$M$7)*$W$11 -> 2.611359 | O21: 0.68904 | P21: =M21+O21*$W$11 -> 2.286279 | Q21: =N21+O21*$W$11 -> 3.300399 | R21: 1.2474 | S21: =M21+R21*$W$11 -> 2.844639 | T21: =N21+R21*$W$11 -> 3.858759 | U21: =E21*B21 -> 343.78668
B22: 678 | C22: 15 | D22: 2 | E22: =(C22-D22)*D22*0.02504 -> 0.65104 | F22: 1 | G22: =CONCATENATE(C22,D22) -> 152 | H22: 2.41 | I22: 1.47 | J22: 3.06 | K22: =I22+J22 -> 4.53 | M22: =((F22*(1-$M$2)+H22+$M$3)*E22*$M$7)*$W$11 -> 1.8815056 | N22: =((F22*(1-$N$2)+K22+$N$3)*E22*$M$7)*$W$11 -> 3.2617104 | O22: 0.7128 | P22: =M22+O22*$W$11 -> 2.5943056 | Q22: =N22+O22*$W$11 -> 3.9745104 | R22: 1.2474 | S22: =M22+R22*$W$11 -> 3.1289056 | T22: =N22+R22*$W$11 -> 4.5091104 | U22: =E22*B22 -> 441.40512
B23: 678 | C23: 16 | D23: 1 | E23: =(C23-D23)*D23*0.02504 -> 0.3756 | F23: 1 | G23: =CONCATENATE(C23,D23) -> 161 | H23: 2.72 | I23: 1.2 | J23: 3.52 | K23: =I23+J23 -> 4.72 | M23: =((F23*(1-$M$2)+H23+$M$3)*E23*$M$7)*$W$11 -> 1.20192 | O23: 0.68904 | P23: =M23+O23*$W$11 -> 1.89096 | R23: 1.2474 | S23: =M23+R23*$W$11 -> 2.44932 | U23: =E23*B23 -> 254.6568
B24: 678 | C24: 16 | D24: 1.2 | E24: =(C24-D24)*D24*0.02504 -> 0.4447104 | F24: 1 | G24: =CONCATENATE(C24,D24) -> 161,2 | H24: 2.7 | I24: 1.2 | J24: 3.5 | K24: =I24+J24 -> 4.7 | M24: =((F24*(1-$M$2)+H24+$M$3)*E24*$M$7)*$W$11 -> 1.4141791 | O24: 0.68904 | P24: =M24+O24*$W$11 -> 2.1032191 | R24: 1.2474 | S24: =M24+R24*$W$11 -> 2.6615791 | U24: =E24*B24 -> 301.51365
B25: 678 | C25: 16 | D25: 1.5 | E25: =(C25-D25)*D25*0.02504 -> 0.54462 | F25: 1 | G25: =CONCATENATE(C25,D25) -> 161,5 | H25: 2.64 | I25: 1.2 | J25: 3.44 | K25: =I25+J25 -> 4.64 | M25: =((F25*(1-$M$2)+H25+$M$3)*E25*$M$7)*$W$11 -> 1.6992144 | N25: =((F25*(1-$N$2)+K25+$N$3)*E25*$M$7)*$W$11 -> 2.7884544 | O25: 0.68904 | P25: =M25+O25*$W$11 -> 2.3882544 | Q25: =N25+O25*$W$11 -> 3.4774944 | R25: 1.2474 | S25: =M25+R25*$W$11 -> 2.9466144 | T25: =N25+R25*$W$11 -> 4.0358544 | U25: =E25*B25 -> 369.25236
B26: 678 | C26: 16 | D26: 2 | E26: =(C26-D26)*D26*0.02504 -> 0.70112 | F26: 1 | G26: =CONCATENATE(C26,D26) -> 162 | H26: 2.38 | I26: 1.47 | J26: 3.03 | K26: =I26+J26 -> 4.5 | M26: =((F26*(1-$M$2)+H26+$M$3)*E26*$M$7)*$W$11 -> 2.0052032 | N26: =((F26*(1-$N$2)+K26+$N$3)*E26*$M$7)*$W$11 -> 3.4915776 | O26: 0.7128 | P26: =M26+O26*$W$11 -> 2.7180032 | Q26: =N26+O26*$W$11 -> 4.2043776 | R26: 1.2474 | S26: =M26+R26*$W$11 -> 3.2526032 | T26: =N26+R26*$W$11 -> 4.7389776 | U26: =E26*B26 -> 475.35936
A27: 3/8" | B27: 678 | C27: 17.2 | D27: 1.5 | E27: =(C27-D27)*D27*0.02504 -> 0.589692 | F27: 1 | G27: =CONCATENATE(C27,D27) -> 17,21,5 | H27: 2.59 | I27: 1.2 | J27: 3.39 | K27: =I27+J27 -> 4.59 | M27: =((F27*(1-$M$2)+H27+$M$3)*E27*$M$7)*$W$11 -> 1.8103544 | N27: =((F27*(1-$N$2)+K27+$N$3)*E27*$M$7)*$W$11 -> 2.9897384 | O27: 0.68904 | P27: =M27+O27*$W$11 -> 2.4993944 | Q27: =N27+O27*$W$11 -> 3.6787784 | R27: 1.2474 | S27: =M27+R27*$W$11 -> 3.0577544 | T27: =N27+R27*$W$11 -> 4.2371384 | U27: =E27*B27 -> 399.81118
B28: 678 | C28: 17.2 | D28: 2 | E28: =(C28-D28)*D28*0.02504 -> 0.761216 | F28: 1 | G28: =CONCATENATE(C28,D28) -> 17,22 | H28: 2.32 | I28: 1.47 | J28: 2.97 | K28: =I28+J28 -> 4.44 | M28: =((F28*(1-$M$2)+H28+$M$3)*E28*$M$7)*$W$11 -> 2.1314048 | N28: =((F28*(1-$N$2)+K28+$N$3)*E28*$M$7)*$W$11 -> 3.7451827 | O28: 0.7128 | P28: =M28+O28*$W$11 -> 2.8442048 | Q28: =N28+O28*$W$11 -> 4.4579827 | R28: 1.2474 | S28: =M28+R28*$W$11 -> 3.3788048 | T28: =N28+R28*$W$11 -> 4.9925827 | U28: =E28*B28 -> 516.10445
B29: 678 | C29: 17.2 | D29: 2.5 | E29: =(C29-D29)*D29*0.02504 -> 0.92022 | F29: 1 | G29: =CONCATENATE(C29,D29) -> 17,22,5 | H29: 2.4 | I29: 1.3 | J29: 3.2 | K29: =I29+J29 -> 4.5 | M29: =((F29*(1-$M$2)+H29+$M$3)*E29*$M$7)*$W$11 -> 2.6502336 | N29: =((F29*(1-$N$2)+K29+$N$3)*E29*$M$7)*$W$11 -> 4.5826956 | O29: 0.71 | P29: =M29+O29*$W$11 -> 3.3602336 | Q29: =N29+O29*$W$11 -> 5.2926956 | R29: 1.79 | S29: =M29+R29*$W$11 -> 4.4402336 | T29: =N29+R29*$W$11 -> 6.3726956 | U29: =E29*B29 -> 623.90916
B30: 678 | C30: 18 | D30: 1 | E30: =(C30-D30)*D30*0.02504 -> 0.42568 | F30: 1 | G30: =CONCATENATE(C30,D30) -> 181 | H30: 2.66 | I30: 1.2 | J30: 3.46 | K30: =I30+J30 -> 4.66 | M30: =((F30*(1-$M$2)+H30+$M$3)*E30*$M$7)*$W$11 -> 1.3366352 | O30: 0.68904 | P30: =M30+O30*$W$11 -> 2.0256752 | R30: 1.2474 | S30: =M30+R30*$W$11 -> 2.5840352 | U30: =E30*B30 -> 288.61104
B31: 678 | C31: 18 | D31: 1.2 | E31: =(C31-D31)*D31*0.02504 -> 0.5048064 | F31: 1 | G31: =CONCATENATE(C31,D31) -> 181,2 | H31: 2.63 | I31: 1.2 | J31: 3.43 | K31: =I31+J31 -> 4.63 | M31: =((F31*(1-$M$2)+H31+$M$3)*E31*$M$7)*$W$11 -> 1.5699479 | O31: 0.68904 | P31: =M31+O31*$W$11 -> 2.2589879 | R31: 1.2474 | S31: =M31+R31*$W$11 -> 2.8173479 | U31: =E31*B31 -> 342.25874
B32: 678 | C32: 18 | D32: 1.5 | E32: =(C32-D32)*D32*0.02504 -> 0.61974 | F32: 1 | G32: =CONCATENATE(C32,D32) -> 181,5 | H32: 2.58 | I32: 1.2 | J32: 3.38 | K32: =I32+J32 -> 4.58 | M32: =((F32*(1-$M$2)+H32+$M$3)*E32*$M$7)*$W$11 -> 1.8964044 | N32: =((F32*(1-$N$2)+K32+$N$3)*E32*$M$7)*$W$11 -> 3.1358844 | O32: 0.68904 | P32: =M32+O32*$W$11 -> 2.5854444 | Q32: =N32+O32*$W$11 -> 3.8249244 | R32: 1.2474 | S32: =M32+R32*$W$11 -> 3.1438044 | T32: =N32+R32*$W$11 -> 4.3832844 | U32: =E32*B32 -> 420.18372
B33: 678 | C33: 18 | D33: 2 | E33: =(C33-D33)*D33*0.02504 -> 0.80128 | F33: 1 | G33: =CONCATENATE(C33,D33) -> 182 | H33: 2.31 | I33: 1.47 | J33: 2.96 | K33: =I33+J33 -> 4.43 | M33: =((F33*(1-$M$2)+H33+$M$3)*E33*$M$7)*$W$11 -> 2.2355712 | N33: =((F33*(1-$N$2)+K33+$N$3)*E33*$M$7)*$W$11 -> 3.9342848 | O33: 0.7128 | P33: =M33+O33*$W$11 -> 2.9483712 | Q33: =N33+O33*$W$11 -> 4.6470848 | R33: 1.2474 | S33: =M33+R33*$W$11 -> 3.4829712 | T33: =N33+R33*$W$11 -> 5.1816848 | U33: =E33*B33 -> 543.26784
B34: 678 | C34: 19 | D34: 1 | E34: =(C34-D34)*D34*0.02504 -> 0.45072 | F34: 1 | G34: =CONCATENATE(C34,D34) -> 191 | H34: 2.66 | I34: 1.2 | J34: 3.46 | K34: =I34+J34 -> 4.66 | M34: =((F34*(1-$M$2)+H34+$M$3)*E34*$M$7)*$W$11 -> 1.4152608 | O34: 0.68904 | P34: =M34+O34*$W$11 -> 2.1043008 | R34: 1.2474 | S34: =M34+R34*$W$11 -> 2.6626608 | U34: =E34*B34 -> 305.58816
B35: 678 | C35: 19 | D35: 1.2 | E35: =(C35-D35)*D35*0.02504 -> 0.5348544 | F35: 1 | G35: =CONCATENATE(C35,D35) -> 191,2 | H35: 2.63 | I35: 1.2 | J35: 3.43 | K35: =I35+J35 -> 4.63 | M35: =((F35*(1-$M$2)+H35+$M$3)*E35*$M$7)*$W$11 -> 1.6633972 | O35: 0.68904 | P35: =M35+O35*$W$11 -> 2.3524372 | R35: 1.2474 | S35: =M35+R35*$W$11 -> 2.9107972 | U35: =E35*B35 -> 362.63128
B36: 678 | C36: 19 | D36: 1.5 | E36: =(C36-D36)*D36*0.02504 -> 0.6573 | F36: 1 | G36: =CONCATENATE(C36,D36) -> 191,5 | H36: 2.58 | I36: 1.2 | J36: 3.38 | K36: =I36+J36 -> 4.58 | M36: =((F36*(1-$M$2)+H36+$M$3)*E36*$M$7)*$W$11 -> 2.011338 | N36: =((F36*(1-$N$2)+K36+$N$3)*E36*$M$7)*$W$11 -> 3.325938 | O36: 0.68904 | P36: =M36+O36*$W$11 -> 2.700378 | Q36: =N36+O36*$W$11 -> 4.014978 | R36: 1.2474 | S36: =M36+R36*$W$11 -> 3.258738 | T36: =N36+R36*$W$11 -> 4.573338 | U36: =E36*B36 -> 445.6494
B37: 678 | C37: 20 | D37: 1 | E37: =(C37-D37)*D37*0.02504 -> 0.47576 | F37: 1 | G37: =CONCATENATE(C37,D37) -> 201 | H37: 2.63 | I37: 1.2 | J37: 3.43 | K37: =I37+J37 -> 4.63 | M37: =((F37*(1-$M$2)+H37+$M$3)*E37*$M$7)*$W$11 -> 1.4796136 | O37: 0.68904 | P37: =M37+O37*$W$11 -> 2.1686536 | R37: 1.2474 | S37: =M37+R37*$W$11 -> 2.7270136 | U37: =E37*B37 -> 322.56528
B38: 678 | C38: 20 | D38: 1.2 | E38: =(C38-D38)*D38*0.02504 -> 0.5649024 | F38: 1 | G38: =CONCATENATE(C38,D38) -> 201,2 | H38: 2.61 | I38: 1.2 | J38: 3.41 | K38: =I38+J38 -> 4.61 | M38: =((F38*(1-$M$2)+H38+$M$3)*E38*$M$7)*$W$11 -> 1.7455484 | O38: 0.68904 | P38: =M38+O38*$W$11 -> 2.4345884 | R38: 1.2474 | S38: =M38+R38*$W$11 -> 2.9929484 | U38: =E38*B38 -> 383.00383
B39: 678 | C39: 20 | D39: 1.5 | E39: =(C39-D39)*D39*0.02504 -> 0.69486 | F39: 1 | G39: =CONCATENATE(C39,D39) -> 201,5 | H39: 2.56 | I39: 1.2 | J39: 3.36 | K39: =I39+J39 -> 4.56 | M39: =((F39*(1-$M$2)+H39+$M$3)*E39*$M$7)*$W$11 -> 2.1123744 | N39: =((F39*(1-$N$2)+K39+$N$3)*E39*$M$7)*$W$11 -> 3.5020944 | O39: 0.68904 | P39: =M39+O39*$W$11 -> 2.8014144 | Q39: =N39+O39*$W$11 -> 4.1911344 | R39: 1.2474 | S39: =M39+R39*$W$11 -> 3.3597744 | T39: =N39+R39*$W$11 -> 4.7494944 | U39: =E39*B39 -> 471.11508
B40: 678 | C40: 20 | D40: 2 | E40: =(C40-D40)*D40*0.02504 -> 0.90144 | F40: 1 | G40: =CONCATENATE(C40,D40) -> 202 | H40: 2.29 | I40: 1.47 | J40: 2.94 | K40: =I40+J40 -> 4.41 | M40: =((F40*(1-$M$2)+H40+$M$3)*E40*$M$7)*$W$11 -> 2.4969888 | N40: =((F40*(1-$N$2)+K40+$N$3)*E40*$M$7)*$W$11 -> 4.4080416 | O40: 0.7128 | P40: =M40+O40*$W$11 -> 3.2097888 | Q40: =N40+O40*$W$11 -> 5.1208416 | R40: 1.2474 | S40: =M40+R40*$W$11 -> 3.7443888 | T40: =N40+R40*$W$11 -> 5.6554416 | U40: =E40*B40 -> 611.17632
B41: 678 | C41: 20 | D41: 2.5 | E41: =(C41-D41)*D41*0.02504 -> 1.0955 | F41: 1 | G41: =CONCATENATE(C41,D41) -> 202,5 | H41: 2.35 | I41: 1.3 | J41: 3.15 | K41: =I41+J41 -> 4.45 | M41: =((F41*(1-$M$2)+H41+$M$3)*E41*$M$7)*$W$11 -> 3.100265 | O41: 0.9 | P41: =M41+O41*$W$11 -> 4.000265 | R41: 1.79 | S41: =M41+R41*$W$11 -> 4.890265 | U41: =E41*B41 -> 742.749
B42: 678 | C42: 20 | D42: 3 | E42: =(C42-D42)*D42*0.02504 -> 1.27704 | F42: 1 | G42: =CONCATENATE(C42,D42) -> 203 | H42: 2.4 | I42: 1.2 | J42: 3.2 | K42: =I42+J42 -> 4.4 | M42: =((F42*(1-$M$2)+H42+$M$3)*E42*$M$7)*$W$11 -> 3.6778752 | O42: 0.9 | P42: =M42+O42*$W$11 -> 4.5778752 | R42: 1.79 | S42: =M42+R42*$W$11 -> 5.4678752 | U42: =E42*B42 -> 865.83312
A43: 1/2" | B43: 678 | C43: 21.3 | D43: 1.5 | E43: =(C43-D43)*D43*0.02504 -> 0.743688 | F43: 1 | G43: =CONCATENATE(C43,D43) -> 21,31,5 | H43: 2.54 | I43: 1.2 | J43: 3.34 | K43: =I43+J43 -> 4.54 | M43: =((F43*(1-$M$2)+H43+$M$3)*E43*$M$7)*$W$11 -> 2.2459378 | N43: =((F43*(1-$N$2)+K43+$N$3)*E43*$M$7)*$W$11 -> 3.7333138 | O43: 0.68904 | P43: =M43+O43*$W$11 -> 2.9349778 | Q43: =N43+O43*$W$11 -> 4.4223538 | R43: 1.2474 | S43: =M43+R43*$W$11 -> 3.4933378 | T43: =N43+R43*$W$11 -> 4.9807138 | U43: =E43*B43 -> 504.22046
B44: 678 | C44: 21.3 | D44: 2 | E44: =(C44-D44)*D44*0.02504 -> 0.966544 | F44: 1 | G44: =CONCATENATE(C44,D44) -> 21,32 | H44: 2.28 | I44: 1.47 | J44: 2.93 | K44: =I44+J44 -> 4.4 | M44: =((F44*(1-$M$2)+H44+$M$3)*E44*$M$7)*$W$11 -> 2.6676614 | N44: =((F44*(1-$N$2)+K44+$N$3)*E44*$M$7)*$W$11 -> 4.7167347 | O44: 0.73656 | P44: =M44+O44*$W$11 -> 3.4042214 | Q44: =N44+O44*$W$11 -> 5.4532947 | R44: 1.2474 | S44: =M44+R44*$W$11 -> 3.9150614 | T44: =N44+R44*$W$11 -> 5.9641347 | U44: =E44*B44 -> 655.31683
B45: 678 | C45: 21.3 | D45: 2.5 | E45: =(C45-D45)*D45*0.02504 -> 1.17688 | F45: 1 | G45: =CONCATENATE(C45,D45) -> 21,32,5 | H45: 2.28 | I45: 1.3 | J45: 2.88 | K45: =I45+J45 -> 4.18 | M45: =((F45*(1-$M$2)+H45+$M$3)*E45*$M$7)*$W$11 -> 3.2481888 | N45: =((F45*(1-$N$2)+K45+$N$3)*E45*$M$7)*$W$11 -> 5.4842608 | O45: 0.85536 | P45: =M45+O45*$W$11 -> 4.1035488 | Q45: =N45+O45*$W$11 -> 6.3396208 | R45: 1.7226 | S45: =M45+R45*$W$11 -> 4.9707888 | T45: =N45+R45*$W$11 -> 7.2068608 | U45: =E45*B45 -> 797.92464
B46: 678 | C46: 21.3 | D46: 3 | E46: =(C46-D46)*D46*0.02504 -> 1.374696 | F46: 1 | G46: =CONCATENATE(C46,D46) -> 21,33 | H46: 2.33 | I46: 1.2 | J46: 3.03 | K46: =I46+J46 -> 4.23 | M46: =((F46*(1-$M$2)+H46+$M$3)*E46*$M$7)*$W$11 -> 3.8628958 | O46: 0.90288 | P46: =M46+O46*$W$11 -> 4.7657758 | R46: 1.79388 | S46: =M46+R46*$W$11 -> 5.6567758 | U46: =E46*B46 -> 932.04389
B47: 678 | C47: 22 | D47: 1 | E47: =(C47-D47)*D47*0.02504 -> 0.52584 | F47: 1 | G47: =CONCATENATE(C47,D47) -> 221 | H47: 2.61 | I47: 1.2 | J47: 3.41 | K47: =I47+J47 -> 4.61 | M47: =((F47*(1-$M$2)+H47+$M$3)*E47*$M$7)*$W$11 -> 1.6248456 | O47: 0.68904 | P47: =M47+O47*$W$11 -> 2.3138856 | R47: 1.2474 | S47: =M47+R47*$W$11 -> 2.8722456 | U47: =E47*B47 -> 356.51952
B48: 678 | C48: 22 | D48: 1.2 | E48: =(C48-D48)*D48*0.02504 -> 0.6249984 | F48: 1 | G48: =CONCATENATE(C48,D48) -> 221,2 | H48: 2.59 | I48: 1.2 | J48: 3.39 | K48: =I48+J48 -> 4.59 | M48: =((F48*(1-$M$2)+H48+$M$3)*E48*$M$7)*$W$11 -> 1.9187451 | O48: 0.68904 | P48: =M48+O48*$W$11 -> 2.6077851 | R48: 1.2474 | S48: =M48+R48*$W$11 -> 3.1661451 | U48: =E48*B48 -> 423.74892
B49: 678 | C49: 22 | D49: 1.5 | E49: =(C49-D49)*D49*0.02504 -> 0.76998 | F49: 1 | G49: =CONCATENATE(C49,D49) -> 221,5 | H49: 2.54 | I49: 1.2 | J49: 3.34 | K49: =I49+J49 -> 4.54 | M49: =((F49*(1-$M$2)+H49+$M$3)*E49*$M$7)*$W$11 -> 2.3253396 | N49: =((F49*(1-$N$2)+K49+$N$3)*E49*$M$7)*$W$11 -> 3.8652996 | O49: 0.68904 | P49: =M49+O49*$W$11 -> 3.0143796 | Q49: =N49+O49*$W$11 -> 4.5543396 | R49: 1.2474 | S49: =M49+R49*$W$11 -> 3.5727396 | T49: =N49+R49*$W$11 -> 5.1126996 | U49: =E49*B49 -> 522.04644
B50: 678 | C50: 22 | D50: 2 | E50: =(C50-D50)*D50*0.02504 -> 1.0016 | F50: 1 | G50: =CONCATENATE(C50,D50) -> 222 | H50: 2.27 | I50: 1.47 | J50: 2.92 | K50: =I50+J50 -> 4.39 | M50: =((F50*(1-$M$2)+H50+$M$3)*E50*$M$7)*$W$11 -> 2.7544 | N50: =((F50*(1-$N$2)+K50+$N$3)*E50*$M$7)*$W$11 -> 4.877792 | O50: 0.74844 | P50: =M50+O50*$W$11 -> 3.50284 | Q50: =N50+O50*$W$11 -> 5.626232 | R50: 1.2474 | S50: =M50+R50*$W$11 -> 4.0018 | T50: =N50+R50*$W$11 -> 6.125192 | U50: =E50*B50 -> 679.0848
B51: 678 | C51: 23 | D51: 1.5 | E51: =(C51-D51)*D51*0.02504 -> 0.80754 | F51: 1 | G51: =CONCATENATE(C51,D51) -> 231,5 | H51: 2.6 | I51: 1.2 | J51: 3.4 | K51: =I51+J51 -> 4.6 | M51: =((F51*(1-$M$2)+H51+$M$3)*E51*$M$7)*$W$11 -> 2.4872232 | N51: =((F51*(1-$N$2)+K51+$N$3)*E51*$M$7)*$W$11 -> 4.1023032 | O51: 0.71 | P51: =M51+O51*$W$11 -> 3.1972232 | Q51: =N51+O51*$W$11 -> 4.8123032 | R51: 1.25 | S51: =M51+R51*$W$11 -> 3.7372232 | T51: =N51+R51*$W$11 -> 5.3523032 | U51: =E51*B51 -> 547.51212
B52: 678 | C52: 23 | D52: 2 | E52: =(C52-D52)*D52*0.02504 -> 1.05168 | F52: 1 | G52: =CONCATENATE(C52,D52) -> 232 | H52: 2.45 | I52: 1.47 | J52: 3.25 | K52: =I52+J52 -> 4.72 | M52: =((F52*(1-$M$2)+H52+$M$3)*E52*$M$7)*$W$11 -> 3.0814224 | N52: =((F52*(1-$N$2)+K52+$N$3)*E52*$M$7)*$W$11 -> 5.468736 | O52: 0.82 | P52: =M52+O52*$W$11 -> 3.9014224 | R52: 1.25 | S52: =M52+R52*$W$11 -> 4.3314224 | U52: =E52*B52 -> 713.03904
B53: 678 | C53: 25 | D53: 1 | E53: =(C53-D53)*D53*0.02504 -> 0.60096 | F53: 1 | G53: =CONCATENATE(C53,D53) -> 251 | H53: 2.61 | I53: 1.2 | J53: 3.41 | K53: =I53+J53 -> 4.61 | M53: =((F53*(1-$M$2)+H53+$M$3)*E53*$M$7)*$W$11 -> 1.8569664 | O53: 0.7128 | P53: =M53+O53*$W$11 -> 2.5697664 | R53: 1.2474 | S53: =M53+R53*$W$11 -> 3.1043664 | U53: =E53*B53 -> 407.45088
B54: 678 | C54: 25 | D54: 1.2 | E54: =(C54-D54)*D54*0.02504 -> 0.7151424 | F54: 1 | G54: =CONCATENATE(C54,D54) -> 251,2 | H54: 2.59 | I54: 1.2 | J54: 3.39 | K54: =I54+J54 -> 4.59 | M54: =((F54*(1-$M$2)+H54+$M$3)*E54*$M$7)*$W$11 -> 2.1954872 | O54: 0.7128 | P54: =M54+O54*$W$11 -> 2.9082872 | R54: 1.2474 | S54: =M54+R54*$W$11 -> 3.4428872 | U54: =E54*B54 -> 484.86655
B55: 678 | C55: 25 | D55: 1.5 | E55: =(C55-D55)*D55*0.02504 -> 0.88266 | F55: 1 | G55: =CONCATENATE(C55,D55) -> 251,5 | H55: 2.54 | I55: 1.2 | J55: 3.34 | K55: =I55+J55 -> 4.54 | M55: =((F55*(1-$M$2)+H55+$M$3)*E55*$M$7)*$W$11 -> 2.6656332 | N55: =((F55*(1-$N$2)+K55+$N$3)*E55*$M$7)*$W$11 -> 4.4309532 | O55: 0.7128 | P55: =M55+O55*$W$11 -> 3.3784332 | Q55: =N55+O55*$W$11 -> 5.1437532 | R55: 1.2474 | S55: =M55+R55*$W$11 -> 3.9130332 | T55: =N55+R55*$W$11 -> 5.6783532 | U55: =E55*B55 -> 598.44348
B56: 678 | C56: 25 | D56: 2 | E56: =(C56-D56)*D56*0.02504 -> 1.15184 | F56: 1 | G56: =CONCATENATE(C56,D56) -> 252 | H56: 2.27 | I56: 1.47 | J56: 2.92 | K56: =I56+J56 -> 4.39 | M56: =((F56*(1-$M$2)+H56+$M$3)*E56*$M$7)*$W$11 -> 3.16756 | N56: =((F56*(1-$N$2)+K56+$N$3)*E56*$M$7)*$W$11 -> 5.6094608 | O56: 0.81972 | P56: =M56+O56*$W$11 -> 3.98728 | Q56: =N56+O56*$W$11 -> 6.4291808 | R56: 1.2474 | S56: =M56+R56*$W$11 -> 4.41496 | T56: =N56+R56*$W$11 -> 6.8568608 | U56: =E56*B56 -> 780.94752
B57: 474 | C57: 25 | D57: 2.5 | E57: =(C57-D57)*D57*0.02504 -> 1.4085 | F57: 1 | G57: =CONCATENATE(C57,D57) -> 252,5 | H57: 2.28 | I57: 1.3 | J57: 2.88 | K57: =I57+J57 -> 4.18 | M57: =((F57*(1-$M$2)+H57+$M$3)*E57*$M$7)*$W$11 -> 3.88746 | N57: =((F57*(1-$N$2)+K57+$N$3)*E57*$M$7)*$W$11 -> 6.56361 | O57: 0.93852 | P57: =M57+O57*$W$11 -> 4.82598 | Q57: =N57+O57*$W$11 -> 7.50213 | R57: 1.7226 | S57: =M57+R57*$W$11 -> 5.61006 | T57: =N57+R57*$W$11 -> 8.28621 | U57: =E57*B57 -> 667.629
B58: 474 | C58: 25 | D58: 3 | E58: =(C58-D58)*D58*0.02504 -> 1.65264 | F58: 1 | G58: =CONCATENATE(C58,D58) -> 253 | H58: 2.33 | I58: 1.2 | J58: 3.03 | K58: =I58+J58 -> 4.23 | M58: =((F58*(1-$M$2)+H58+$M$3)*E58*$M$7)*$W$11 -> 4.6439184 | O58: 1.05732 | P58: =M58+O58*$W$11 -> 5.7012384 | R58: 1.99584 | S58: =M58+R58*$W$11 -> 6.6397584 | U58: =E58*B58 -> 783.35136
B59: 678 | C59: 25.4 | D59: 1.5 | E59: =(C59-D59)*D59*0.02504 -> 0.897684 | F59: 1 | G59: =CONCATENATE(C59,D59) -> 25,41,5 | H59: 2.54 | I59: 1.2 | J59: 3.34 | K59: =I59+J59 -> 4.54 | M59: =((F59*(1-$M$2)+H59+$M$3)*E59*$M$7)*$W$11 -> 2.7110057 | N59: =((F59*(1-$N$2)+K59+$N$3)*E59*$M$7)*$W$11 -> 4.5063737 | O59: 0.72468 | P59: =M59+O59*$W$11 -> 3.4356857 | R59: 1.2474 | S59: =M59+R59*$W$11 -> 3.9584057 | U59: =E59*B59 -> 608.62975
A60: 3/4" | B60: 678 | C60: 26.9 | D60: 1.5 | E60: =(C60-D60)*D60*0.02504 -> 0.954024 | F60: 1 | G60: =CONCATENATE(C60,D60) -> 26,91,5 | H60: 2.54 | I60: 1.2 | J60: 3.34 | K60: =I60+J60 -> 4.54 | M60: =((F60*(1-$M$2)+H60+$M$3)*E60*$M$7)*$W$11 -> 2.8811525 | N60: =((F60*(1-$N$2)+K60+$N$3)*E60*$M$7)*$W$11 -> 4.7892005 | O60: 0.68904 | P60: =M60+O60*$W$11 -> 3.5701925 | Q60: =N60+O60*$W$11 -> 5.4782405 | R60: 1.2474 | S60: =M60+R60*$W$11 -> 4.1285525 | T60: =N60+R60*$W$11 -> 6.0366005 | U60: =E60*B60 -> 646.82827
B61: 678 | C61: 26.9 | D61: 2 | E61: =(C61-D61)*D61*0.02504 -> 1.246992 | F61: 1 | G61: =CONCATENATE(C61,D61) -> 26,92 | H61: 2.24 | I61: 1.47 | J61: 2.89 | K61: =I61+J61 -> 4.36 | M61: =((F61*(1-$M$2)+H61+$M$3)*E61*$M$7)*$W$11 -> 3.3918182 | N61: =((F61*(1-$N$2)+K61+$N$3)*E61*$M$7)*$W$11 -> 6.0354413 | O61: 0.79596 | P61: =M61+O61*$W$11 -> 4.1877782 | Q61: =N61+O61*$W$11 -> 6.8314013 | R61: 1.2474 | S61: =M61+R61*$W$11 -> 4.6392182 | T61: =N61+R61*$W$11 -> 7.2828413 | U61: =E61*B61 -> 845.46058
B62: 366 | C62: 26.9 | D62: 2.5 | E62: =(C62-D62)*D62*0.02504 -> 1.52744 | F62: 1 | G62: =CONCATENATE(C62,D62) -> 26,92,5 | H62: 2.26 | I62: 1.3 | J62: 2.86 | K62: =I62+J62 -> 4.16 | M62: =((F62*(1-$M$2)+H62+$M$3)*E62*$M$7)*$W$11 -> 4.1851856 | N62: =((F62*(1-$N$2)+K62+$N$3)*E62*$M$7)*$W$11 -> 7.0873216 | O62: 0.92664 | P62: =M62+O62*$W$11 -> 5.1118256 | Q62: =N62+O62*$W$11 -> 8.0139616 | R62: 1.7226 | S62: =M62+R62*$W$11 -> 5.9077856 | T62: =N62+R62*$W$11 -> 8.8099216 | U62: =E62*B62 -> 559.04304
B63: 366 | C63: 26.9 | D63: 3 | E63: =(C63-D63)*D63*0.02504 -> 1.795368 | F63: 1 | G63: =CONCATENATE(C63,D63) -> 26,93 | H63: 2.32 | I63: 1.2 | J63: 3.02 | K63: =I63+J63 -> 4.22 | M63: =((F63*(1-$M$2)+H63+$M$3)*E63*$M$7)*$W$11 -> 5.0270304 | O63: 1.0692 | P63: =M63+O63*$W$11 -> 6.0962304 | R63: 2.04336 | S63: =M63+R63*$W$11 -> 7.0703904 | U63: =E63*B63 -> 657.10469
B64: 366 | C64: 28 | D64: 1 | E64: =(C64-D64)*D64*0.02504 -> 0.67608 | F64: 1 | G64: =CONCATENATE(C64,D64) -> 281 | H64: 2.6 | I64: 1.2 | J64: 3.4 | K64: =I64+J64 -> 4.6 | M64: =((F64*(1-$M$2)+H64+$M$3)*E64*$M$7)*$W$11 -> 2.0823264 | O64: 0.7128 | P64: =M64+O64*$W$11 -> 2.7951264 | R64: 1.2474 | S64: =M64+R64*$W$11 -> 3.3297264 | U64: =E64*B64 -> 247.44528
B65: 366 | C65: 28 | D65: 1.2 | E65: =(C65-D65)*D65*0.02504 -> 0.8052864 | F65: 1 | G65: =CONCATENATE(C65,D65) -> 281,2 | H65: 2.58 | I65: 1.2 | J65: 3.38 | K65: =I65+J65 -> 4.58 | M65: =((F65*(1-$M$2)+H65+$M$3)*E65*$M$7)*$W$11 -> 2.4641764 | O65: 0.7128 | P65: =M65+O65*$W$11 -> 3.1769764 | R65: 1.2474 | S65: =M65+R65*$W$11 -> 3.7115764 | U65: =E65*B65 -> 294.73482
B66: 366 | C66: 28 | D66: 1.5 | E66: =(C66-D66)*D66*0.02504 -> 0.99534 | F66: 1 | G66: =CONCATENATE(C66,D66) -> 281,5 | H66: 2.53 | I66: 1.2 | J66: 3.33 | K66: =I66+J66 -> 4.53 | M66: =((F66*(1-$M$2)+H66+$M$3)*E66*$M$7)*$W$11 -> 2.9959734 | N66: =((F66*(1-$N$2)+K66+$N$3)*E66*$M$7)*$W$11 -> 4.9866534 | O66: 0.7128 | P66: =M66+O66*$W$11 -> 3.7087734 | Q66: =N66+O66*$W$11 -> 5.6994534 | R66: 1.2474 | S66: =M66+R66*$W$11 -> 4.2433734 | T66: =N66+R66*$W$11 -> 6.2340534 | U66: =E66*B66 -> 364.29444
B67: 366 | C67: 28 | D67: 2 | E67: =(C67-D67)*D67*0.02504 -> 1.30208 | F67: 1 | G67: =CONCATENATE(C67,D67) -> 282 | H67: 2.26 | I67: 1.47 | J67: 2.91 | K67: =I67+J67 -> 4.38 | M67: =((F67*(1-$M$2)+H67+$M$3)*E67*$M$7)*$W$11 -> 3.5676992 | N67: =((F67*(1-$N$2)+K67+$N$3)*E67*$M$7)*$W$11 -> 6.3281088 | O67: 0.80784 | P67: =M67+O67*$W$11 -> 4.3755392 | Q67: =N67+O67*$W$11 -> 7.1359488 | R67: 1.2474 | S67: =M67+R67*$W$11 -> 4.8150992 | T67: =N67+R67*$W$11 -> 7.5755088 | U67: =E67*B67 -> 476.56128
B68: 366 | C68: 30 | D68: 1 | E68: =(C68-D68)*D68*0.02504 -> 0.72616 | F68: 1 | G68: =CONCATENATE(C68,D68) -> 301 | H68: 2.59 | I68: 1.2 | J68: 3.39 | K68: =I68+J68 -> 4.59 | M68: =((F68*(1-$M$2)+H68+$M$3)*E68*$M$7)*$W$11 -> 2.2293112 | O68: 0.73656 | P68: =M68+O68*$W$11 -> 2.9658712 | R68: 1.2474 | S68: =M68+R68*$W$11 -> 3.4767112 | U68: =E68*B68 -> 265.77456
B69: 366 | C69: 30 | D69: 1.2 | E69: =(C69-D69)*D69*0.02504 -> 0.8653824 | F69: 1 | G69: =CONCATENATE(C69,D69) -> 301,2 | H69: 2.57 | I69: 1.2 | J69: 3.37 | K69: =I69+J69 -> 4.57 | M69: =((F69*(1-$M$2)+H69+$M$3)*E69*$M$7)*$W$11 -> 2.6394163 | O69: 0.73656 | P69: =M69+O69*$W$11 -> 3.3759763 | R69: 1.2474 | S69: =M69+R69*$W$11 -> 3.8868163 | U69: =E69*B69 -> 316.72996
B70: 366 | C70: 30 | D70: 1.5 | E70: =(C70-D70)*D70*0.02504 -> 1.07046 | F70: 1 | G70: =CONCATENATE(C70,D70) -> 301,5 | H70: 2.51 | I70: 1.2 | J70: 3.31 | K70: =I70+J70 -> 4.51 | M70: =((F70*(1-$M$2)+H70+$M$3)*E70*$M$7)*$W$11 -> 3.2006754 | N70: =((F70*(1-$N$2)+K70+$N$3)*E70*$M$7)*$W$11 -> 5.3415954 | O70: 0.73656 | P70: =M70+O70*$W$11 -> 3.9372354 | Q70: =N70+O70*$W$11 -> 6.0781554 | R70: 1.2474 | S70: =M70+R70*$W$11 -> 4.4480754 | T70: =N70+R70*$W$11 -> 6.5889954 | U70: =E70*B70 -> 391.78836
B71: 366 | C71: 30 | D71: 2 | E71: =(C71-D71)*D71*0.02504 -> 1.40224 | F71: 1 | G71: =CONCATENATE(C71,D71) -> 302 | H71: 2.24 | I71: 1.47 | J71: 2.89 | K71: =I71+J71 -> 4.36 | M71: =((F71*(1-$M$2)+H71+$M$3)*E71*$M$7)*$W$11 -> 3.8140928 | N71: =((F71*(1-$N$2)+K71+$N$3)*E71*$M$7)*$W$11 -> 6.7868416 | O71: 0.8316 | P71: =M71+O71*$W$11 -> 4.6456928 | Q71: =N71+O71*$W$11 -> 7.6184416 | R71: 1.2474 | S71: =M71+R71*$W$11 -> 5.0614928 | T71: =N71+R71*$W$11 -> 8.0342416 | U71: =E71*B71 -> 513.21984
B72: 366 | C72: 30 | D72: 2.5 | E72: =(C72-D72)*D72*0.02504 -> 1.7215 | F72: 1 | G72: =CONCATENATE(C72,D72) -> 302,5 | H72: 2.26 | I72: 1.3 | J72: 2.86 | K72: =I72+J72 -> 4.16 | M72: =((F72*(1-$M$2)+H72+$M$3)*E72*$M$7)*$W$11 -> 4.71691 | N72: =((F72*(1-$N$2)+K72+$N$3)*E72*$M$7)*$W$11 -> 7.98776 | O72: 1.03356 | P72: =M72+O72*$W$11 -> 5.75047 | Q72: =N72+O72*$W$11 -> 9.02132 | R72: 1.88892 | S72: =M72+R72*$W$11 -> 6.60583 | T72: =N72+R72*$W$11 -> 9.87668 | U72: =E72*B72 -> 630.069
B73: 366 | C73: 30 | D73: 3 | E73: =(C73-D73)*D73*0.02504 -> 2.02824 | F73: 1 | G73: =CONCATENATE(C73,D73) -> 303 | H73: 2.34 | I73: 1.2 | J73: 3.04 | K73: =I73+J73 -> 4.24 | M73: =((F73*(1-$M$2)+H73+$M$3)*E73*$M$7)*$W$11 -> 5.7196368 | O73: 1.03356 | P73: =M73+O73*$W$11 -> 6.7531968 | R73: 1.98396 | S73: =M73+R73*$W$11 -> 7.7035968 | U73: =E73*B73 -> 742.33584
B74: 366 | C74: 32 | D74: 1 | E74: =(C74-D74)*D74*0.02504 -> 0.77624 | F74: 1 | G74: =CONCATENATE(C74,D74) -> 321 | H74: 2.57 | I74: 1.2 | J74: 3.37 | K74: =I74+J74 -> 4.57 | M74: =((F74*(1-$M$2)+H74+$M$3)*E74*$M$7)*$W$11 -> 2.367532 | O74: 0.78408 | P74: =M74+O74*$W$11 -> 3.151612 | R74: 1.33056 | S74: =M74+R74*$W$11 -> 3.698092 | U74: =E74*B74 -> 284.10384
B75: 366 | C75: 32 | D75: 1.2 | E75: =(C75-D75)*D75*0.02504 -> 0.9254784 | F75: 1 | G75: =CONCATENATE(C75,D75) -> 321,2 | H75: 2.54 | I75: 1.2 | J75: 3.34 | K75: =I75+J75 -> 4.54 | M75: =((F75*(1-$M$2)+H75+$M$3)*E75*$M$7)*$W$11 -> 2.7949448 | O75: 0.78408 | P75: =M75+O75*$W$11 -> 3.5790248 | R75: 1.33056 | S75: =M75+R75*$W$11 -> 4.1255048 | U75: =E75*B75 -> 338.72509
B76: 366 | C76: 32 | D76: 1.5 | E76: =(C76-D76)*D76*0.02504 -> 1.14558 | F76: 1 | G76: =CONCATENATE(C76,D76) -> 321,5 | H76: 2.49 | I76: 1.2 | J76: 3.29 | K76: =I76+J76 -> 4.49 | M76: =((F76*(1-$M$2)+H76+$M$3)*E76*$M$7)*$W$11 -> 3.4023726 | N76: =((F76*(1-$N$2)+K76+$N$3)*E76*$M$7)*$W$11 -> 5.6935326 | O76: 0.78408 | P76: =M76+O76*$W$11 -> 4.1864526 | Q76: =N76+O76*$W$11 -> 6.4776126 | R76: 1.33056 | S76: =M76+R76*$W$11 -> 4.7329326 | T76: =N76+R76*$W$11 -> 7.0240926 | U76: =E76*B76 -> 419.28228
B77: 366 | C77: 32 | D77: 2 | E77: =(C77-D77)*D77*0.02504 -> 1.5024 | F77: 1 | G77: =CONCATENATE(C77,D77) -> 322 | H77: 2.22 | I77: 1.47 | J77: 2.87 | K77: =I77+J77 -> 4.34 | M77: =((F77*(1-$M$2)+H77+$M$3)*E77*$M$7)*$W$11 -> 4.05648 | N77: =((F77*(1-$N$2)+K77+$N$3)*E77*$M$7)*$W$11 -> 7.241568 | O77: 0.85536 | P77: =M77+O77*$W$11 -> 4.91184 | Q77: =N77+O77*$W$11 -> 8.096928 | R77: 1.33056 | S77: =M77+R77*$W$11 -> 5.38704 | T77: =N77+R77*$W$11 -> 8.572128 | U77: =E77*B77 -> 549.8784
B78: 366 | C78: 32 | D78: 2.5 | E78: =(C78-D78)*D78*0.02504 -> 1.8467 | F78: 1 | G78: =CONCATENATE(C78,D78) -> 322,5 | H78: 2.24 | I78: 1.3 | J78: 2.84 | K78: =I78+J78 -> 4.14 | M78: =((F78*(1-$M$2)+H78+$M$3)*E78*$M$7)*$W$11 -> 5.023024 | N78: =((F78*(1-$N$2)+K78+$N$3)*E78*$M$7)*$W$11 -> 8.531754 | O78: 0.99792 | P78: =M78+O78*$W$11 -> 6.020944 | Q78: =N78+O78*$W$11 -> 9.529674 | R78: 1.8414 | S78: =M78+R78*$W$11 -> 6.864424 | T78: =N78+R78*$W$11 -> 10.373154 | U78: =E78*B78 -> 675.8922
B79: 366 | C79: 32 | D79: 3 | E79: =(C79-D79)*D79*0.02504 -> 2.17848 | F79: 1 | G79: =CONCATENATE(C79,D79) -> 323 | H79: 2.3 | I79: 1.2 | J79: 3 | K79: =I79+J79 -> 4.2 | M79: =((F79*(1-$M$2)+H79+$M$3)*E79*$M$7)*$W$11 -> 6.0561744 | O79: 1.21176 | P79: =M79+O79*$W$11 -> 7.2679344 | R79: 2.30472 | S79: =M79+R79*$W$11 -> 8.3608944 | U79: =E79*B79 -> 797.32368
A80: 1" | B80: 366 | C80: 33.7 | D80: 1.2 | E80: =(C80-D80)*D80*0.02504 -> 0.97656 | F80: 1 | G80: =CONCATENATE(C80,D80) -> 33,71,2 | H80: 2.53 | I80: 1.2 | J80: 3.33 | K80: =I80+J80 -> 4.53 | M80: =((F80*(1-$M$2)+H80+$M$3)*E80*$M$7)*$W$11 -> 2.9394456 | O80: 0.8316 | P80: =M80+O80*$W$11 -> 3.7710456 | R80: 1.40184 | S80: =M80+R80*$W$11 -> 4.3412856 | U80: =E80*B80 -> 357.42096
B81: 366 | C81: 33.7 | D81: 1.5 | E81: =(C81-D81)*D81*0.02504 -> 1.209432 | F81: 1 | G81: =CONCATENATE(C81,D81) -> 33,71,5 | H81: 2.47 | I81: 1.2 | J81: 3.27 | K81: =I81+J81 -> 4.47 | M81: =((F81*(1-$M$2)+H81+$M$3)*E81*$M$7)*$W$11 -> 3.5678244 | N81: =((F81*(1-$N$2)+K81+$N$3)*E81*$M$7)*$W$11 -> 5.9866884 | O81: 0.8316 | P81: =M81+O81*$W$11 -> 4.3994244 | Q81: =N81+O81*$W$11 -> 6.8182884 | R81: 1.40184 | S81: =M81+R81*$W$11 -> 4.9696644 | T81: =N81+R81*$W$11 -> 7.3885284 | U81: =E81*B81 -> 442.65211
B82: 366 | C82: 33.7 | D82: 2 | E82: =(C82-D82)*D82*0.02504 -> 1.587536 | F82: 1 | G82: =CONCATENATE(C82,D82) -> 33,72 | H82: 2.21 | I82: 1.47 | J82: 2.859 | K82: =I82+J82 -> 4.329 | M82: =((F82*(1-$M$2)+H82+$M$3)*E82*$M$7)*$W$11 -> 4.2704718 | N82: =((F82*(1-$N$2)+K82+$N$3)*E82*$M$7)*$W$11 -> 7.6344606 | O82: 0.86724 | P82: =M82+O82*$W$11 -> 5.1377118 | Q82: =N82+O82*$W$11 -> 8.5017006 | R82: 1.40184 | S82: =M82+R82*$W$11 -> 5.6723118 | T82: =N82+R82*$W$11 -> 9.0363006 | U82: =E82*B82 -> 581.03818
B83: 366 | C83: 33.7 | D83: 2.5 | E83: =(C83-D83)*D83*0.02504 -> 1.95312 | F83: 1 | G83: =CONCATENATE(C83,D83) -> 33,72,5 | H83: 2.17 | I83: 1.3 | J83: 2.774 | K83: =I83+J83 -> 4.074 | M83: =((F83*(1-$M$2)+H83+$M$3)*E83*$M$7)*$W$11 -> 5.175768 | N83: =((F83*(1-$N$2)+K83+$N$3)*E83*$M$7)*$W$11 -> 8.8945085 | O83: 0.93852 | P83: =M83+O83*$W$11 -> 6.114288 | Q83: =N83+O83*$W$11 -> 9.8330285 | R83: 1.93644 | S83: =M83+R83*$W$11 -> 7.112208 | T83: =N83+R83*$W$11 -> 10.830948 | U83: =E83*B83 -> 714.84192
B84: 366 | C84: 33.7 | D84: 3 | E84: =(C84-D84)*D84*0.02504 -> 2.306184 | F84: 1 | G84: =CONCATENATE(C84,D84) -> 33,73 | H84: 2.22 | I84: 1.2 | J84: 2.92 | K84: =I84+J84 -> 4.12 | M84: =((F84*(1-$M$2)+H84+$M$3)*E84*$M$7)*$W$11 -> 6.2266968 | O84: 0.97416 | P84: =M84+O84*$W$11 -> 7.2008568 | R84: 2.0196 | S84: =M84+R84*$W$11 -> 8.2462968 | U84: =E84*B84 -> 844.06334
B85: 366 | C85: 35 | D85: 1 | E85: =(C85-D85)*D85*0.02504 -> 0.85136 | F85: 1 | G85: =CONCATENATE(C85,D85) -> 351 | H85: 2.57 | I85: 1.2 | J85: 3.37 | K85: =I85+J85 -> 4.57 | M85: =((F85*(1-$M$2)+H85+$M$3)*E85*$M$7)*$W$11 -> 2.596648 | O85: 0.85536 | P85: =M85+O85*$W$11 -> 3.452008 | R85: 1.44936 | S85: =M85+R85*$W$11 -> 4.046008 | U85: =E85*B85 -> 311.59776
B86: 366 | C86: 35 | D86: 1.2 | E86: =(C86-D86)*D86*0.02504 -> 1.0156224 | F86: 1 | G86: =CONCATENATE(C86,D86) -> 351,2 | H86: 2.55 | I86: 1.2 | J86: 3.35 | K86: =I86+J86 -> 4.55 | M86: =((F86*(1-$M$2)+H86+$M$3)*E86*$M$7)*$W$11 -> 3.0773359 | O86: 0.85536 | P86: =M86+O86*$W$11 -> 3.9326959 | R86: 1.44936 | S86: =M86+R86*$W$11 -> 4.5266959 | U86: =E86*B86 -> 371.7178
B87: 366 | C87: 35 | D87: 1.5 | E87: =(C87-D87)*D87*0.02504 -> 1.25826 | F87: 1 | G87: =CONCATENATE(C87,D87) -> 351,5 | H87: 2.5 | I87: 1.2 | J87: 3.3 | K87: =I87+J87 -> 4.5 | M87: =((F87*(1-$M$2)+H87+$M$3)*E87*$M$7)*$W$11 -> 3.7496148 | N87: =((F87*(1-$N$2)+K87+$N$3)*E87*$M$7)*$W$11 -> 6.2661348 | O87: 0.85536 | P87: =M87+O87*$W$11 -> 4.6049748 | Q87: =N87+O87*$W$11 -> 7.1214948 | R87: 1.44936 | S87: =M87+R87*$W$11 -> 5.1989748 | T87: =N87+R87*$W$11 -> 7.7154948 | U87: =E87*B87 -> 460.52316
B88: 366 | C88: 35 | D88: 2 | E88: =(C88-D88)*D88*0.02504 -> 1.65264 | F88: 1 | G88: =CONCATENATE(C88,D88) -> 352 | H88: 2.23 | I88: 1.47 | J88: 2.875 | K88: =I88+J88 -> 4.345 | M88: =((F88*(1-$M$2)+H88+$M$3)*E88*$M$7)*$W$11 -> 4.4786544 | N88: =((F88*(1-$N$2)+K88+$N$3)*E88*$M$7)*$W$11 -> 7.973988 | O88: 0.891 | P88: =M88+O88*$W$11 -> 5.3696544 | Q88: =N88+O88*$W$11 -> 8.864988 | R88: 1.44936 | S88: =M88+R88*$W$11 -> 5.9280144 | T88: =N88+R88*$W$11 -> 9.423348 | U88: =E88*B88 -> 604.86624
B89: 366 | C89: 35 | D89: 2.5 | E89: =(C89-D89)*D89*0.02504 -> 2.0345 | F89: 1 | G89: =CONCATENATE(C89,D89) -> 352,5 | H89: 2.35 | I89: 1.3 | J89: 3.15 | K89: =I89+J89 -> 4.45 | M89: =((F89*(1-$M$2)+H89+$M$3)*E89*$M$7)*$W$11 -> 5.757635 | N89: =((F89*(1-$N$2)+K89+$N$3)*E89*$M$7)*$W$11 -> 10.030085 | O89: 0.94 | P89: =M89+O89*$W$11 -> 6.697635 | Q89: =N89+O89*$W$11 -> 10.970085 | R89: 1.58 | S89: =M89+R89*$W$11 -> 7.337635 | T89: =N89+R89*$W$11 -> 11.610085 | U89: =E89*B89 -> 744.627
B90: 366 | C90: 35 | D90: 3 | E90: =(C90-D90)*D90*0.02504 -> 2.40384 | F90: 1 | G90: =CONCATENATE(C90,D90) -> 353 | H90: 2.4 | I90: 1.2 | J90: 3.2 | K90: =I90+J90 -> 4.4 | M90: =((F90*(1-$M$2)+H90+$M$3)*E90*$M$7)*$W$11 -> 6.9230592 | O90: 0.94 | P90: =M90+O90*$W$11 -> 7.8630592 | R90: 2.28 | S90: =M90+R90*$W$11 -> 9.2030592 | U90: =E90*B90 -> 879.80544
B91: 366 | C91: 38 | D91: 1 | E91: =(C91-D91)*D91*0.02504 -> 0.92648 | F91: 1 | G91: =CONCATENATE(C91,D91) -> 381 | H91: 2.57 | I91: 1.2 | J91: 3.37 | K91: =I91+J91 -> 4.57 | M91: =((F91*(1-$M$2)+H91+$M$3)*E91*$M$7)*$W$11 -> 2.825764 | O91: 0.93852 | P91: =M91+O91*$W$11 -> 3.764284 | R91: 1.58004 | S91: =M91+R91*$W$11 -> 4.405804 | U91: =E91*B91 -> 339.09168
B92: 366 | C92: 38 | D92: 1.2 | E92: =(C92-D92)*D92*0.02504 -> 1.1057664 | F92: 1 | G92: =CONCATENATE(C92,D92) -> 381,2 | H92: 2.55 | I92: 1.2 | J92: 3.35 | K92: =I92+J92 -> 4.55 | M92: =((F92*(1-$M$2)+H92+$M$3)*E92*$M$7)*$W$11 -> 3.3504722 | O92: 0.93852 | P92: =M92+O92*$W$11 -> 4.2889922 | R92: 1.58004 | S92: =M92+R92*$W$11 -> 4.9305122 | U92: =E92*B92 -> 404.7105
B93: 366 | C93: 38 | D93: 1.5 | E93: =(C93-D93)*D93*0.02504 -> 1.37094 | F93: 1 | G93: =CONCATENATE(C93,D93) -> 381,5 | H93: 2.5 | I93: 1.2 | J93: 3.3 | K93: =I93+J93 -> 4.5 | M93: =((F93*(1-$M$2)+H93+$M$3)*E93*$M$7)*$W$11 -> 4.0854012 | N93: =((F93*(1-$N$2)+K93+$N$3)*E93*$M$7)*$W$11 -> 6.8272812 | O93: 0.93852 | P93: =M93+O93*$W$11 -> 5.0239212 | Q93: =N93+O93*$W$11 -> 7.7658012 | R93: 1.58004 | S93: =M93+R93*$W$11 -> 5.6654412 | T93: =N93+R93*$W$11 -> 8.4073212 | U93: =E93*B93 -> 501.76404
B94: 366 | C94: 38 | D94: 2 | E94: =(C94-D94)*D94*0.02504 -> 1.80288 | F94: 1 | G94: =CONCATENATE(C94,D94) -> 382 | H94: 2.23 | I94: 1.47 | J94: 2.885 | K94: =I94+J94 -> 4.355 | M94: =((F94*(1-$M$2)+H94+$M$3)*E94*$M$7)*$W$11 -> 4.8858048 | N94: =((F94*(1-$N$2)+K94+$N$3)*E94*$M$7)*$W$11 -> 8.7169248 | O94: 0.97416 | P94: =M94+O94*$W$11 -> 5.8599648 | Q94: =N94+O94*$W$11 -> 9.6910848 | R94: 1.58004 | S94: =M94+R94*$W$11 -> 6.4658448 | T94: =N94+R94*$W$11 -> 10.296965 | U94: =E94*B94 -> 659.85408
B95: 366 | C95: 38 | D95: 2.5 | E95: =(C95-D95)*D95*0.02504 -> 2.2223 | F95: 1 | G95: =CONCATENATE(C95,D95) -> 382,5 | H95: 2.19 | I95: 1.3 | J95: 2.79 | K95: =I95+J95 -> 4.09 | M95: =((F95*(1-$M$2)+H95+$M$3)*E95*$M$7)*$W$11 -> 5.933541 | N95: =((F95*(1-$N$2)+K95+$N$3)*E95*$M$7)*$W$11 -> 10.155911 | O95: 1.09296 | P95: =M95+O95*$W$11 -> 7.026501 | Q95: =N95+O95*$W$11 -> 11.248871 | R95: 2.18592 | S95: =M95+R95*$W$11 -> 8.119461 | T95: =N95+R95*$W$11 -> 12.341831 | U95: =E95*B95 -> 813.3618
B96: 366 | C96: 38 | D96: 3 | E96: =(C96-D96)*D96*0.02504 -> 2.6292 | F96: 1 | G96: =CONCATENATE(C96,D96) -> 383 | H96: 2.2 | I96: 1.2 | J96: 2.905 | K96: =I96+J96 -> 4.105 | M96: =((F96*(1-$M$2)+H96+$M$3)*E96*$M$7)*$W$11 -> 7.046256 | O96: 1.188 | P96: =M96+O96*$W$11 -> 8.234256 | R96: 2.28096 | S96: =M96+R96*$W$11 -> 9.327216 | U96: =E96*B96 -> 962.2872
B97: 366 | C97: 40 | D97: 1 | E97: =(C97-D97)*D97*0.02504 -> 0.97656 | F97: 1 | G97: =CONCATENATE(C97,D97) -> 401 | H97: 2.55 | I97: 1.2 | J97: 3.35 | K97: =I97+J97 -> 4.55 | M97: =((F97*(1-$M$2)+H97+$M$3)*E97*$M$7)*$W$11 -> 2.9589768 | O97: 0.98604 | P97: =M97+O97*$W$11 -> 3.9450168 | R97: 1.6632 | S97: =M97+R97*$W$11 -> 4.6221768 | U97: =E97*B97 -> 357.42096
B98: 366 | C98: 40 | D98: 1.2 | E98: =(C98-D98)*D98*0.02504 -> 1.1658624 | F98: 1 | G98: =CONCATENATE(C98,D98) -> 401,2 | H98: 2.53 | I98: 1.2 | J98: 3.33 | K98: =I98+J98 -> 4.53 | M98: =((F98*(1-$M$2)+H98+$M$3)*E98*$M$7)*$W$11 -> 3.5092458 | O98: 0.98604 | P98: =M98+O98*$W$11 -> 4.4952858 | R98: 1.6632 | S98: =M98+R98*$W$11 -> 5.1724458 | U98: =E98*B98 -> 426.70564
B99: 366 | C99: 40 | D99: 1.5 | E99: =(C99-D99)*D99*0.02504 -> 1.44606 | F99: 1 | G99: =CONCATENATE(C99,D99) -> 401,5 | H99: 2.47 | I99: 1.2 | J99: 3.269 | K99: =I99+J99 -> 4.469 | M99: =((F99*(1-$M$2)+H99+$M$3)*E99*$M$7)*$W$11 -> 4.265877 | N99: =((F99*(1-$N$2)+K99+$N$3)*E99*$M$7)*$W$11 -> 7.1565509 | O99: 0.98604 | P99: =M99+O99*$W$11 -> 5.251917 | Q99: =N99+O99*$W$11 -> 8.1425909 | R99: 1.6632 | S99: =M99+R99*$W$11 -> 5.929077 | T99: =N99+R99*$W$11 -> 8.8197509 | U99: =E99*B99 -> 529.25796
B100: 366 | C100: 40 | D100: 2 | E100: =(C100-D100)*D100*0.02504 -> 1.90304 | F100: 1 | G100: =CONCATENATE(C100,D100) -> 402 | H100: 2.21 | I100: 1.47 | J100: 2.857 | K100: =I100+J100 -> 4.327 | M100: =((F100*(1-$M$2)+H100+$M$3)*E100*$M$7)*$W$11 -> 5.1191776 | N100: =((F100*(1-$N$2)+K100+$N$3)*E100*$M$7)*$W$11 -> 9.1479133 | O100: 1.02168 | P100: =M100+O100*$W$11 -> 6.1408576 | Q100: =N100+O100*$W$11 -> 10.169593 | R100: 1.6632 | S100: =M100+R100*$W$11 -> 6.7823776 | T100: =N100+R100*$W$11 -> 10.811113 | U100: =E100*B100 -> 696.51264
...

Sheet BOX SECTION
A1: PRICE LIST MAY '26 | X1: DC 8.2_03
B2: DISCOUNT | S2: 0.52 | T2: 304L | V2: 0.52 | W2: 316L | Y2: 0.5 | Z2: 316Ti | AC2: DKK | AD2: 0
B3: Alloy Surcharge €/Kg | S3: 0 | T3: 304L | V3: 0 | W3: 316L | Y3: 0 | Z3: 316Ti | AC3: EUR | AD3: 1
AC4: GBP | AD4: 0.87
AC5: NOK | AD5: 0
D6: EXTRA % | S6: 1 | V6: 1 | AC6: SEK | AD6: 0
D7: Rate | S7: EUR | AC7: USD | AD7: 1.16
A9: MT BDL | B9: Section | J9: EUR/KG 304 | P9: EXTRA | Q9: EXTRA | S9: 304L | T9: 304L | U9: 304L | V9: 316L | W9: 316L | X9: 316L | Y9: 316Ti | Z9: 316Ti | AA9: 316Ti | AD9: =VLOOKUP(S7,$AC$2:$AD$7,2) -> 1
B10: A | D10: B | F10: Thk. | G10: kg/mt | H10: €/kg | J10: 304 | K10: EX 316 | L10: Fisso 316L | M10: T.316L | N10: EX Ti | O10: Fis. 316Ti | P10: SATINATURA | Q10: LUCIDAT. | S10: BRUSHED | T10: POLISHED | U10: MIRROR | V10: BRUSHED | W10: POLISHED | X10: MIRROR | Y10: BRUSHED | Z10: POLISHED | AA10: MIRROR | AB10: Kg/Bdl
A11: 900 | B11: 10 | C11: x | D11: 10 | E11: x | F11: 1 | G11: =(((B11*2+D11*2)/3.14)-F11)*F11*0.02504 -> 0.29394089 | H11: 1 | I11: =CONCATENATE(B11,D11,F11) -> 10101 | J11: 3.11 | K11: 1.2 | L11: 3.91 | M11: =K11+L11 -> 5.11 | N11: 0.4 | O11: =M11+N11 -> 5.51 | P11: 1.12 | Q11: 1.81 | S11: =((H11*(1-$S$2)+J11+$S$3)*G11*$S$6)*$AD$9 -> 1.0552478 | T11: =S11+(P11*$AD$9) -> 2.1752478 | U11: =S11+(Q11*$AD$9) -> 2.8652478 | AB11: =A11*G11 -> 264.5468
A12: 900 | B12: 12 | C12: x | D12: 12 | E12: x | F12: 1 | G12: =(((B12*2+D12*2)/3.14)-F12)*F12*0.02504 -> 0.35773707 | H12: 1 | I12: =CONCATENATE(B12,D12,F12) -> 12121 | J12: 3.11 | K12: 1.5 | L12: 3.91 | M12: =K12+L12 -> 5.41 | N12: 0.4 | O12: =M12+N12 -> 5.81 | P12: 1.12 | Q12: 1.81 | S12: =((H12*(1-$S$2)+J12+$S$3)*G12*$S$6)*$AD$9 -> 1.2842761 | T12: =S12+(P12*$AD$9) -> 2.4042761 | U12: =S12+(Q12*$AD$9) -> 3.0942761 | AB12: =A12*G12 -> 321.96336
A13: 900 | B13: 12 | C13: x | D13: 12 | E13: x | F13: 1.2 | G13: =(((B13*2+D13*2)/3.14)-F13)*F13*0.02504 -> 0.42327488 | H13: 1 | I13: =CONCATENATE(B13,D13,F13) -> 12121,2 | J13: 3.03 | K13: 1.2 | L13: 3.83 | M13: =K13+L13 -> 5.03 | N13: 0.4 | O13: =M13+N13 -> 5.43 | P13: 1.12 | Q13: 1.81 | S13: =((H13*(1-$S$2)+J13+$S$3)*G13*$S$6)*$AD$9 -> 1.4856948 | T13: =S13+(P13*$AD$9) -> 2.6056948 | U13: =S13+(Q13*$AD$9) -> 3.2956948 | AB13: =A13*G13 -> 380.9474
A14: 900 | B14: 12 | C14: x | D14: 12 | E14: x | F14: 1.5 | G14: =(((B14*2+D14*2)/3.14)-F14)*F14*0.02504 -> 0.51782561 | H14: 1 | I14: =CONCATENATE(B14,D14,F14) -> 12121,5 | J14: 2.98 | K14: 1.2 | L14: 3.78 | M14: =K14+L14 -> 4.98 | N14: 0.4 | O14: =M14+N14 -> 5.38 | P14: 1.12 | Q14: 1.81 | S14: =((H14*(1-$S$2)+J14+$S$3)*G14*$S$6)*$AD$9 -> 1.7916766 | T14: =S14+(P14*$AD$9) -> 2.9116766 | U14: =S14+(Q14*$AD$9) -> 3.6016766 | V14: =((H14*(1-$V$2)+M14+$V$3)*G14*$S$6)*$AD$9 -> 2.8273278 | AB14: =A14*G14 -> 466.04304
A15: 726 | B15: 15 | C15: x | D15: 15 | E15: x | F15: 1 | G15: =(((B15*2+D15*2)/3.14)-F15)*F15*0.02504 -> 0.45343134 | H15: 1 | I15: =CONCATENATE(B15,D15,F15) -> 15151 | J15: 2.78 | K15: 1.2 | L15: 3.58 | M15: =K15+L15 -> 4.78 | N15: 0.4 | O15: =M15+N15 -> 5.18 | P15: 1.11672 | Q15: 1.80576 | S15: =((H15*(1-$S$2)+J15+$S$3)*G15*$S$6)*$AD$9 -> 1.4781862 | T15: =S15+(P15*$AD$9) -> 2.5949062 | U15: =S15+(Q15*$AD$9) -> 3.2839462 | AB15: =A15*G15 -> 329.19115
A16: 726 | B16: 15 | C16: x | D16: 15 | E16: x | F16: 1.2 | G16: =(((B16*2+D16*2)/3.14)-F16)*F16*0.02504 -> 0.53810801 | H16: 1 | I16: =CONCATENATE(B16,D16,F16) -> 15151,2 | J16: 2.76 | K16: 1.2 | L16: 3.56 | M16: =K16+L16 -> 4.76 | N16: 0.4 | O16: =M16+N16 -> 5.16 | P16: 1.11672 | Q16: 1.80576 | S16: =((H16*(1-$S$2)+J16+$S$3)*G16*$S$6)*$AD$9 -> 1.7434699 | T16: =S16+(P16*$AD$9) -> 2.8601899 | U16: =S16+(Q16*$AD$9) -> 3.5492299 | AB16: =A16*G16 -> 390.66641
A17: 726 | B17: 15 | C17: x | D17: 15 | E17: x | F17: 1.5 | G17: =(((B17*2+D17*2)/3.14)-F17)*F17*0.02504 -> 0.66136701 | H17: 1 | I17: =CONCATENATE(B17,D17,F17) -> 15151,5 | J17: 2.7 | K17: 1.2 | L17: 3.5 | M17: =K17+L17 -> 4.7 | N17: 0.4 | O17: =M17+N17 -> 5.1 | P17: 1.11672 | Q17: 1.80576 | S17: =((H17*(1-$S$2)+J17+$S$3)*G17*$S$6)*$AD$9 -> 2.1031471 | T17: =S17+(P17*$AD$9) -> 3.2198671 | U17: =S17+(Q17*$AD$9) -> 3.9089071 | V17: =((H17*(1-$V$2)+M17+$V$3)*G17*$S$6)*$AD$9 -> 3.4258811 | W17: =V17+P17*$AD$9 -> 4.5426011 | X17: =V17+(Q17*$AD$9) -> 5.2316411 | AB17: =A17*G17 -> 480.15245
A18: 726 | B18: 15 | C18: x | D18: 15 | E18: x | F18: 2 | G18: =(((B18*2+D18*2)/3.14)-F18)*F18*0.02504 -> 0.85678268 | H18: 1 | I18: =CONCATENATE(B18,D18,F18) -> 15152 | J18: 2.65 | K18: 1.47 | L18: 3.45 | M18: =K18+L18 -> 4.92 | N18: 0.4 | O18: =M18+N18 -> 5.32 | P18: 1.28 | Q18: 3 | S18: =((H18*(1-$S$2)+J18+$S$3)*G18*$S$6)*$AD$9 -> 2.6817298 | T18: =S18+(P18*$AD$9) -> 3.9617298 | U18: =S18+(Q18*$AD$9) -> 5.6817298 | V18: =((H18*(1-$V$2)+M18+$V$3)*G18*$S$6)*$AD$9 -> 4.6266264 | AB18: =A18*G18 -> 622.02422
A19: 726 | B19: 16 | C19: x | D19: 16 | E19: x | F19: 1 | G19: =(((B19*2+D19*2)/3.14)-F19)*F19*0.02504 -> 0.48532943 | H19: 1 | I19: =CONCATENATE(B19,D19,F19) -> 16161 | J19: 2.69 | K19: 1.2 | L19: 3.49 | M19: =K19+L19 -> 4.69 | N19: 0.4 | O19: =M19+N19 -> 5.09 | P19: 1.11672 | Q19: 1.92456 | S19: =((H19*(1-$S$2)+J19+$S$3)*G19*$S$6)*$AD$9 -> 1.5384943 | T19: =S19+(P19*$AD$9) -> 2.6552143 | U19: =S19+(Q19*$AD$9) -> 3.4630543 | AB19: =A19*G19 -> 352.34916
A20: 726 | B20: 16 | C20: x | D20: 16 | E20: x | F20: 1.5 | G20: =(((B20*2+D20*2)/3.14)-F20)*F20*0.02504 -> 0.70921414 | H20: 1 | I20: =CONCATENATE(B20,D20,F20) -> 16161,5 | J20: 2.61 | K20: 1.2 | L20: 3.41 | M20: =K20+L20 -> 4.61 | N20: 0.4 | O20: =M20+N20 -> 5.01 | P20: 1.11672 | Q20: 1.92456 | S20: =((H20*(1-$S$2)+J20+$S$3)*G20*$S$6)*$AD$9 -> 2.1914717 | T20: =S20+(P20*$AD$9) -> 3.3081917 | U20: =S20+(Q20*$AD$9) -> 4.1160317 | V20: =((H20*(1-$V$2)+M20+$V$3)*G20*$S$6)*$AD$9 -> 3.6099 | W20: =V20+P20*$AD$9 -> 4.72662 | X20: =V20+(Q20*$AD$9) -> 5.53446 | AB20: =A20*G20 -> 514.88947
A21: 726 | B21: 20 | C21: x | D21: 20 | E21: x | F21: 1 | G21: =(((B21*2+D21*2)/3.14)-F21)*F21*0.02504 -> 0.61292178 | H21: 1 | I21: =CONCATENATE(B21,D21,F21) -> 20201 | J21: 2.63 | K21: 1.2 | L21: 3.43 | M21: =K21+L21 -> 4.63 | N21: 0.4 | O21: =M21+N21 -> 5.03 | P21: 1.11672 | Q21: 2.41164 | S21: =((H21*(1-$S$2)+J21+$S$3)*G21*$S$6)*$AD$9 -> 1.9061867 | T21: =S21+(P21*$AD$9) -> 3.0229067 | U21: =S21+(Q21*$AD$9) -> 4.3178267 | AB21: =A21*G21 -> 444.98121
A22: 726 | B22: 20 | C22: x | D22: 20 | E22: x | F22: 1.2 | G22: =(((B22*2+D22*2)/3.14)-F22)*F22*0.02504 -> 0.72949654 | H22: 1 | I22: =CONCATENATE(B22,D22,F22) -> 20201,2 | J22: 2.6 | K22: 1.2 | L22: 3.4 | M22: =K22+L22 -> 4.6 | N22: 0.4 | O22: =M22+N22 -> 5 | P22: 1.11672 | Q22: 2.41164 | S22: =((H22*(1-$S$2)+J22+$S$3)*G22*$S$6)*$AD$9 -> 2.2468493 | T22: =S22+(P22*$AD$9) -> 3.3635693 | U22: =S22+(Q22*$AD$9) -> 4.6584893 | AB22: =A22*G22 -> 529.61449
A23: 726 | B23: 20 | C23: x | D23: 20 | E23: x | F23: 1.5 | G23: =(((B23*2+D23*2)/3.14)-F23)*F23*0.02504 -> 0.90060268 | H23: 1 | I23: =CONCATENATE(B23,D23,F23) -> 20201,5 | J23: 2.56 | K23: 1.2 | L23: 3.36 | M23: =K23+L23 -> 4.56 | N23: 0.4 | O23: =M23+N23 -> 4.96 | P23: 1.11672 | Q23: 2.41164 | S23: =((H23*(1-$S$2)+J23+$S$3)*G23*$S$6)*$AD$9 -> 2.7378321 | T23: =S23+(P23*$AD$9) -> 3.8545521 | U23: =S23+(Q23*$AD$9) -> 5.1494721 | V23: =((H23*(1-$V$2)+M23+$V$3)*G23*$S$6)*$AD$9 -> 4.5390375 | W23: =V23+P23*$AD$9 -> 5.6557575 | X23: =V23+(Q23*$AD$9) -> 6.9506775 | AB23: =A23*G23 -> 653.83754
A24: 726 | B24: 20 | C24: x | D24: 20 | E24: x | F24: 2 | G24: =(((B24*2+D24*2)/3.14)-F24)*F24*0.02504 -> 1.1757636 | H24: 1 | I24: =CONCATENATE(B24,D24,F24) -> 20202 | J24: 2.29 | K24: 1.47 | L24: 2.942 | M24: =K24+L24 -> 4.412 | N24: 0.4 | O24: =M24+N24 -> 4.812 | P24: 1.28304 | Q24: 3.35016 | S24: =((H24*(1-$S$2)+J24+$S$3)*G24*$S$6)*$AD$9 -> 3.2568651 | T24: =S24+(P24*$AD$9) -> 4.5399051 | U24: =S24+(Q24*$AD$9) -> 6.6070251 | V24: =((H24*(1-$V$2)+M24+$V$3)*G24*$S$6)*$AD$9 -> 5.7518354 | W24: =V24+P24*$AD$9 -> 7.0348754 | X24: =V24+(Q24*$AD$9) -> 9.1019954 | Y24: =((H24*(1-$Y$2)+O24+$Y$3)*G24*$S$6)*$AD$9 -> 6.2456561 | Z24: =Y24+P24*$AD$9 -> 7.5286961 | AA24: =Y24+(Q24*$AD$9) -> 9.5958161 | AB24: =A24*G24 -> 853.60435
A25: 486 | B25: 20 | C25: x | D25: 20 | E25: x | F25: 3 | G25: =(((B25*2+D25*2)/3.14)-F25)*F25*0.02504 -> 1.6885254 | H25: 1 | I25: =CONCATENATE(B25,D25,F25) -> 20203 | J25: 2.4 | K25: 1.2 | L25: 3.2 | M25: =K25+L25 -> 4.4 | N25: 0.4 | O25: =M25+N25 -> 4.8 | P25: 1.3 | Q25: 6.77 | S25: =((H25*(1-$S$2)+J25+$S$3)*G25*$S$6)*$AD$9 -> 4.862953 | T25: =S25+(P25*$AD$9) -> 6.162953 | U25: =S25+(Q25*$AD$9) -> 11.632953 | V25: =((H25*(1-$V$2)+M25+$V$3)*G25*$S$6)*$AD$9 -> 8.2400037 | W25: =V25+P25*$AD$9 -> 9.5400037 | X25: =V25+(Q25*$AD$9) -> 15.010004 | Y25: =((H25*(1-$Y$2)+O25+$Y$3)*G25*$S$6)*$AD$9 -> 8.9491844 | Z25: =Y25+P25*$AD$9 -> 10.249184 | AA25: =Y25+(Q25*$AD$9) -> 15.719184 | AB25: =A25*G25 -> 820.62332
A26: 726 | B26: 22 | C26: x | D26: 22 | E26: x | F26: 1.5 | G26: =(((B26*2+D26*2)/3.14)-F26)*F26*0.02504 -> 0.99629694 | H26: 1 | I26: =CONCATENATE(B26,D26,F26) -> 22221,5 | J26: 2.75 | K26: 1.2 | L26: 3.55 | M26: =K26+L26 -> 4.75 | N26: 0.4 | O26: =M26+N26 -> 5.15 | P26: 1.12 | Q26: 3.01 | S26: =((H26*(1-$S$2)+J26+$S$3)*G26*$S$6)*$AD$9 -> 3.2180391 | T26: =S26+(P26*$AD$9) -> 4.3380391 | U26: =S26+(Q26*$AD$9) -> 6.2280391 | V26: =((H26*(1-$V$2)+M26+$V$3)*G26*$S$6)*$AD$9 -> 5.210633 | W26: =V26+P26*$AD$9 -> 6.330633 | X26: =V26+(Q26*$AD$9) -> 8.220633 | AB26: =A26*G26 -> 723.31158
A27: 864 | B27: 25 | C27: x | D27: 25 | E27: x | F27: 1 | G27: =(((B27*2+D27*2)/3.14)-F27)*F27*0.02504 -> 0.77241223 | H27: 1 | I27: =CONCATENATE(B27,D27,F27) -> 25251 | J27: 2.59 | K27: 1.2 | L27: 3.39 | M27: =K27+L27 -> 4.59 | N27: 0.4 | O27: =M27+N27 -> 4.99 | P27: 1.11672 | Q27: 3.00564 | S27: =((H27*(1-$S$2)+J27+$S$3)*G27*$S$6)*$AD$9 -> 2.3713055 | T27: =S27+(P27*$AD$9) -> 3.4880255 | U27: =S27+(Q27*$AD$9) -> 5.3769455 | AB27: =A27*G27 -> 667.36417
A28: 864 | B28: 25 | C28: x | D28: 25 | E28: x | F28: 1.2 | G28: =(((B28*2+D28*2)/3.14)-F28)*F28*0.02504 -> 0.92088508 | H28: 1 | I28: =CONCATENATE(B28,D28,F28) -> 25251,2 | J28: 2.57 | K28: 1.2 | L28: 3.37 | M28: =K28+L28 -> 4.57 | N28: 0.4 | O28: =M28+N28 -> 4.97 | P28: 1.11672 | Q28: 3.00564 | S28: =((H28*(1-$S$2)+J28+$S$3)*G28*$S$6)*$AD$9 -> 2.8086995 | T28: =S28+(P28*$AD$9) -> 3.9254195 | U28: =S28+(Q28*$AD$9) -> 5.8143395 | AB28: =A28*G28 -> 795.6447
A29: 864 | B29: 25 | C29: x | D29: 25 | E29: x | F29: 1.5 | G29: =(((B29*2+D29*2)/3.14)-F29)*F29*0.02504 -> 1.1398383 | H29: 1 | I29: =CONCATENATE(B29,D29,F29) -> 25251,5 | J29: 2.51 | K29: 1.2 | L29: 3.31 | M29: =K29+L29 -> 4.51 | N29: 0.4 | O29: =M29+N29 -> 4.91 | P29: 1.11672 | Q29: 3.00564 | S29: =((H29*(1-$S$2)+J29+$S$3)*G29*$S$6)*$AD$9 -> 3.4081166 | T29: =S29+(P29*$AD$9) -> 4.5248366 | U29: =S29+(Q29*$AD$9) -> 6.4137566 | V29: =((H29*(1-$V$2)+M29+$V$3)*G29*$S$6)*$AD$9 -> 5.6877933 | W29: =V29+P29*$AD$9 -> 6.8045133 | X29: =V29+(Q29*$AD$9) -> 8.6934333 | AB29: =A29*G29 -> 984.82033
A30: 726 | B30: 25 | C30: x | D30: 25 | E30: x | F30: 2 | G30: =(((B30*2+D30*2)/3.14)-F30)*F30*0.02504 -> 1.4947445 | H30: 1 | I30: =CONCATENATE(B30,D30,F30) -> 25252 | J30: 2.24 | K30: 1.47 | L30: 2.89 | M30: =K30+L30 -> 4.36 | N30: 0.4 | O30: =M30+N30 -> 4.76 | P30: 1.28304 | Q30: 4.18176 | S30: =((H30*(1-$S$2)+J30+$S$3)*G30*$S$6)*$AD$9 -> 4.0657049 | T30: =S30+(P30*$AD$9) -> 5.3487449 | U30: =S30+(Q30*$AD$9) -> 8.2474649 | V30: =((H30*(1-$V$2)+M30+$V$3)*G30*$S$6)*$AD$9 -> 7.2345632 | W30: =V30+P30*$AD$9 -> 8.5176032 | X30: =V30+(Q30*$AD$9) -> 11.416323 | Y30: =((H30*(1-$Y$2)+O30+$Y$3)*G30*$S$6)*$AD$9 -> 7.8623559 | Z30: =Y30+P30*$AD$9 -> 9.1453959 | AA30: =Y30+(Q30*$AD$9) -> 12.044116 | AB30: =A30*G30 -> 1085.1845
A31: 486 | B31: 25 | C31: x | D31: 25 | E31: x | F31: 2.5 | G31: =(((B31*2+D31*2)/3.14)-F31)*F31*0.02504 -> 1.8371306 | H31: 1 | I31: =CONCATENATE(B31,D31,F31) -> 25252,5 | J31: 2.35 | K31: 1.2 | L31: 3.15 | M31: =K31+L31 -> 4.35 | N31: 0.4 | O31: =M31+N31 -> 4.75 | P31: 1.52 | Q31: 6.77 | S31: =((H31*(1-$S$2)+J31+$S$3)*G31*$S$6)*$AD$9 -> 5.1990795 | T31: =S31+(P31*$AD$9) -> 6.7190795 | U31: =S31+(Q31*$AD$9) -> 11.96908 | AB31: =A31*G31 -> 892.84546
A32: 486 | B32: 25 | C32: x | D32: 25 | E32: x | F32: 3 | G32: =(((B32*2+D32*2)/3.14)-F32)*F32*0.02504 -> 2.1669967 | H32: 1 | I32: =CONCATENATE(B32,D32,F32) -> 25253 | J32: 2.3 | K32: 1.2 | L32: 3.003 | M32: =K32+L32 -> 4.203 | N32: 0.4 | O32: =M32+N32 -> 4.603 | P32: 1.52064 | Q32: 6.7716 | S32: =((H32*(1-$S$2)+J32+$S$3)*G32*$S$6)*$AD$9 -> 6.0242508 | T32: =S32+(P32*$AD$9) -> 7.5448908 | U32: =S32+(Q32*$AD$9) -> 12.795851 | AB32: =A32*G32 -> 1053.1604
A33: 600 | B33: 30 | C33: x | D33: 30 | E33: x | F33: 1 | G33: =(((B33*2+D33*2)/3.14)-F33)*F33*0.02504 -> 0.93190268 | H33: 1 | I33: =CONCATENATE(B33,D33,F33) -> 30301 | J33: 2.52 | K33: 1.2 | L33: 3.32 | M33: =K33+L33 -> 4.52 | N33: 0.4 | O33: =M33+N33 -> 4.92 | P33: 1.11672 | Q33: 3.61152 | S33: =((H33*(1-$S$2)+J33+$S$3)*G33*$S$6)*$AD$9 -> 2.795708 | T33: =S33+(P33*$AD$9) -> 3.912428 | U33: =S33+(Q33*$AD$9) -> 6.407228 | AB33: =A33*G33 -> 559.14161
A34: 600 | B34: 30 | C34: x | D34: 30 | E34: x | F34: 1.2 | G34: =(((B34*2+D34*2)/3.14)-F34)*F34*0.02504 -> 1.1122736 | H34: 1 | I34: =CONCATENATE(B34,D34,F34) -> 30301,2 | J34: 2.46 | K34: 1.2 | L34: 3.26 | M34: =K34+L34 -> 4.46 | N34: 0.4 | O34: =M34+N34 -> 4.86 | P34: 1.11672 | Q34: 3.61152 | S34: =((H34*(1-$S$2)+J34+$S$3)*G34*$S$6)*$AD$9 -> 3.2700844 | T34: =S34+(P34*$AD$9) -> 4.3868044 | U34: =S34+(Q34*$AD$9) -> 6.8816044 | AB34: =A34*G34 -> 667.36417
A35: 600 | B35: 30 | C35: x | D35: 30 | E35: x | F35: 1.5 | G35: =(((B35*2+D35*2)/3.14)-F35)*F35*0.02504 -> 1.379074 | H35: 1 | I35: =CONCATENATE(B35,D35,F35) -> 30301,5 | J35: 2.41 | K35: 1.2 | L35: 3.21 | M35: =K35+L35 -> 4.41 | N35: 0.4 | O35: =M35+N35 -> 4.81 | P35: 1.11672 | Q35: 3.61152 | S35: =((H35*(1-$S$2)+J35+$S$3)*G35*$S$6)*$AD$9 -> 3.9855239 | T35: =S35+(P35*$AD$9) -> 5.1022439 | U35: =S35+(Q35*$AD$9) -> 7.5970439 | V35: =((H35*(1-$V$2)+M35+$V$3)*G35*$S$6)*$AD$9 -> 6.7436719 | W35: =V35+P35*$AD$9 -> 7.8603919 | X35: =V35+(Q35*$AD$9) -> 10.355192 | AB35: =A35*G35 -> 827.44441
A36: 600 | B36: 30 | C36: x | D36: 30 | E36: x | F36: 2 | G36: =(((B36*2+D36*2)/3.14)-F36)*F36*0.02504 -> 1.8137254 | H36: 1 | I36: =CONCATENATE(B36,D36,F36) -> 30302 | J36: 2.14 | K36: 1.47 | L36: 2.79 | M36: =K36+L36 -> 4.26 | N36: 0.4 | O36: =M36+N36 -> 4.66 | P36: 1.28304 | Q36: 5.01336 | S36: =((H36*(1-$S$2)+J36+$S$3)*G36*$S$6)*$AD$9 -> 4.7519604 | T36: =S36+(P36*$AD$9) -> 6.0350004 | U36: =S36+(Q36*$AD$9) -> 9.7653204 | V36: =((H36*(1-$V$2)+M36+$V$3)*G36*$S$6)*$AD$9 -> 8.5970582 | W36: =V36+P36*$AD$9 -> 9.8800982 | X36: =V36+(Q36*$AD$9) -> 13.610418 | Y36: =((H36*(1-$Y$2)+O36+$Y$3)*G36*$S$6)*$AD$9 -> 9.3588228 | Z36: =Y36+P36*$AD$9 -> 10.641863 | AA36: =Y36+(Q36*$AD$9) -> 14.372183 | AB36: =A36*G36 -> 1088.2352
A37: 384 | B37: 30 | C37: x | D37: 30 | E37: x | F37: 2.5 | G37: =(((B37*2+D37*2)/3.14)-F37)*F37*0.02504 -> 2.2358567 | H37: 1 | I37: =CONCATENATE(B37,D37,F37) -> 30302,5 | J37: 2.16 | K37: 1.3 | L37: 2.761 | M37: =K37+L37 -> 4.061 | N37: 0.4 | O37: =M37+N37 -> 4.461 | P37: 1.46124 | Q37: 7.7814 | S37: =((H37*(1-$S$2)+J37+$S$3)*G37*$S$6)*$AD$9 -> 5.9026617 | T37: =S37+(P37*$AD$9) -> 7.3639017 | U37: =S37+(Q37*$AD$9) -> 13.684062 | V37: =((H37*(1-$V$2)+M37+$V$3)*G37*$S$6)*$AD$9 -> 10.153025 | W37: =V37+P37*$AD$9 -> 11.614265 | X37: =V37+(Q37*$AD$9) -> 17.934425 | AB37: =A37*G37 -> 858.56897
A38: 384 | B38: 30 | C38: x | D38: 30 | E38: x | F38: 3 | G38: =(((B38*2+D38*2)/3.14)-F38)*F38*0.02504 -> 2.645468 | H38: 1 | I38: =CONCATENATE(B38,D38,F38) -> 30303 | J38: 2.13 | K38: 1.2 | L38: 2.833 | M38: =K38+L38 -> 4.033 | N38: 0.4 | O38: =M38+N38 -> 4.433 | P38: 1.61568 | Q38: 8.12592 | S38: =((H38*(1-$S$2)+J38+$S$3)*G38*$S$6)*$AD$9 -> 6.9046715 | T38: =S38+(P38*$AD$9) -> 8.5203515 | U38: =S38+(Q38*$AD$9) -> 15.030592 | V38: =((H38*(1-$V$2)+M38+$V$3)*G38*$S$6)*$AD$9 -> 11.938997 | W38: =V38+P38*$AD$9 -> 13.554677 | X38: =V38+(Q38*$AD$9) -> 20.064917 | Y38: =((H38*(1-$Y$2)+O38+$Y$3)*G38*$S$6)*$AD$9 -> 13.050094 | Z38: =Y38+P38*$AD$9 -> 14.665774 | AA38: =Y38+(Q38*$AD$9) -> 21.176014 | AB38: =A38*G38 -> 1015.8597
A39: 600 | B39: 35 | C39: x | D39: 35 | E39: x | F39: 1 | G39: =(((B39*2+D39*2)/3.14)-F39)*F39*0.02504 -> 1.0913931 | H39: 1 | I39: =CONCATENATE(B39,D39,F39) -> 35351 | J39: 2.58 | K39: 1.2 | L39: 3.38 | M39: =K39+L39 -> 4.58 | N39: 0.4 | O39: =M39+N39 -> 4.98 | P39: 1.3068 | Q39: 4.2174 | S39: =((H39*(1-$S$2)+J39+$S$3)*G39*$S$6)*$AD$9 -> 3.339663 | T39: =S39+(P39*$AD$9) -> 4.646463 | U39: =S39+(Q39*$AD$9) -> 7.557063 | AB39: =A39*G39 -> 654.83587
A40: 600 | B40: 35 | C40: x | D40: 35 | E40: x | F40: 1.2 | G40: =(((B40*2+D40*2)/3.14)-F40)*F40*0.02504 -> 1.3036621 | H40: 1 | I40: =CONCATENATE(B40,D40,F40) -> 35351,2 | J40: 2.49 | K40: 1.2 | L40: 3.29 | M40: =K40+L40 -> 4.49 | N40: 0.4 | O40: =M40+N40 -> 4.89 | P40: 1.3068 | Q40: 4.2174 | S40: =((H40*(1-$S$2)+J40+$S$3)*G40*$S$6)*$AD$9 -> 3.8718766 | T40: =S40+(P40*$AD$9) -> 5.1786766 | U40: =S40+(Q40*$AD$9) -> 8.0892766 | AB40: =A40*G40 -> 782.19729
A41: 600 | B41: 35 | C41: x | D41: 35 | E41: x | F41: 1.5 | G41: =(((B41*2+D41*2)/3.14)-F41)*F41*0.02504 -> 1.6183097 | H41: 1 | I41: =CONCATENATE(B41,D41,F41) -> 35351,5 | J41: 2.42 | K41: 1.2 | L41: 3.22 | M41: =K41+L41 -> 4.42 | N41: 0.4 | O41: =M41+N41 -> 4.82 | P41: 1.31868 | Q41: 4.2174 | S41: =((H41*(1-$S$2)+J41+$S$3)*G41*$S$6)*$AD$9 -> 4.6930981 | T41: =S41+(P41*$AD$9) -> 6.0117781 | U41: =S41+(Q41*$AD$9) -> 8.9104981 | V41: =((H41*(1-$V$2)+M41+$V$3)*G41*$S$6)*$AD$9 -> 7.9297174 | W41: =V41+P41*$AD$9 -> 9.2483974 | X41: =V41+(Q41*$AD$9) -> 12.147117 | AB41: =A41*G41 -> 970.98581
A42: 432 | B42: 35 | C42: x | D42: 35 | E42: x | F42: 2 | G42: =(((B42*2+D42*2)/3.14)-F42)*F42*0.02504 -> 2.1327062 | H42: 1 | I42: =CONCATENATE(B42,D42,F42) -> 35352 | J42: 2.15 | K42: 1.47 | L42: 2.8 | M42: =K42+L42 -> 4.27 | N42: 0.4 | O42: =M42+N42 -> 4.67 | P42: 1.4256 | Q42: 5.85684 | S42: =((H42*(1-$S$2)+J42+$S$3)*G42*$S$6)*$AD$9 -> 5.6090174 | T42: =S42+(P42*$AD$9) -> 7.0346174 | U42: =S42+(Q42*$AD$9) -> 11.465857 | V42: =((H42*(1-$V$2)+M42+$V$3)*G42*$S$6)*$AD$9 -> 10.130355 | W42: =V42+P42*$AD$9 -> 11.555955 | X42: =V42+(Q42*$AD$9) -> 15.987195 | Y42: =((H42*(1-$Y$2)+O42+$Y$3)*G42*$S$6)*$AD$9 -> 11.026091 | Z42: =Y42+P42*$AD$9 -> 12.451691 | AA42: =Y42+(Q42*$AD$9) -> 16.882931 | AB42: =A42*G42 -> 921.3291
A43: 294 | B43: 35 | C43: x | D43: 35 | E43: x | F43: 2.5 | G43: =(((B43*2+D43*2)/3.14)-F43)*F43*0.02504 -> 2.6345828 | H43: 1 | I43: =CONCATENATE(B43,D43,F43) -> 35352,5 | J43: 2.25 | K43: 1.2 | L43: 2.95 | M43: =K43+L43 -> 4.15 | N43: 0.4 | O43: =M43+N43 -> 4.55 | P43: 1.81 | Q43: 9.48 | S43: =((H43*(1-$S$2)+J43+$S$3)*G43*$S$6)*$AD$9 -> 7.1924111 | T43: =S43+(P43*$AD$9) -> 9.0024111 | U43: =S43+(Q43*$AD$9) -> 16.672411 | V43: =((H43*(1-$V$2)+M43+$V$3)*G43*$S$6)*$AD$9 -> 12.198118 | W43: =V43+P43*$AD$9 -> 14.008118 | X43: =V43+(Q43*$AD$9) -> 21.678118 | AB43: =A43*G43 -> 774.56734
A44: 294 | B44: 35 | C44: x | D44: 35 | E44: x | F44: 3 | G44: =(((B44*2+D44*2)/3.14)-F44)*F44*0.02504 -> 3.1239394 | H44: 1 | I44: =CONCATENATE(B44,D44,F44) -> 35353 | J44: 2.19 | K44: 1.2 | L44: 2.888 | M44: =K44+L44 -> 4.088 | N44: 0.4 | O44: =M44+N44 -> 4.488 | P44: 1.80576 | Q44: 9.48024 | S44: =((H44*(1-$S$2)+J44+$S$3)*G44*$S$6)*$AD$9 -> 8.3409181 | T44: =S44+(P44*$AD$9) -> 10.146678 | U44: =S44+(Q44*$AD$9) -> 17.821158 | V44: =((H44*(1-$V$2)+M44+$V$3)*G44*$S$6)*$AD$9 -> 14.270155 | W44: =V44+P44*$AD$9 -> 16.075915 | X44: =V44+(Q44*$AD$9) -> 23.750395 | Y44: =((H44*(1-$Y$2)+O44+$Y$3)*G44*$S$6)*$AD$9 -> 15.58221 | Z44: =Y44+P44*$AD$9 -> 17.38797 | AA44: =Y44+(Q44*$AD$9) -> 25.06245 | AB44: =A44*G44 -> 918.43817
A45: 540 | B45: 40 | C45: x | D45: 40 | E45: x | F45: 1 | G45: =(((B45*2+D45*2)/3.14)-F45)*F45*0.02504 -> 1.2508836 | H45: 1 | I45: =CONCATENATE(B45,D45,F45) -> 40401 | J45: 2.64 | K45: 1.2 | L45: 3.44 | M45: =K45+L45 -> 4.64 | N45: 0.4 | O45: =M45+N45 -> 5.04 | P45: 1.50876 | Q45: 4.8114 | S45: =((H45*(1-$S$2)+J45+$S$3)*G45*$S$6)*$AD$9 -> 3.9027567 | T45: =S45+(P45*$AD$9) -> 5.4115167 | U45: =S45+(Q45*$AD$9) -> 8.7141567 | AB45: =A45*G45 -> 675.47713
A46: 540 | B46: 40 | C46: x | D46: 40 | E46: x | F46: 1.2 | G46: =(((B46*2+D46*2)/3.14)-F46)*F46*0.02504 -> 1.4950507 | H46: 1 | I46: =CONCATENATE(B46,D46,F46) -> 40401,2 | J46: 2.44 | K46: 1.2 | L46: 3.24 | M46: =K46+L46 -> 4.44 | N46: 0.4 | O46: =M46+N46 -> 4.84 | P46: 1.50876 | Q46: 4.8114 | S46: =((H46*(1-$S$2)+J46+$S$3)*G46*$S$6)*$AD$9 -> 4.365548 | T46: =S46+(P46*$AD$9) -> 5.874308 | U46: =S46+(Q46*$AD$9) -> 9.176948 | AB46: =A46*G46 -> 807.32737
A47: 540 | B47: 40 | C47: x | D47: 40 | E47: x | F47: 1.5 | G47: =(((B47*2+D47*2)/3.14)-F47)*F47*0.02504 -> 1.8575454 | H47: 1 | I47: =CONCATENATE(B47,D47,F47) -> 40401,5 | J47: 2.4 | K47: 1.2 | L47: 3.2 | M47: =K47+L47 -> 4.4 | N47: 0.4 | O47: =M47+N47 -> 4.8 | P47: 1.50876 | Q47: 4.8114 | S47: =((H47*(1-$S$2)+J47+$S$3)*G47*$S$6)*$AD$9 -> 5.3497306 | T47: =S47+(P47*$AD$9) -> 6.8584906 | U47: =S47+(Q47*$AD$9) -> 10.161131 | V47: =((H47*(1-$V$2)+M47+$V$3)*G47*$S$6)*$AD$9 -> 9.0648213 | W47: =V47+P47*$AD$9 -> 10.573581 | X47: =V47+(Q47*$AD$9) -> 13.876221 | Y47: =((H47*(1-$Y$2)+O47+$Y$3)*G47*$S$6)*$AD$9 -> 9.8449904 | Z47: =Y47+P47*$AD$9 -> 11.35375 | AA47: =Y47+(Q47*$AD$9) -> 14.65639 | AB47: =A47*G47 -> 1003.0745
A48: 486 | B48: 40 | C48: x | D48: 40 | E48: x | F48: 2 | G48: =(((B48*2+D48*2)/3.14)-F48)*F48*0.02504 -> 2.4516871 | H48: 1 | I48: =CONCATENATE(B48,D48,F48) -> 40402 | J48: 2.13 | K48: 1.47 | L48: 2.78 | M48: =K48+L48 -> 4.25 | N48: 0.4 | O48: =M48+N48 -> 4.65 | P48: 1.65132 | Q48: 6.68844 | S48: =((H48*(1-$S$2)+J48+$S$3)*G48*$S$6)*$AD$9 -> 6.3989034 | T48: =S48+(P48*$AD$9) -> 8.0502234 | U48: =S48+(Q48*$AD$9) -> 13.087343 | V48: =((H48*(1-$V$2)+M48+$V$3)*G48*$S$6)*$AD$9 -> 11.59648 | W48: =V48+P48*$AD$9 -> 13.2478 | X48: =V48+(Q48*$AD$9) -> 18.28492 | Y48: =((H48*(1-$Y$2)+O48+$Y$3)*G48*$S$6)*$AD$9 -> 12.626189 | Z48: =Y48+P48*$AD$9 -> 14.277509 | AA48: =Y48+(Q48*$AD$9) -> 19.314629 | AB48: =A48*G48 -> 1191.5199
A49: 294 | B49: 40 | C49: x | D49: 40 | E49: x | F49: 2.5 | G49: =(((B49*2+D49*2)/3.14)-F49)*F49*0.02504 -> 3.0333089 | H49: 1 | I49: =CONCATENATE(B49,D49,F49) -> 40402,5 | J49: 2.16 | K49: 1.3 | L49: 2.76 | M49: =K49+L49 -> 4.06 | N49: 0.4 | O49: =M49+N49 -> 4.46 | P49: 1.86516 | Q49: 10.37124 | S49: =((H49*(1-$S$2)+J49+$S$3)*G49*$S$6)*$AD$9 -> 8.0079355 | T49: =S49+(P49*$AD$9) -> 9.8730955 | U49: =S49+(Q49*$AD$9) -> 18.379176 | V49: =((H49*(1-$V$2)+M49+$V$3)*G49*$S$6)*$AD$9 -> 13.771222 | W49: =V49+P49*$AD$9 -> 15.636382 | X49: =V49+(Q49*$AD$9) -> 24.142462 | AB49: =A49*G49 -> 891.79282
A50: 294 | B50: 40 | C50: x | D50: 40 | E50: x | F50: 3 | G50: =(((B50*2+D50*2)/3.14)-F50)*F50*0.02504 -> 3.6024107 | H50: 1 | I50: =CONCATENATE(B50,D50,F50) -> 40403 | J50: 2.1 | K50: 1.2 | L50: 2.8 | M50: =K50+L50 -> 4 | N50: 0.4 | O50: =M50+N50 -> 4.4 | P50: 2.04336 | Q50: 10.83456 | S50: =((H50*(1-$S$2)+J50+$S$3)*G50*$S$6)*$AD$9 -> 9.2942196 | T50: =S50+(P50*$AD$9) -> 11.33758 | U50: =S50+(Q50*$AD$9) -> 20.12878 | V50: =((H50*(1-$V$2)+M50+$V$3)*G50*$S$6)*$AD$9 -> 16.1388 | W50: =V50+P50*$AD$9 -> 18.18216 | X50: =V50+(Q50*$AD$9) -> 26.97336 | Y50: =((H50*(1-$Y$2)+O50+$Y$3)*G50*$S$6)*$AD$9 -> 17.651812 | Z50: =Y50+P50*$AD$9 -> 19.695172 | AA50: =Y50+(Q50*$AD$9) -> 28.486372 | AB50: =A50*G50 -> 1059.1087
A51: 216 | B51: 40 | C51: x | D51: 40 | E51: x | F51: 4 | G51: =(((B51*2+D51*2)/3.14)-F51)*F51*0.02504 -> 4.7030543 | H51: 1 | I51: =CONCATENATE(B51,D51,F51) -> 40404 | J51: 2.12 | K51: 1.2 | L51: 2.82 | M51: =K51+L51 -> 4.02 | N51: 0.4 | O51: =M51+N51 -> 4.42 | P51: 2.94624 | Q51: 10.83456 | S51: =((H51*(1-$S$2)+J51+$S$3)*G51*$S$6)*$AD$9 -> 12.227941 | T51: =S51+(P51*$AD$9) -> 15.174181 | U51: =S51+(Q51*$AD$9) -> 23.062501 | V51: =((H51*(1-$V$2)+M51+$V$3)*G51*$S$6)*$AD$9 -> 21.163744 | W51: =V51+P51*$AD$9 -> 24.109984 | X51: =V51+(Q51*$AD$9) -> 31.998304 | Y51: =((H51*(1-$Y$2)+O51+$Y$3)*G51*$S$6)*$AD$9 -> 23.139027 | Z51: =Y51+P51*$AD$9 -> 26.085267 | AA51: =Y51+(Q51*$AD$9) -> 33.973587 | AB51: =A51*G51 -> 1015.8597
A52: 180 | B52: 40 | C52: x | D52: 40 | E52: x | F52: 5 | G52: =(((B52*2+D52*2)/3.14)-F52)*F52*0.02504 -> 5.7536178 | H52: 1 | I52: =CONCATENATE(B52,D52,F52) -> 40405 | J52: 2.25 | K52: 1.2 | L52: 2.95 | M52: =K52+L52 -> 4.15 | N52: 0.4 | O52: =M52+N52 -> 4.55 | P52: 4.15 | Q52: 13.54 | S52: =((H52*(1-$S$2)+J52+$S$3)*G52*$S$6)*$AD$9 -> 15.707377 | T52: =S52+(P52*$AD$9) -> 19.857377 | AB52: =A52*G52 -> 1035.6512
A53: 294 | B53: 45 | C53: x | D53: 45 | E53: x | F53: 1.2 | G53: =(((B53*2+D53*2)/3.14)-F53)*F53*0.02504 -> 1.6864392 | H53: 1 | I53: =CONCATENATE(B53,D53,F53) -> 45451,2 | J53: 2.55 | K53: 1.2 | L53: 3.35 | M53: =K53+L53 -> 4.55 | N53: 0.4 | O53: =M53+N53 -> 4.95 | P53: 1.69884 | Q53: 5.41728 | S53: =((H53*(1-$S$2)+J53+$S$3)*G53*$S$6)*$AD$9 -> 5.1099108 | T53: =S53+(P53*$AD$9) -> 6.8087508 | U53: =S53+(Q53*$AD$9) -> 10.527191 | AB53: =A53*G53 -> 495.81313
A54: 294 | B54: 45 | C54: x | D54: 45 | E54: x | F54: 1.5 | G54: =(((B54*2+D54*2)/3.14)-F54)*F54*0.02504 -> 2.096781 | H54: 1 | I54: =CONCATENATE(B54,D54,F54) -> 45451,5 | J54: 2.5 | K54: 1.2 | L54: 3.3 | M54: =K54+L54 -> 4.5 | N54: 0.4 | O54: =M54+N54 -> 4.9 | P54: 1.68696 | Q54: 5.41728 | S54: =((H54*(1-$S$2)+J54+$S$3)*G54*$S$6)*$AD$9 -> 6.2484074 | T54: =S54+(P54*$AD$9) -> 7.9353674 | U54: =S54+(Q54*$AD$9) -> 11.665687 | V54: =((H54*(1-$V$2)+M54+$V$3)*G54*$S$6)*$AD$9 -> 10.441969 | W54: =V54+P54*$AD$9 -> 12.128929 | X54: =V54+(Q54*$AD$9) -> 15.859249 | AB54: =A54*G54 -> 616.45362
A55: 294 | B55: 45 | C55: x | D55: 45 | E55: x | F55: 2 | G55: =(((B55*2+D55*2)/3.14)-F55)*F55*0.02504 -> 2.770668 | H55: 1 | I55: =CONCATENATE(B55,D55,F55) -> 45452 | J55: 2.23 | K55: 1.47 | L55: 2.88 | M55: =K55+L55 -> 4.35 | N55: 0.4 | O55: =M55+N55 -> 4.75 | P55: 1.86516 | Q55: 7.53192 | S55: =((H55*(1-$S$2)+J55+$S$3)*G55*$S$6)*$AD$9 -> 7.5085103 | T55: =S55+(P55*$AD$9) -> 9.3736703 | U55: =S55+(Q55*$AD$9) -> 15.04043 | V55: =((H55*(1-$V$2)+M55+$V$3)*G55*$S$6)*$AD$9 -> 13.382327 | W55: =V55+P55*$AD$9 -> 15.247487 | X55: =V55+(Q55*$AD$9) -> 20.914247 | AB55: =A55*G55 -> 814.5764
A56: 216 | B56: 45 | C56: x | D56: 45 | E56: x | F56: 3 | G56: =(((B56*2+D56*2)/3.14)-F56)*F56*0.02504 -> 4.080882 | H56: 1 | I56: =CONCATENATE(B56,D56,F56) -> 45453 | J56: 2.2 | K56: 1.2 | L56: 2.9 | M56: =K56+L56 -> 4.1 | N56: 0.4 | O56: =M56+N56 -> 4.5 | P56: 2.3166 | Q56: 12.18888 | S56: =((H56*(1-$S$2)+J56+$S$3)*G56*$S$6)*$AD$9 -> 10.936764 | T56: =S56+(P56*$AD$9) -> 13.253364 | U56: =S56+(Q56*$AD$9) -> 23.125644 | V56: =((H56*(1-$V$2)+M56+$V$3)*G56*$S$6)*$AD$9 -> 18.69044 | W56: =V56+P56*$AD$9 -> 21.00704 | X56: =V56+(Q56*$AD$9) -> 30.87932 | AB56: =A56*G56 -> 881.47052
A57: 294 | B57: 50 | C57: x | D57: 50 | E57: x | F57: 1.2 | G57: =(((B57*2+D57*2)/3.14)-F57)*F57*0.02504 -> 1.8778278 | H57: 1 | I57: =CONCATENATE(B57,D57,F57) -> 50501,2 | J57: 2.5 | K57: 1.2 | L57: 3.3 | M57: =K57+L57 -> 4.5 | N57: 0.4 | O57: =M57+N57 -> 4.9 | P57: 1.87704 | Q57: 6.02316 | S57: =((H57*(1-$S$2)+J57+$S$3)*G57*$S$6)*$AD$9 -> 5.5959267 | T57: =S57+(P57*$AD$9) -> 7.4729667 | U57: =S57+(Q57*$AD$9) -> 11.619087 | AB57: =A57*G57 -> 552.08136
A58: 294 | B58: 50 | C58: x | D58: 50 | E58: x | F58: 1.5 | G58: =(((B58*2+D58*2)/3.14)-F58)*F58*0.02504 -> 2.3360167 | H58: 1 | I58: =CONCATENATE(B58,D58,F58) -> 50501,5 | J58: 2.41 | K58: 1.2 | L58: 3.21 | M58: =K58+L58 -> 4.41 | N58: 0.4 | O58: =M58+N58 -> 4.81 | P58: 1.87704 | Q58: 6.02316 | S58: =((H58*(1-$S$2)+J58+$S$3)*G58*$S$6)*$AD$9 -> 6.7510882 | T58: =S58+(P58*$AD$9) -> 8.6281282 | U58: =S58+(Q58*$AD$9) -> 12.774248 | V58: =((H58*(1-$V$2)+M58+$V$3)*G58*$S$6)*$AD$9 -> 11.423122 | W58: =V58+P58*$AD$9 -> 13.300162 | X58: =V58+(Q58*$AD$9) -> 17.446282 | AB58: =A58*G58 -> 686.78891
A59: 294 | B59: 50 | C59: x | D59: 50 | E59: x | F59: 2 | G59: =(((B59*2+D59*2)/3.14)-F59)*F59*0.02504 -> 3.0896489 | H59: 1 | I59: =CONCATENATE(B59,D59,F59) -> 50502 | J59: 2.13 | K59: 1.47 | L59: 2.78 | M59: =K59+L59 -> 4.25 | N59: 0.4 | O59: =M59+N59 -> 4.65 | P59: 2.06712 | Q59: 8.36352 | S59: =((H59*(1-$S$2)+J59+$S$3)*G59*$S$6)*$AD$9 -> 8.0639837 | T59: =S59+(P59*$AD$9) -> 10.131104 | U59: =S59+(Q59*$AD$9) -> 16.427504 | V59: =((H59*(1-$V$2)+M59+$V$3)*G59*$S$6)*$AD$9 -> 14.614039 | W59: =V59+P59*$AD$9 -> 16.681159 | X59: =V59+(Q59*$AD$9) -> 22.977559 | Y59: =((H59*(1-$Y$2)+O59+$Y$3)*G59*$S$6)*$AD$9 -> 15.911692 | Z59: =Y59+P59*$AD$9 -> 17.978812 | AA59: =Y59+(Q59*$AD$9) -> 24.275212 | AB59: =A59*G59 -> 908.35678
A60: 216 | B60: 50 | C60: x | D60: 50 | E60: x | F60: 2.5 | G60: =(((B60*2+D60*2)/3.14)-F60)*F60*0.02504 -> 3.8307611 | H60: 1 | I60: =CONCATENATE(B60,D60,F60) -> 50502,5 | J60: 2.14 | K60: 1.3 | L60: 2.74 | M60: =K60+L60 -> 4.04 | N60: 0.4 | O60: =M60+N60 -> 4.44 | P60: 2.23344 | Q60: 12.97296 | S60: =((H60*(1-$S$2)+J60+$S$3)*G60*$S$6)*$AD$9 -> 10.036594 | T60: =S60+(P60*$AD$9) -> 12.270034 | U60: =S60+(Q60*$AD$9) -> 23.009554 | V60: =((H60*(1-$V$2)+M60+$V$3)*G60*$S$6)*$AD$9 -> 17.31504 | W60: =V60+P60*$AD$9 -> 19.54848 | X60: =V60+(Q60*$AD$9) -> 30.288 | AB60: =A60*G60 -> 827.44441
A61: 216 | B61: 50 | C61: x | D61: 50 | E61: x | F61: 3 | G61: =(((B61*2+D61*2)/3.14)-F61)*F61*0.02504 -> 4.5593534 | H61: 1 | I61: =CONCATENATE(B61,D61,F61) -> 50503 | J61: 2.09 | K61: 1.2 | L61: 2.79 | M61: =K61+L61 -> 3.99 | N61: 0.4 | O61: =M61+N61 -> 4.39 | P61: 2.5542 | Q61: 13.5432 | S61: =((H61*(1-$S$2)+J61+$S$3)*G61*$S$6)*$AD$9 -> 11.717538 | T61: =S61+(P61*$AD$9) -> 14.271738 | U61: =S61+(Q61*$AD$9) -> 25.260738 | V61: =((H61*(1-$V$2)+M61+$V$3)*G61*$S$6)*$AD$9 -> 20.38031 | W61: =V61+P61*$AD$9 -> 22.93451 | X61: =V61+(Q61*$AD$9) -> 33.92351 | Y61: =((H61*(1-$Y$2)+O61+$Y$3)*G61*$S$6)*$AD$9 -> 22.295238 | Z61: =Y61+P61*$AD$9 -> 24.849438 | AA61: =Y61+(Q61*$AD$9) -> 35.838438 | AB61: =A61*G61 -> 984.82033
A62: 150 | B62: 50 | C62: x | D62: 50 | E62: x | F62: 4 | G62: =(((B62*2+D62*2)/3.14)-F62)*F62*0.02504 -> 5.9789778 | H62: 1 | I62: =CONCATENATE(B62,D62,F62) -> 50504 | J62: 2.12 | K62: 1.2 | L62: 2.82 | M62: =K62+L62 -> 4.02 | N62: 0.4 | O62: =M62+N62 -> 4.42 | P62: 3.6828 | Q62: 13.5432 | S62: =((H62*(1-$S$2)+J62+$S$3)*G62*$S$6)*$AD$9 -> 15.545342 | T62: =S62+(P62*$AD$9) -> 19.228142 | U62: =S62+(Q62*$AD$9) -> 29.088542 | V62: =((H62*(1-$V$2)+M62+$V$3)*G62*$S$6)*$AD$9 -> 26.9054 | W62: =V62+P62*$AD$9 -> 30.5882 | X62: =V62+(Q62*$AD$9) -> 40.4486 | Y62: =((H62*(1-$Y$2)+O62+$Y$3)*G62*$S$6)*$AD$9 -> 29.416571 | Z62: =Y62+P62*$AD$9 -> 33.099371 | AA62: =Y62+(Q62*$AD$9) -> 42.959771 | AB62: =A62*G62 -> 896.84668
A63: 150 | B63: 50 | C63: x | D63: 50 | E63: x | F63: 5 | G63: =(((B63*2+D63*2)/3.14)-F63)*F63*0.02504 -> 7.3485223 | H63: 1 | I63: =CONCATENATE(B63,D63,F63) -> 50505 | J63: 2.19 | K63: 1.2 | L63: 2.89 | M63: =K63+L63 -> 4.09 | N63: 0.4 | O63: =M63+N63 -> 4.49 | P63: 4.14612 | Q63: 13.5432 | S63: =((H63*(1-$S$2)+J63+$S$3)*G63*$S$6)*$AD$9 -> 19.620555 | T63: =S63+(P63*$AD$9) -> 23.766675 | U63: =S63+(Q63*$AD$9) -> 33.163755 | V63: =((H63*(1-$V$2)+M63+$V$3)*G63*$S$6)*$AD$9 -> 33.582747 | W63: =V63+P63*$AD$9 -> 37.728867 | X63: =V63+(Q63*$AD$9) -> 47.125947 | Y63: =((H63*(1-$Y$2)+O63+$Y$3)*G63*$S$6)*$AD$9 -> 36.669126 | Z63: =Y63+P63*$AD$9 -> 40.815246 | AA63: =Y63+(Q63*$AD$9) -> 50.212326 | AB63: =A63*G63 -> 1102.2783
A64: 96 | B64: 50 | C64: x | D64: 50 | E64: x | F64: 6 | G64: =(((B64*2+D64*2)/3.14)-F64)*F64*0.02504 -> 8.6679868 | S64: Prices on Demand | AB64: =A64*G64 -> 832.12673
A65: 294 | B65: 60 | C65: x | D65: 60 | E65: x | F65: 1.5 | G65: =(((B65*2+D65*2)/3.14)-F65)*F65*0.02504 -> 2.814488 | H65: 1 | I65: =CONCATENATE(B65,D65,F65) -> 60601,5 | J65: 2.43 | K65: 1.2 | L65: 3.23 | M65: =K65+L65 -> 4.43 | N65: 0.4 | O65: =M65+N65 -> 4.83 | P65: 2.2572 | Q65: 7.22304 | S65: =((H65*(1-$S$2)+J65+$S$3)*G65*$S$6)*$AD$9 -> 8.1901602 | T65: =S65+(P65*$AD$9) -> 10.44736 | U65: =S65+(Q65*$AD$9) -> 15.4132 | V65: =((H65*(1-$V$2)+M65+$V$3)*G65*$S$6)*$AD$9 -> 13.819136 | W65: =V65+P65*$AD$9 -> 16.076336 | X65: =V65+(Q65*$AD$9) -> 21.042176 | AB65: =A65*G65 -> 827.45948
A66: 294 | B66: 60 | C66: x | D66: 60 | E66: x | F66: 2 | G66: =(((B66*2+D66*2)/3.14)-F66)*F66*0.02504 -> 3.7276107 | H66: 1 | I66: =CONCATENATE(B66,D66,F66) -> 60602 | J66: 2.12 | K66: 1.47 | L66: 2.767 | M66: =K66+L66 -> 4.237 | N66: 0.4 | O66: =M66+N66 -> 4.637 | P66: 2.45916 | Q66: 10.0386 | S66: =((H66*(1-$S$2)+J66+$S$3)*G66*$S$6)*$AD$9 -> 9.6917878 | T66: =S66+(P66*$AD$9) -> 12.150948 | U66: =S66+(Q66*$AD$9) -> 19.730388 | V66: =((H66*(1-$V$2)+M66+$V$3)*G66*$S$6)*$AD$9 -> 17.58314 | W66: =V66+P66*$AD$9 -> 20.0423 | X66: =V66+(Q66*$AD$9) -> 27.62174 | Y66: =((H66*(1-$Y$2)+O66+$Y$3)*G66*$S$6)*$AD$9 -> 19.148736 | Z66: =Y66+P66*$AD$9 -> 21.607896 | AA66: =Y66+(Q66*$AD$9) -> 29.187336 | AB66: =A66*G66 -> 1095.9175
A67: 180 | B67: 60 | C67: x | D67: 60 | E67: x | F67: 2.5 | G67: =(((B67*2+D67*2)/3.14)-F67)*F67*0.02504 -> 4.6282134 | H67: 1 | I67: =CONCATENATE(B67,D67,F67) -> 60602,5 | J67: 2.14 | K67: 1.3 | L67: 2.74 | M67: =K67+L67 -> 4.04 | N67: 0.4 | O67: =M67+N67 -> 4.44 | P67: 2.81556 | Q67: 15.5628 | S67: =((H67*(1-$S$2)+J67+$S$3)*G67*$S$6)*$AD$9 -> 12.125919 | T67: =S67+(P67*$AD$9) -> 14.941479 | U67: =S67+(Q67*$AD$9) -> 27.688719 | V67: =((H67*(1-$V$2)+M67+$V$3)*G67*$S$6)*$AD$9 -> 20.919524 | W67: =V67+P67*$AD$9 -> 23.735084 | X67: =V67+(Q67*$AD$9) -> 36.482324 | AB67: =A67*G67 -> 833.07841
A68: 216 | B68: 60 | C68: x | D68: 60 | E68: x | F68: 3 | G68: =(((B68*2+D68*2)/3.14)-F68)*F68*0.02504 -> 5.5162961 | H68: 1 | I68: =CONCATENATE(B68,D68,F68) -> 60603 | J68: 2.09 | K68: 1.2 | L68: 2.79 | M68: =K68+L68 -> 3.99 | N68: 0.4 | O68: =M68+N68 -> 4.39 | P68: 3.07692 | Q68: 16.25184 | S68: =((H68*(1-$S$2)+J68+$S$3)*G68*$S$6)*$AD$9 -> 14.176881 | T68: =S68+(P68*$AD$9) -> 17.253801 | U68: =S68+(Q68*$AD$9) -> 30.428721 | V68: =((H68*(1-$V$2)+M68+$V$3)*G68*$S$6)*$AD$9 -> 24.657843 | W68: =V68+P68*$AD$9 -> 27.734763 | X68: =V68+(Q68*$AD$9) -> 40.909683 | Y68: =((H68*(1-$Y$2)+O68+$Y$3)*G68*$S$6)*$AD$9 -> 26.974688 | Z68: =Y68+P68*$AD$9 -> 30.051608 | AA68: =Y68+(Q68*$AD$9) -> 43.226528 | AB68: =A68*G68 -> 1191.5199
A69: 150 | B69: 60 | C69: x | D69: 60 | E69: x | F69: 4 | G69: =(((B69*2+D69*2)/3.14)-F69)*F69*0.02504 -> 7.2549014 | H69: 1 | I69: =CONCATENATE(B69,D69,F69) -> 60604 | J69: 2.12 | K69: 1.2 | L69: 2.82 | M69: =K69+L69 -> 4.02 | N69: 0.4 | O69: =M69+N69 -> 4.42 | P69: 4.44312 | Q69: 16.25184 | S69: =((H69*(1-$S$2)+J69+$S$3)*G69*$S$6)*$AD$9 -> 18.862744 | T69: =S69+(P69*$AD$9) -> 23.305864 | U69: =S69+(Q69*$AD$9) -> 35.114584 | V69: =((H69*(1-$V$2)+M69+$V$3)*G69*$S$6)*$AD$9 -> 32.647056 | W69: =V69+P69*$AD$9 -> 37.090176 | X69: =V69+(Q69*$AD$9) -> 48.898896 | Y69: =((H69*(1-$Y$2)+O69+$Y$3)*G69*$S$6)*$AD$9 -> 35.694115 | Z69: =Y69+P69*$AD$9 -> 40.137235 | AA69: =Y69+(Q69*$AD$9) -> 51.945955 | AB69: =A69*G69 -> 1088.2352
A70: 96 | B70: 60 | C70: x | D70: 60 | E70: x | F70: 5 | G70: =(((B70*2+D70*2)/3.14)-F70)*F70*0.02504 -> 8.9434268 | H70: 1 | I70: =CONCATENATE(B70,D70,F70) -> 60605 | J70: 2.14 | K70: 1.2 | L70: 2.84 | M70: =K70+L70 -> 4.04 | N70: 0.4 | O70: =M70+N70 -> 4.44 | P70: 4.95396 | Q70: 16.25184 | S70: =((H70*(1-$S$2)+J70+$S$3)*G70*$S$6)*$AD$9 -> 23.431778 | T70: =S70+(P70*$AD$9) -> 28.385738 | U70: =S70+(Q70*$AD$9) -> 39.683618 | V70: =((H70*(1-$V$2)+M70+$V$3)*G70*$S$6)*$AD$9 -> 40.424289 | W70: =V70+P70*$AD$9 -> 45.378249 | X70: =V70+(Q70*$AD$9) -> 56.676129 | Y70: =((H70*(1-$Y$2)+O70+$Y$3)*G70*$S$6)*$AD$9 -> 44.180528 | Z70: =Y70+P70*$AD$9 -> 49.134488 | AA70: =Y70+(Q70*$AD$9) -> 60.432368 | AB70: =A70*G70 -> 858.56897
A71: 96 | B71: 60 | C71: x | D71: 60 | E71: x | F71: 6 | G71: =(((B71*2+D71*2)/3.14)-F71)*F71*0.02504 -> 10.581872 | S71: Prices on Demand | AB71: =A71*G71 -> 1015.8597
A72: 216 | B72: 70 | C72: x | D72: 70 | E72: x | F72: 2 | G72: =(((B72*2+D72*2)/3.14)-F72)*F72*0.02504 -> 4.3655725 | H72: 1 | I72: =CONCATENATE(B72,D72,F72) -> 70702 | J72: 2.18 | K72: 1.47 | L72: 2.83 | M72: =K72+L72 -> 4.3 | N72: 0.4 | O72: =M72+N72 -> 4.7 | P72: 2.87496 | Q72: 17.55864 | S72: =((H72*(1-$S$2)+J72+$S$3)*G72*$S$6)*$AD$9 -> 11.612423 | T72: =S72+(P72*$AD$9) -> 14.487383 | U72: =S72+(Q72*$AD$9) -> 29.171063 | V72: =((H72*(1-$V$2)+M72+$V$3)*G72*$S$6)*$AD$9 -> 20.867436 | W72: =V72+P72*$AD$9 -> 23.742396 | X72: =V72+(Q72*$AD$9) -> 38.426076 | AB72: =A72*G72 -> 942.96366
A73: 150 | B73: 70 | C73: x | D73: 70 | E73: x | F73: 3 | G73: =(((B73*2+D73*2)/3.14)-F73)*F73*0.02504 -> 6.4732387 | H73: 1 | I73: =CONCATENATE(B73,D73,F73) -> 70703 | J73: 2.15 | K73: 1.2 | L73: 2.85 | M73: =K73+L73 -> 4.05 | N73: 0.4 | O73: =M73+N73 -> 4.45 | P73: 3.58776 | Q73: 28.44072 | S73: =((H73*(1-$S$2)+J73+$S$3)*G73*$S$6)*$AD$9 -> 17.024618 | T73: =S73+(P73*$AD$9) -> 20.612378 | U73: =S73+(Q73*$AD$9) -> 45.465338 | V73: =((H73*(1-$V$2)+M73+$V$3)*G73*$S$6)*$AD$9 -> 29.323771 | W73: =V73+P73*$AD$9 -> 32.911531 | X73: =V73+(Q73*$AD$9) -> 57.764491 | Y73: =((H73*(1-$Y$2)+O73+$Y$3)*G73*$S$6)*$AD$9 -> 32.042532 | Z73: =Y73+P73*$AD$9 -> 35.630292 | AA73: =Y73+(Q73*$AD$9) -> 60.483252 | AB73: =A73*G73 -> 970.98581
A74: 120 | B74: 70 | C74: x | D74: 70 | E74: x | F74: 4 | G74: =(((B74*2+D74*2)/3.14)-F74)*F74*0.02504 -> 8.530825 | H74: 1 | I74: =CONCATENATE(B74,D74,F74) -> 70704 | J74: 2.18 | K74: 1.2 | L74: 2.88 | M74: =K74+L74 -> 4.08 | N74: 0.4 | O74: =M74+N74 -> 4.48 | P74: 5.17968 | Q74: 28.44072 | S74: =((H74*(1-$S$2)+J74+$S$3)*G74*$S$6)*$AD$9 -> 22.691994 | T74: =S74+(P74*$AD$9) -> 27.871674 | U74: =S74+(Q74*$AD$9) -> 51.132714 | V74: =((H74*(1-$V$2)+M74+$V$3)*G74*$S$6)*$AD$9 -> 38.900562 | W74: =V74+P74*$AD$9 -> 44.080242 | X74: =V74+(Q74*$AD$9) -> 67.341282 | Y74: =((H74*(1-$Y$2)+O74+$Y$3)*G74*$S$6)*$AD$9 -> 42.483508 | Z74: =Y74+P74*$AD$9 -> 47.663188 | AA74: =Y74+(Q74*$AD$9) -> 70.924228 | AB74: =A74*G74 -> 1023.699
A75: 96 | B75: 70 | C75: x | D75: 70 | E75: x | F75: 5 | G75: =(((B75*2+D75*2)/3.14)-F75)*F75*0.02504 -> 10.538331 | H75: 1 | I75: =CONCATENATE(B75,D75,F75) -> 70705 | J75: 2.25 | K75: 1.2 | L75: 3 | M75: =K75+L75 -> 4.2 | N75: 0.4 | O75: =M75+N75 -> 4.6 | P75: 6.62 | Q75: 32.5 | S75: =((H75*(1-$S$2)+J75+$S$3)*G75*$S$6)*$AD$9 -> 28.769644 | T75: =S75+(P75*$AD$9) -> 35.389644 | U75: =S75+(Q75*$AD$9) -> 61.269644 | V75: =((H75*(1-$V$2)+M75+$V$3)*G75*$S$6)*$AD$9 -> 49.31939 | W75: =V75+P75*$AD$9 -> 55.93939 | X75: =V75+(Q75*$AD$9) -> 81.81939 | AB75: =A75*G75 -> 1011.6798
A76: 180 | B76: 80 | C76: x | D76: 80 | E76: x | F76: 1.5 | G76: =(((B76*2+D76*2)/3.14)-F76)*F76*0.02504 -> 3.7714307 | H76: 1 | I76: =CONCATENATE(B76,D76,F76) -> 80801,5 | J76: 2.46 | K76: 1.2 | L76: 3.26 | M76: =K76+L76 -> 4.46 | N76: 0.4 | O76: =M76+N76 -> 4.86 | P76: 3.00564 | Q76: 14.44608 | S76: =((H76*(1-$S$2)+J76+$S$3)*G76*$S$6)*$AD$9 -> 11.088006 | T76: =S76+(P76*$AD$9) -> 14.093646 | V76: =((H76*(1-$V$2)+M76+$V$3)*G76*$S$6)*$AD$9 -> 18.630868 | W76: =V76+P76*$AD$9 -> 21.636508 | X76: =V76+(Q76*$AD$9) -> 33.076948 | AB76: =A76*G76 -> 678.85753
A77: 180 | B77: 80 | C77: x | D77: 80 | E77: x | F77: 2 | G77: =(((B77*2+D77*2)/3.14)-F77)*F77*0.02504 -> 5.0035343 | H77: 1 | I77: =CONCATENATE(B77,D77,F77) -> 80802 | J77: 2.13 | K77: 1.47 | L77: 2.78 | M77: =K77+L77 -> 4.25 | N77: 0.4 | O77: =M77+N77 -> 4.65 | P77: 3.29076 | Q77: 20.06532 | S77: =((H77*(1-$S$2)+J77+$S$3)*G77*$S$6)*$AD$9 -> 13.059224 | T77: =S77+(P77*$AD$9) -> 16.349984 | U77: =S77+(Q77*$AD$9) -> 33.124544 | V77: =((H77*(1-$V$2)+M77+$V$3)*G77*$S$6)*$AD$9 -> 23.666717 | W77: =V77+P77*$AD$9 -> 26.957477 | X77: =V77+(Q77*$AD$9) -> 43.732037 | Y77: =((H77*(1-$Y$2)+O77+$Y$3)*G77*$S$6)*$AD$9 -> 25.768201 | Z77: =Y77+P77*$AD$9 -> 29.058961 | AA77: =Y77+(Q77*$AD$9) -> 45.833521 | AB77: =A77*G77 -> 900.63617
A78: 150 | B78: 80 | C78: x | D78: 80 | E78: x | F78: 2.5 | G78: =(((B78*2+D78*2)/3.14)-F78)*F78*0.02504 -> 6.2231178 | H78: 1 | I78: =CONCATENATE(B78,D78,F78) -> 80802,5 | J78: 2.15 | K78: 1.3 | L78: 2.75 | M78: =K78+L78 -> 4.05 | N78: 0.4 | O78: =M78+N78 -> 4.45 | P78: 3.564 | Q78: 31.1256 | S78: =((H78*(1-$S$2)+J78+$S$3)*G78*$S$6)*$AD$9 -> 16.3668 | T78: =S78+(P78*$AD$9) -> 19.9308 | U78: =S78+(Q78*$AD$9) -> 47.4924 | V78: =((H78*(1-$V$2)+M78+$V$3)*G78*$S$6)*$AD$9 -> 28.190724 | W78: =V78+P78*$AD$9 -> 31.754724 | X78: =V78+(Q78*$AD$9) -> 59.316324 | AB78: =A78*G78 -> 933.46768
A79: 150 | B79: 80 | C79: x | D79: 80 | E79: x | F79: 3 | G79: =(((B79*2+D79*2)/3.14)-F79)*F79*0.02504 -> 7.4301814 | H79: 1 | I79: =CONCATENATE(B79,D79,F79) -> 80803 | J79: 2.1 | K79: 1.2 | L79: 2.8 | M79: =K79+L79 -> 4 | N79: 0.4 | O79: =M79+N79 -> 4.4 | P79: 4.0986 | Q79: 32.50368 | S79: =((H79*(1-$S$2)+J79+$S$3)*G79*$S$6)*$AD$9 -> 19.169868 | T79: =S79+(P79*$AD$9) -> 23.268468 | U79: =S79+(Q79*$AD$9) -> 51.673548 | V79: =((H79*(1-$V$2)+M79+$V$3)*G79*$S$6)*$AD$9 -> 33.287213 | W79: =V79+P79*$AD$9 -> 37.385813 | X79: =V79+(Q79*$AD$9) -> 65.790893 | Y79: =((H79*(1-$Y$2)+O79+$Y$3)*G79*$S$6)*$AD$9 -> 36.407889 | Z79: =Y79+P79*$AD$9 -> 40.506489 | AA79: =Y79+(Q79*$AD$9) -> 68.911569 | AB79: =A79*G79 -> 1114.5272
A80: 96 | B80: 80 | C80: x | D80: 80 | E80: x | F80: 4 | G80: =(((B80*2+D80*2)/3.14)-F80)*F80*0.02504 -> 9.8067485 | H80: 1 | I80: =CONCATENATE(B80,D80,F80) -> 80804 | J80: 2.12 | K80: 1.2 | L80: 2.82 | M80: =K80+L80 -> 4.02 | N80: 0.4 | O80: =M80+N80 -> 4.42 | P80: 5.91624 | Q80: 32.50368 | S80: =((H80*(1-$S$2)+J80+$S$3)*G80*$S$6)*$AD$9 -> 25.497546 | T80: =S80+(P80*$AD$9) -> 31.413786 | U80: =S80+(Q80*$AD$9) -> 58.001226 | V80: =((H80*(1-$V$2)+M80+$V$3)*G80*$S$6)*$AD$9 -> 44.130368 | W80: =V80+P80*$AD$9 -> 50.046608 | X80: =V80+(Q80*$AD$9) -> 76.634048 | Y80: =((H80*(1-$Y$2)+O80+$Y$3)*G80*$S$6)*$AD$9 -> 48.249203 | Z80: =Y80+P80*$AD$9 -> 54.165443 | AA80: =Y80+(Q80*$AD$9) -> 80.752883 | AB80: =A80*G80 -> 941.44786
A81: 72 | B81: 80 | C81: x | D81: 80 | E81: x | F81: 5 | G81: =(((B81*2+D81*2)/3.14)-F81)*F81*0.02504 -> 12.133236 | H81: 1 | I81: =CONCATENATE(B81,D81,F81) -> 80805 | J81: 2.15 | K81: 1.2 | L81: 2.85 | M81: =K81+L81 -> 4.05 | N81: 0.4 | O81: =M81+N81 -> 4.45 | P81: 6.61716 | Q81: 32.50368 | S81: =((H81*(1-$S$2)+J81+$S$3)*G81*$S$6)*$AD$9 -> 31.91041 | T81: =S81+(P81*$AD$9) -> 38.52757 | U81: =S81+(Q81*$AD$9) -> 64.41409 | V81: =((H81*(1-$V$2)+M81+$V$3)*G81*$S$6)*$AD$9 -> 54.963558 | W81: =V81+P81*$AD$9 -> 61.580718 | X81: =V81+(Q81*$AD$9) -> 87.467238 | Y81: =((H81*(1-$Y$2)+O81+$Y$3)*G81*$S$6)*$AD$9 -> 60.059517 | Z81: =Y81+P81*$AD$9 -> 66.676677 | AA81: =Y81+(Q81*$AD$9) -> 92.563197 | AB81: =A81*G81 -> 873.59297
A82: 72 | B82: 80 | C82: x | D82: 80 | E82: x | F82: 6 | G82: =(((B82*2+D82*2)/3.14)-F82)*F82*0.02504 -> 14.409643 | S82: Prices on Demand | V82: Prices on Demand | AB82: =A82*G82 -> 1037.4943
A83: 120 | B83: 90 | C83: x | D83: 90 | E83: x | F83: 3 | G83: =(((B83*2+D83*2)/3.14)-F83)*F83*0.02504 -> 8.3871241 | H83: 1 | I83: =CONCATENATE(B83,D83,F83) -> 90903 | J83: 2.4 | K83: 1.2 | L83: 3.17 | M83: =K83+L83 -> 4.37 | N83: 0.4 | O83: =M83+N83 -> 4.77 | S83: =((H83*(1-$S$2)+J83+$S$3)*G83*$S$6)*$AD$9 -> 24.154917 | AB83: =A83*G83 -> 1006.4549
A84: 96 | B84: 90 | C84: x | D84: 90 | E84: x | F84: 4 | G84: =(((B84*2+D84*2)/3.14)-F84)*F84*0.02504 -> 11.082672 | H84: 1 | I84: =CONCATENATE(B84,D84,F84) -> 90904 | J84: 2.45 | K84: 1.2 | L84: 3.23 | M84: =K84+L84 -> 4.43 | N84: 0.4 | O84: =M84+N84 -> 4.83 | S84: =((H84*(1-$S$2)+J84+$S$3)*G84*$S$6)*$AD$9 -> 32.472229 | AB84: =A84*G84 -> 1063.9365
A85: 150 | B85: 100 | C85: x | D85: 100 | E85: x | F85: 2 | G85: =(((B85*2+D85*2)/3.14)-F85)*F85*0.02504 -> 6.2794578 | H85: 1 | I85: =CONCATENATE(B85,D85,F85) -> 1001002 | J85: 2.13 | K85: 1.47 | L85: 2.782 | M85: =K85+L85 -> 4.252 | N85: 0.4 | O85: =M85+N85 -> 4.652 | P85: 4.0986 | Q85: 41.80572 | S85: =((H85*(1-$S$2)+J85+$S$3)*G85*$S$6)*$AD$9 -> 16.389385 | T85: =S85+(P85*$AD$9) -> 20.487985 | U85: =S85+(Q85*$AD$9) -> 58.195105 | V85: =((H85*(1-$V$2)+M85+$V$3)*G85*$S$6)*$AD$9 -> 29.714394 | W85: =V85+P85*$AD$9 -> 33.812994 | X85: =V85+(Q85*$AD$9) -> 71.520114 | Y85: =((H85*(1-$Y$2)+O85+$Y$3)*G85*$S$6)*$AD$9 -> 32.351767 | Z85: =Y85+P85*$AD$9 -> 36.450367 | AA85: =Y85+(Q85*$AD$9) -> 74.157487 | AB85: =A85*G85 -> 941.91868
A86: 120 | B86: 100 | C86: x | D86: 100 | E86: x | F86: 3 | G86: =(((B86*2+D86*2)/3.14)-F86)*F86*0.02504 -> 9.3440668 | H86: 1 | I86: =CONCATENATE(B86,D86,F86) -> 1001003 | J86: 2.1 | K86: 1.2 | L86: 2.8 | M86: =K86+L86 -> 4 | N86: 0.4 | O86: =M86+N86 -> 4.4 | P86: 5.69052 | Q86: 67.70412 | S86: =((H86*(1-$S$2)+J86+$S$3)*G86*$S$6)*$AD$9 -> 24.107692 | T86: =S86+(P86*$AD$9) -> 29.798212 | U86: =S86+(Q86*$AD$9) -> 91.811812 | V86: =((H86*(1-$V$2)+M86+$V$3)*G86*$S$6)*$AD$9 -> 41.861419 | W86: =V86+P86*$AD$9 -> 47.551939 | X86: =V86+(Q86*$AD$9) -> 109.56554 | Y86: =((H86*(1-$Y$2)+O86+$Y$3)*G86*$S$6)*$AD$9 -> 45.785927 | Z86: =Y86+P86*$AD$9 -> 51.476447 | AA86: =Y86+(Q86*$AD$9) -> 113.49005 | AB86: =A86*G86 -> 1121.288
A87: 96 | B87: 100 | C87: x | D87: 100 | E87: x | F87: 4 | G87: =(((B87*2+D87*2)/3.14)-F87)*F87*0.02504 -> 12.358596 | H87: 1 | I87: =CONCATENATE(B87,D87,F87) -> 1001004 | J87: 2.12 | K87: 1.2 | L87: 2.82 | M87: =K87+L87 -> 4.02 | N87: 0.4 | O87: =M87+N87 -> 4.42 | P87: 7.76952 | Q87: 67.70412 | S87: =((H87*(1-$S$2)+J87+$S$3)*G87*$S$6)*$AD$9 -> 32.132349 | T87: =S87+(P87*$AD$9) -> 39.901869 | U87: =S87+(Q87*$AD$9) -> 99.836469 | V87: =((H87*(1-$V$2)+M87+$V$3)*G87*$S$6)*$AD$9 -> 55.613681 | W87: =V87+P87*$AD$9 -> 63.383201 | X87: =V87+(Q87*$AD$9) -> 123.3178 | Y87: =((H87*(1-$Y$2)+O87+$Y$3)*G87*$S$6)*$AD$9 -> 60.804291 | Z87: =Y87+P87*$AD$9 -> 68.573811 | AA87: =Y87+(Q87*$AD$9) -> 128.50841 | AB87: =A87*G87 -> 1186.4252
A88: 72 | B88: 100 | C88: x | D88: 100 | E88: x | F88: 5 | G88: =(((B88*2+D88*2)/3.14)-F88)*F88*0.02504 -> 15.323045 | H88: 1 | I88: =CONCATENATE(B88,D88,F88) -> 1001005 | J88: 2.14 | K88: 1.2 | L88: 2.84 | M88: =K88+L88 -> 4.04 | N88: 0.4 | O88: =M88+N88 -> 4.44 | P88: 9.2664 | Q88: 67.70412 | S88: =((H88*(1-$S$2)+J88+$S$3)*G88*$S$6)*$AD$9 -> 40.146377 | T88: =S88+(P88*$AD$9) -> 49.412777 | U88: =S88+(Q88*$AD$9) -> 107.8505 | V88: =((H88*(1-$V$2)+M88+$V$3)*G88*$S$6)*$AD$9 -> 69.260162 | W88: =V88+P88*$AD$9 -> 78.526562 | X88: =V88+(Q88*$AD$9) -> 136.96428 | Y88: =((H88*(1-$Y$2)+O88+$Y$3)*G88*$S$6)*$AD$9 -> 75.69584 | Z88: =Y88+P88*$AD$9 -> 84.96224 | AA88: =Y88+(Q88*$AD$9) -> 143.39996 | AB88: =A88*G88 -> 1103.2592
A89: 54 | B89: 100 | C89: x | D89: 100 | E89: x | F89: 6 | G89: =(((B89*2+D89*2)/3.14)-F89)*F89*0.02504 -> 18.237414 | S89: Prices on Demand | V89: Prices on Demand | AB89: =A89*G89 -> 984.82033
A90: 120 | B90: 120 | C90: x | D90: 120 | E90: x | F90: 2 | G90: =(((B90*2+D90*2)/3.14)-F90)*F90*0.02504 -> 7.5553814 | H90: 1 | I90: =CONCATENATE(B90,D90,F90) -> 1201202 | J90: 2.4 | K90: 1.47 | L90: 3.17 | M90: =K90+L90 -> 4.64 | N90: 0.4 | O90: =M90+N90 -> 5.04 | P90: 7.98 | S90: =((H90*(1-$S$2)+J90+$S$3)*G90*$S$6)*$AD$9 -> 21.759498 | T90: =S90+(P90*$AD$9) -> 29.739498 | V90: =((H90*(1-$V$2)+M90+$V$3)*G90*$S$6)*$AD$9 -> 38.683553 | W90: =V90+P90*$AD$9 -> 46.663553 | Y90: =((H90*(1-$Y$2)+O90+$Y$3)*G90*$S$6)*$AD$9 -> 41.856813 | Z90: =Y90+P90*$AD$9 -> 49.836813 | AB90: =A90*G90 -> 906.64577
A91: 96 | B91: 120 | C91: x | D91: 120 | E91: x | F91: 3 | G91: =(((B91*2+D91*2)/3.14)-F91)*F91*0.02504 -> 11.257952 | H91: 1 | I91: =CONCATENATE(B91,D91,F91) -> 1201203 | J91: 2.12 | K91: 1.2 | L91: 2.89 | M91: =K91+L91 -> 4.09 | N91: 0.4 | O91: =M91+N91 -> 4.49 | P91: 7.94772 | S91: =((H91*(1-$S$2)+J91+$S$3)*G91*$S$6)*$AD$9 -> 29.270675 | T91: =S91+(P91*$AD$9) -> 37.218395 | V91: =((H91*(1-$V$2)+M91+$V$3)*G91*$S$6)*$AD$9 -> 51.448841 | W91: =V91+P91*$AD$9 -> 59.396561 | Y91: =((H91*(1-$Y$2)+O91+$Y$3)*G91*$S$6)*$AD$9 -> 56.177181 | Z91: =Y91+P91*$AD$9 -> 64.124901 | AB91: =A91*G91 -> 1080.7634
A92: 72 | B92: 120 | C92: x | D92: 120 | E92: x | F92: 4 | G92: =(((B92*2+D92*2)/3.14)-F92)*F92*0.02504 -> 14.910443 | H92: 1 | I92: =CONCATENATE(B92,D92,F92) -> 1201204 | J92: 2.15 | K92: 1.2 | L92: 2.91 | M92: =K92+L92 -> 4.11 | N92: 0.4 | O92: =M92+N92 -> 4.51 | P92: 10.08612 | S92: =((H92*(1-$S$2)+J92+$S$3)*G92*$S$6)*$AD$9 -> 39.214465 | T92: =S92+(P92*$AD$9) -> 49.300585 | V92: =((H92*(1-$V$2)+M92+$V$3)*G92*$S$6)*$AD$9 -> 68.438932 | W92: =V92+P92*$AD$9 -> 78.525052 | Y92: =((H92*(1-$Y$2)+O92+$Y$3)*G92*$S$6)*$AD$9 -> 74.701318 | Z92: =Y92+P92*$AD$9 -> 84.787438 | AB92: =A92*G92 -> 1073.5519
A93: 54 | B93: 120 | C93: x | D93: 120 | E93: x | F93: 5 | G93: =(((B93*2+D93*2)/3.14)-F93)*F93*0.02504 -> 18.512854 | H93: 1 | I93: =CONCATENATE(B93,D93,F93) -> 1201205 | J93: 2.2 | K93: 1.2 | L93: 2.93 | M93: 4.1 | N93: 0.4 | O93: =M93+N93 -> 4.5 | P93: 10.08612 | S93: =((H93*(1-$S$2)+J93+$S$3)*G93*$S$6)*$AD$9 -> 49.614447 | T93: =S93+(P93*$AD$9) -> 59.700567 | V93: =((H93*(1-$V$2)+M93+$V$3)*G93*$S$6)*$AD$9 -> 84.788869 | W93: =V93+P93*$AD$9 -> 94.874989 | Y93: =((H93*(1-$Y$2)+O93+$Y$3)*G93*$S$6)*$AD$9 -> 92.564268 | Z93: =Y93+P93*$AD$9 -> 102.65039 | AB93: =A93*G93 -> 999.69409
A94: 54 | B94: 120 | C94: x | D94: 120 | E94: x | F94: 6 | G94: =(((B94*2+D94*2)/3.14)-F94)*F94*0.02504 -> 22.065184 | S94: Prices on Demand | V94: Prices on Demand | AB94: =A94*G94 -> 1191.5199
A95: 54 | B95: 140 | C95: x | D95: 140 | E95: x | F95: 3 | G95: =(((B95*2+D95*2)/3.14)-F95)*F95*0.02504 -> 13.171837 | H95: 1 | I95: =CONCATENATE(B95,D95,F95) -> 1401403 | J95: 2.3 | K95: 1.2 | L95: 3.1 | M95: =K95+L95 -> 4.3 | N95: 0.4 | O95: =M95+N95 -> 4.7 | S95: =((H95*(1-$S$2)+J95+$S$3)*G95*$S$6)*$AD$9 -> 36.617708 | AB95: =A95*G95 -> 711.27922
A96: 54 | B96: 140 | C96: x | D96: 140 | E96: x | F96: 4 | G96: =(((B96*2+D96*2)/3.14)-F96)*F96*0.02504 -> 17.46229 | H96: 1 | I96: =CONCATENATE(B96,D96,F96) -> 1401404 | J96: 2.33 | K96: 1.2 | L96: 3.13 | M96: =K96+L96 -> 4.33 | N96: 0.4 | O96: =M96+N96 -> 4.73 | S96: =((H96*(1-$S$2)+J96+$S$3)*G96*$S$6)*$AD$9 -> 49.069035 | AB96: =A96*G96 -> 942.96366
A97: 54 | B97: 140 | C97: x | D97: 140 | E97: x | F97: 5 | G97: =(((B97*2+D97*2)/3.14)-F97)*F97*0.02504 -> 21.702662 | H97: 1 | I97: =CONCATENATE(B97,D97,F97) -> 1401405 | J97: 2.38 | K97: 1.2 | L97: 3.18 | M97: =K97+L97 -> 4.38 | N97: 0.4 | O97: =M97+N97 -> 4.78 | S97: =((H97*(1-$S$2)+J97+$S$3)*G97*$S$6)*$AD$9 -> 62.069615 | AB97: =A97*G97 -> 1171.9438
A98: 24 | B98: 140 | C98: x | D98: 140 | E98: x | F98: 6 | G98: =(((B98*2+D98*2)/3.14)-F98)*F98*0.02504 -> 25.892955 | S98: Prices on Demand | AB98: =A98*G98 -> 621.43092
A99: 96 | B99: 150 | C99: x | D99: 150 | E99: x | F99: 2 | G99: =(((B99*2+D99*2)/3.14)-F99)*F99*0.02504 -> 9.4692668 | H99: 1 | I99: =CONCATENATE(B99,D99,F99) -> 1501502 | J99: 2.35 | K99: 1.47 | L99: 3.15 | M99: =K99+L99 -> 4.62 | N99: 0.4 | O99: =M99+N99 -> 5.02 | P99: 12 | S99: =((H99*(1-$S$2)+J99+$S$3)*G99*$S$6)*$AD$9 -> 26.798025 | T99: =S99+(P99*$AD$9) -> 38.798025 | V99: =((H99*(1-$V$2)+M99+$V$3)*G99*$S$6)*$AD$9 -> 48.29326 | W99: =V99+P99*$AD$9 -> 60.29326 | AB99: =A99*G99 -> 909.04961
A100: 72 | B100: 150 | C100: x | D100: 150 | E100: x | F100: 3 | G100: =(((B100*2+D100*2)/3.14)-F100)*F100*0.02504 -> 14.12878 | H100: 1 | I100: =CONCATENATE(B100,D100,F100) -> 1501503 | J100: 2.15 | K100: 1.2 | L100: 2.95 | M100: =K100+L100 -> 4.15 | N100: 0.4 | O100: =M100+N100 -> 4.55 | P100: 16 | S100: =((H100*(1-$S$2)+J100+$S$3)*G100*$S$6)*$AD$9 -> 37.158692 | T100: =S100+(P100*$AD$9) -> 53.158692 | V100: =((H100*(1-$V$2)+M100+$V$3)*G100*$S$6)*$AD$9 -> 65.416252 | W100: =V100+P100*$AD$9 -> 81.416252 | Y100: =((H100*(1-$Y$2)+O100+$Y$3)*G100*$S$6)*$AD$9 -> 71.35034 | Z100: =Y100+P100*$AD$9 -> 87.35034 | AB100: =A100*G100 -> 1017.2722
A101: 54 | B101: 150 | C101: x | D101: 150 | E101: x | F101: 4 | G101: =(((B101*2+D101*2)/3.14)-F101)*F101*0.02504 -> 18.738214 | H101: 1 | I101: =CONCATENATE(B101,D101,F101) -> 1501504 | J101: 2.18 | K101: 1.2 | L101: 2.98 | M101: =K101+L101 -> 4.18 | N101: 0.4 | O101: =M101+N101 -> 4.58 | P101: 30 | S101: =((H101*(1-$S$2)+J101+$S$3)*G101*$S$6)*$AD$9 -> 49.843648 | V101: =((H101*(1-$V$2)+M101+$V$3)*G101*$S$6)*$AD$9 -> 87.320075 | Y101: =((H101*(1-$Y$2)+O101+$Y$3)*G101*$S$6)*$AD$9 -> 95.190125 | AB101: =A101*G101 -> 1011.8635
...

Sheet ROUND TIG-LASER
A1: PRICE LIST MAY '26 | X1: DC 8.2_03
D2: DISCOUNT | O2: 0.55 | P2: 0.55 | Q2: 0.55
D3: Alloy Surcharge €/Kg | O3: 0 | P3: 0 | Q3: 0
D4: ROUND TIG-LASER | O4: 304L | P4: 316L | Q4: 316Ti | AA4: DKK | AB4: 0
AA5: EUR | AB5: 1
AA6: GBP | AB6: 0.87
E7: EXTRA % | O7: 1 | AA7: NOK | AB7: 0
D8: Rate | O8: EUR | AA8: SEK | AB8: 0
AA9: USD | AB9: 1.16
O10: BRUSHED NOT ANNEALED | S10: O.D. POLISHED G.240/320 | W10: O.D. MIRROR POLISHED
C11: MT | D11: Dimension | G11: €/kg | I11: FISSO | O11: 1.4301 | P11: 1.4404 | Q11: 1.4571 | S11: 1.4301 | T11: 1.4404 | U11: 1.4571 | W11: 1.4301 | X11: 1.4404 | Y11: 1.4571 | AA11: IN USO | AB11: =VLOOKUP(O8,$AA$4:$AB$9,2) -> 1
A12: DN | B12: POL. | C12: BDL | D12: Diam. | E12: Thk. | F12: kg/mt | G12: €/kg | I12: 304 | J12: E316L | K12: E316Ti | O12: 304 | P12: 316 L / Ti | Q12: 316 Ti | R12: SAT | S12: 304 | T12: 316 L / Ti | U12: 316 Ti | V12: LUC | W12: 304 | X12: 316 L / Ti | Y12: 316 Ti | Z12: Kg/Bdl
C13: 1050 | D13: 6 | E13: 1 | F13: =(D13-E13)*E13*0.02504 -> 0.1252 | G13: 1 | H13: =CONCATENATE(D13,E13) -> 61 | I13: 7.65 | J13: 1.9 | K13: 2.3 | L13: =I13+J13 -> 9.55 | M13: =I13+K13 -> 9.95 | O13: =((G13*(1-$O$2)+I13+$O$3)*F13*$O$7)*$AB$11 -> 1.01412 | R13: 0 | V13: 0 | Z13: =F13*C13 -> 131.46
C14: 1050 | D14: 8 | E14: 1 | F14: =(D14-E14)*E14*0.02504 -> 0.17528 | G14: 1 | H14: =CONCATENATE(D14,E14) -> 81 | I14: 6.2 | J14: 1.9 | K14: 2.3 | L14: =I14+J14 -> 8.1 | M14: =I14+K14 -> 8.5 | O14: =((G14*(1-$O$2)+I14+$O$3)*F14*$O$7)*$AB$11 -> 1.165612 | R14: 0 | V14: 0 | Z14: =F14*C14 -> 184.044
C15: 810 | D15: 10 | E15: 1 | F15: =(D15-E15)*E15*0.02504 -> 0.22536 | G15: 1 | H15: =CONCATENATE(D15,E15) -> 101 | I15: 4.74 | J15: 1.9 | K15: 2.3 | L15: =I15+J15 -> 6.64 | M15: =I15+K15 -> 7.04 | O15: =((G15*(1-$O$2)+I15+$O$3)*F15*$O$7)*$AB$11 -> 1.1696184 | R15: 0.69 | S15: =O15+R15*$AB$11 -> 1.8596184 | V15: 1.25 | W15: =O15+V15*$AB$11 -> 2.4196184 | Z15: =F15*C15 -> 182.5416
C16: 810 | D16: 10 | E16: 1.5 | F16: =(D16-E16)*E16*0.02504 -> 0.31926 | G16: 1 | H16: =CONCATENATE(D16,E16) -> 101,5 | I16: 4.532 | J16: 1.9 | K16: 2.3 | L16: =I16+J16 -> 6.432 | M16: =I16+K16 -> 6.832 | O16: =((G16*(1-$O$2)+I16+$O$3)*F16*$O$7)*$AB$11 -> 1.5905533 | P16: =((G16*(1-$P$2)+I16+J16+$P$3)*F16*$O$7)*$AB$11 -> 2.1971473 | R16: 0.69 | S16: =O16+R16*$AB$11 -> 2.2805533 | V16: 1.25 | W16: =O16+V16*$AB$11 -> 2.8405533 | Z16: =F16*C16 -> 258.6006
C17: 810 | D17: 12 | E17: 1 | F17: =(D17-E17)*E17*0.02504 -> 0.27544 | G17: 1 | H17: =CONCATENATE(D17,E17) -> 121 | I17: 4.312 | J17: 1.9 | K17: 2.3 | L17: =I17+J17 -> 6.212 | M17: =I17+K17 -> 6.612 | O17: =((G17*(1-$O$2)+I17+$O$3)*F17*$O$7)*$AB$11 -> 1.3116453 | R17: 0.68904 | S17: =O17+R17*$AB$11 -> 2.0006853 | V17: 1.25 | W17: =O17+V17*$AB$11 -> 2.5616453 | Z17: =F17*C17 -> 223.1064
C18: 810 | D18: 12 | E18: 1.5 | F18: =(D18-E18)*E18*0.02504 -> 0.39438 | G18: 1 | H18: =CONCATENATE(D18,E18) -> 121,5 | I18: 4.382 | J18: 1.9 | K18: 2.3 | L18: =I18+J18 -> 6.282 | M18: =I18+K18 -> 6.682 | O18: =((G18*(1-$O$2)+I18+$O$3)*F18*$O$7)*$AB$11 -> 1.9056442 | P18: =((G18*(1-$P$2)+I18+J18+$P$3)*F18*$O$7)*$AB$11 -> 2.6549662 | R18: 0.68904 | S18: =O18+R18*$AB$11 -> 2.5946842 | T18: =P18+R18*$AB$11 -> 3.3440062 | V18: 1.2474 | W18: =O18+V18*$AB$11 -> 3.1530442 | X18: =P18+V18*$AB$11 -> 3.9023662 | Z18: =F18*C18 -> 319.4478
C19: 810 | D19: 12 | E19: 2 | F19: =(D19-E19)*E19*0.02504 -> 0.5008 | G19: 1 | H19: =CONCATENATE(D19,E19) -> 122 | I19: 4.15 | J19: 2.05 | K19: 2.45 | L19: =I19+J19 -> 6.2 | M19: =I19+K19 -> 6.6 | O19: =((G19*(1-$O$2)+I19+$O$3)*F19*$O$7)*$AB$11 -> 2.30368 | P19: =((G19*(1-$P$2)+I19+J19+$P$3)*F19*$O$7)*$AB$11 -> 3.33032 | R19: 0.71 | S19: =O19+R19*$AB$11 -> 3.01368 | V19: 1.2 | W19: =O19+V19*$AB$11 -> 3.50368 | Z19: =F19*C19 -> 405.648
C20: 810 | D20: 13 | E20: 1 | F20: =(D20-E20)*E20*0.02504 -> 0.30048 | G20: 1 | H20: =CONCATENATE(D20,E20) -> 131 | I20: 4.09 | J20: 1.9 | K20: 2.3 | L20: =I20+J20 -> 5.99 | M20: =I20+K20 -> 6.39 | O20: =((G20*(1-$O$2)+I20+$O$3)*F20*$O$7)*$AB$11 -> 1.3641792 | R20: 0.68904 | S20: =O20+R20*$AB$11 -> 2.0532192 | V20: 1.2474 | Z20: =F20*C20 -> 243.3888
C21: 810 | D21: 13 | E21: 1.5 | F21: =(D21-E21)*E21*0.02504 -> 0.43194 | G21: 1 | H21: =CONCATENATE(D21,E21) -> 131,5 | I21: 3.92 | J21: 1.9 | K21: 2.3 | L21: =I21+J21 -> 5.82 | M21: =I21+K21 -> 6.22 | O21: =((G21*(1-$O$2)+I21+$O$3)*F21*$O$7)*$AB$11 -> 1.8875778 | P21: =((G21*(1-$P$2)+I21+J21+$P$3)*F21*$O$7)*$AB$11 -> 2.7082638 | R21: 0.69 | S21: =O21+R21*$AB$11 -> 2.5775778 | T21: =P21+R21*$AB$11 -> 3.3982638 | V21: 1.25 | Z21: =F21*C21 -> 349.8714
C22: 678 | D22: 14 | E22: 1 | F22: =(D22-E22)*E22*0.02504 -> 0.32552 | G22: 1 | H22: =CONCATENATE(D22,E22) -> 141 | I22: 3.582 | J22: 1.9 | K22: 2.3 | L22: =I22+J22 -> 5.482 | M22: =I22+K22 -> 5.882 | O22: =((G22*(1-$O$2)+I22+$O$3)*F22*$O$7)*$AB$11 -> 1.3124966 | R22: 0.68904 | S22: =O22+R22*$AB$11 -> 2.0015366 | V22: 1.2474 | W22: =O22+V22*$AB$11 -> 2.5598966 | Z22: =F22*C22 -> 220.70256
C23: 678 | D23: 14 | E23: 1.5 | F23: =(D23-E23)*E23*0.02504 -> 0.4695 | G23: 1 | H23: =CONCATENATE(D23,E23) -> 141,5 | I23: 3.642 | J23: 1.9 | K23: 2.3 | L23: =I23+J23 -> 5.542 | M23: =I23+K23 -> 5.942 | O23: =((G23*(1-$O$2)+I23+$O$3)*F23*$O$7)*$AB$11 -> 1.921194 | P23: =((G23*(1-$P$2)+I23+J23+$P$3)*F23*$O$7)*$AB$11 -> 2.813244 | R23: 0.68904 | S23: =O23+R23*$AB$11 -> 2.610234 | T23: =P23+R23*$AB$11 -> 3.502284 | V23: 1.2474 | W23: =O23+V23*$AB$11 -> 3.168594 | X23: =P23+V23*$AB$11 -> 4.060644 | Z23: =F23*C23 -> 318.321
C24: 678 | D24: 14 | E24: 2 | F24: =(D24-E24)*E24*0.02504 -> 0.60096 | G24: 1 | H24: =CONCATENATE(D24,E24) -> 142 | I24: 3.51 | J24: 2.05 | K24: 2.45 | L24: =I24+J24 -> 5.56 | M24: =I24+K24 -> 5.96 | O24: =((G24*(1-$O$2)+I24+$O$3)*F24*$O$7)*$AB$11 -> 2.3798016 | P24: =((G24*(1-$P$2)+I24+J24+$P$3)*F24*$O$7)*$AB$11 -> 3.6117696 | R24: 0.7128 | S24: =O24+R24*$AB$11 -> 3.0926016 | T24: =P24+R24*$AB$11 -> 4.3245696 | V24: 1.2474 | W24: =O24+V24*$AB$11 -> 3.6272016 | X24: =P24+V24*$AB$11 -> 4.8591696 | Z24: =F24*C24 -> 407.45088
C25: 678 | D25: 15 | E25: 1 | F25: =(D25-E25)*E25*0.02504 -> 0.35056 | G25: 1 | H25: =CONCATENATE(D25,E25) -> 151 | I25: 3.542 | J25: 1.9 | K25: 2.3 | L25: =I25+J25 -> 5.442 | M25: =I25+K25 -> 5.842 | O25: =((G25*(1-$O$2)+I25+$O$3)*F25*$O$7)*$AB$11 -> 1.3994355 | R25: 0.68904 | S25: =O25+R25*$AB$11 -> 2.0884755 | V25: 1.2474 | W25: =O25+V25*$AB$11 -> 2.6468355 | Z25: =F25*C25 -> 237.67968
C26: 678 | D26: 15 | E26: 1.2 | F26: =(D26-E26)*E26*0.02504 -> 0.4146624 | G26: 1 | H26: =CONCATENATE(D26,E26) -> 151,2 | I26: 3.58 | J26: 1.9 | K26: 2.3 | L26: =I26+J26 -> 5.48 | M26: =I26+K26 -> 5.88 | O26: =((G26*(1-$O$2)+I26+$O$3)*F26*$O$7)*$AB$11 -> 1.6710895 | R26: 0.69 | S26: =O26+R26*$AB$11 -> 2.3610895 | V26: 1.25 | W26: =O26+V26*$AB$11 -> 2.9210895 | Z26: =F26*C26 -> 281.14111
C27: 678 | D27: 15 | E27: 1.5 | F27: =(D27-E27)*E27*0.02504 -> 0.50706 | G27: 1 | H27: =CONCATENATE(D27,E27) -> 151,5 | I27: 3.602 | J27: 1.9 | K27: 2.3 | L27: =I27+J27 -> 5.502 | M27: =I27+K27 -> 5.902 | O27: =((G27*(1-$O$2)+I27+$O$3)*F27*$O$7)*$AB$11 -> 2.0546071 | P27: =((G27*(1-$P$2)+I27+J27+$P$3)*F27*$O$7)*$AB$11 -> 3.0180211 | R27: 0.68904 | S27: =O27+R27*$AB$11 -> 2.7436471 | T27: =P27+R27*$AB$11 -> 3.7070611 | V27: 1.2474 | W27: =O27+V27*$AB$11 -> 3.3020071 | X27: =P27+V27*$AB$11 -> 4.2654211 | Z27: =F27*C27 -> 343.78668
C28: 678 | D28: 15 | E28: 2 | F28: =(D28-E28)*E28*0.02504 -> 0.65104 | G28: 1 | H28: =CONCATENATE(D28,E28) -> 152 | I28: 3.56 | J28: 2.05 | K28: 2.45 | L28: =I28+J28 -> 5.61 | M28: =I28+K28 -> 6.01 | O28: =((G28*(1-$O$2)+I28+$O$3)*F28*$O$7)*$AB$11 -> 2.6106704 | P28: =((G28*(1-$P$2)+I28+J28+$P$3)*F28*$O$7)*$AB$11 -> 3.9453024 | R28: 0.7128 | S28: =O28+R28*$AB$11 -> 3.3234704 | T28: =P28+R28*$AB$11 -> 4.6581024 | V28: 1.2474 | W28: =O28+V28*$AB$11 -> 3.8580704 | X28: =P28+V28*$AB$11 -> 5.1927024 | Z28: =F28*C28 -> 441.40512
C29: 678 | D29: 16 | E29: 1 | F29: =(D29-E29)*E29*0.02504 -> 0.3756 | G29: 1 | H29: =CONCATENATE(D29,E29) -> 161 | I29: 3.462 | J29: 1.9 | K29: 2.3 | L29: =I29+J29 -> 5.362 | M29: =I29+K29 -> 5.762 | O29: =((G29*(1-$O$2)+I29+$O$3)*F29*$O$7)*$AB$11 -> 1.4693472 | R29: 0.68904 | S29: =O29+R29*$AB$11 -> 2.1583872 | V29: 1.2474 | W29: =O29+V29*$AB$11 -> 2.7167472 | Z29: =F29*C29 -> 254.6568
C30: 678 | D30: 16 | E30: 1.2 | F30: =(D30-E30)*E30*0.02504 -> 0.4447104 | G30: 1 | H30: =CONCATENATE(D30,E30) -> 161,2 | I30: 3.31 | J30: 1.9 | K30: 2.3 | L30: =I30+J30 -> 5.21 | M30: =I30+K30 -> 5.61 | O30: =((G30*(1-$O$2)+I30+$O$3)*F30*$O$7)*$AB$11 -> 1.6721111 | R30: 0.68904 | S30: =O30+R30*$AB$11 -> 2.3611511 | V30: 1.2474 | W30: =O30+V30*$AB$11 -> 2.9195111 | Z30: =F30*C30 -> 301.51365
C31: 678 | D31: 16 | E31: 1.5 | F31: =(D31-E31)*E31*0.02504 -> 0.54462 | G31: 1 | H31: =CONCATENATE(D31,E31) -> 161,5 | I31: 3.412 | J31: 1.9 | K31: 2.3 | L31: =I31+J31 -> 5.312 | M31: =I31+K31 -> 5.712 | O31: =((G31*(1-$O$2)+I31+$O$3)*F31*$O$7)*$AB$11 -> 2.1033224 | P31: =((G31*(1-$P$2)+I31+J31+$P$3)*F31*$O$7)*$AB$11 -> 3.1381004 | Q31: =((G31*(1-$Q$2)+I31+K31+$Q$3)*F31*$O$7)*$AB$11 -> 3.3559484 | R31: 0.68904 | S31: =O31+R31*$AB$11 -> 2.7923624 | T31: =P31+R31*$AB$11 -> 3.8271404 | U31: =Q31+R31*$AB$11 -> 4.0449884 | V31: 1.2474 | W31: =O31+V31*$AB$11 -> 3.3507224 | X31: =P31+V31*$AB$11 -> 4.3855004 | Y31: =Q31+V31*$AB$11 -> 4.6033484 | Z31: =F31*C31 -> 369.25236
C32: 678 | D32: 16 | E32: 2 | F32: =(D32-E32)*E32*0.02504 -> 0.70112 | G32: 1 | H32: =CONCATENATE(D32,E32) -> 162 | I32: 3.31 | J32: 2.05 | K32: 2.45 | L32: =I32+J32 -> 5.36 | M32: =I32+K32 -> 5.76 | O32: =((G32*(1-$O$2)+I32+$O$3)*F32*$O$7)*$AB$11 -> 2.6362112 | P32: =((G32*(1-$P$2)+I32+J32+$P$3)*F32*$O$7)*$AB$11 -> 4.0735072 | Q32: =((G32*(1-$Q$2)+I32+K32+$Q$3)*F32*$O$7)*$AB$11 -> 4.3539552 | R32: 0.7128 | S32: =O32+R32*$AB$11 -> 3.3490112 | T32: =P32+R32*$AB$11 -> 4.7863072 | U32: =Q32+R32*$AB$11 -> 5.0667552 | V32: 1.2474 | W32: =O32+V32*$AB$11 -> 3.8836112 | X32: =P32+V32*$AB$11 -> 5.3209072 | Y32: =Q32+V32*$AB$11 -> 5.6013552 | Z32: =F32*C32 -> 475.35936
A33: 10 | B33: 3/8" | C33: 678 | D33: 17.2 | E33: 1.5 | F33: =(D33-E33)*E33*0.02504 -> 0.589692 | G33: 1 | H33: =CONCATENATE(D33,E33) -> 17,21,5 | I33: 3.212 | J33: 1.9 | K33: 2.3 | L33: =I33+J33 -> 5.112 | M33: =I33+K33 -> 5.512 | O33: =((G33*(1-$O$2)+I33+$O$3)*F33*$O$7)*$AB$11 -> 2.1594521 | P33: =((G33*(1-$P$2)+I33+J33+$P$3)*F33*$O$7)*$AB$11 -> 3.2798669 | Q33: =((G33*(1-$Q$2)+I33+K33+$Q$3)*F33*$O$7)*$AB$11 -> 3.5157437 | R33: 0.68904 | S33: =O33+R33*$AB$11 -> 2.8484921 | T33: =P33+R33*$AB$11 -> 3.9689069 | U33: =Q33+R33*$AB$11 -> 4.2047837 | V33: 1.2474 | W33: =O33+V33*$AB$11 -> 3.4068521 | X33: =P33+V33*$AB$11 -> 4.5272669 | Y33: =Q33+V33*$AB$11 -> 4.7631437 | Z33: =F33*C33 -> 399.81118
C34: 678 | D34: 17.2 | E34: 1.6 | F34: =(D34-E34)*E34*0.02504 -> 0.6249984 | G34: 1 | H34: =CONCATENATE(D34,E34) -> 17,21,6 | I34: 3.212 | J34: 1.9 | K34: 2.3 | L34: =I34+J34 -> 5.112 | M34: =I34+K34 -> 5.512 | O34: =((G34*(1-$O$2)+I34+$O$3)*F34*$O$7)*$AB$11 -> 2.2887441 | P34: =((G34*(1-$P$2)+I34+J34+$P$3)*F34*$O$7)*$AB$11 -> 3.4762411 | R34: 0.68904 | S34: =O34+R34*$AB$11 -> 2.9777841 | V34: 1.2474 | Z34: =F34*C34 -> 423.74892
C35: 678 | D35: 17.2 | E35: 2 | F35: =(D35-E35)*E35*0.02504 -> 0.761216 | G35: 1 | H35: =CONCATENATE(D35,E35) -> 17,22 | I35: 2.96 | J35: 2.05 | K35: 2.45 | L35: =I35+J35 -> 5.01 | M35: =I35+K35 -> 5.41 | O35: =((G35*(1-$O$2)+I35+$O$3)*F35*$O$7)*$AB$11 -> 2.5957466 | P35: =((G35*(1-$P$2)+I35+J35+$P$3)*F35*$O$7)*$AB$11 -> 4.1562394 | Q35: =((G35*(1-$Q$2)+I35+K35+$Q$3)*F35*$O$7)*$AB$11 -> 4.4607258 | R35: 0.7128 | S35: =O35+R35*$AB$11 -> 3.3085466 | T35: =P35+R35*$AB$11 -> 4.8690394 | U35: =Q35+R35*$AB$11 -> 5.1735258 | V35: 1.2474 | W35: =O35+V35*$AB$11 -> 3.8431466 | X35: =P35+V35*$AB$11 -> 5.4036394 | Y35: =Q35+V35*$AB$11 -> 5.7081258 | Z35: =F35*C35 -> 516.10445
C36: 678 | D36: 17.2 | E36: 2.5 | F36: =(D36-E36)*E36*0.02504 -> 0.92022 | G36: 1 | H36: =CONCATENATE(D36,E36) -> 17,22,5 | I36: 3.11 | J36: 1.9 | K36: 2.3 | L36: =I36+J36 -> 5.01 | M36: =I36+K36 -> 5.41 | O36: =((G36*(1-$O$2)+I36+$O$3)*F36*$O$7)*$AB$11 -> 3.2759832 | P36: =((G36*(1-$P$2)+I36+J36+$P$3)*F36*$O$7)*$AB$11 -> 5.0244012 | Q36: =((G36*(1-$Q$2)+I36+K36+$Q$3)*F36*$O$7)*$AB$11 -> 5.3924892 | R36: 0.86 | S36: =O36+R36*$AB$11 -> 4.1359832 | T36: =P36+R36*$AB$11 -> 5.8844012 | U36: =Q36+R36*$AB$11 -> 6.2524892 | V36: 1.72 | W36: =O36+V36*$AB$11 -> 4.9959832 | X36: =P36+V36*$AB$11 -> 6.7444012 | Y36: =Q36+V36*$AB$11 -> 7.1124892 | Z36: =F36*C36 -> 623.90916
C37: 678 | D37: 18 | E37: 1 | F37: =(D37-E37)*E37*0.02504 -> 0.42568 | G37: 1 | H37: =CONCATENATE(D37,E37) -> 181 | I37: 3.362 | J37: 1.9 | K37: 2.3 | L37: =I37+J37 -> 5.262 | M37: =I37+K37 -> 5.662 | O37: =((G37*(1-$O$2)+I37+$O$3)*F37*$O$7)*$AB$11 -> 1.6226922 | R37: 0.68904 | S37: =O37+R37*$AB$11 -> 2.3117322 | V37: 1.2474 | W37: =O37+V37*$AB$11 -> 2.8700922 | Z37: =F37*C37 -> 288.61104
C38: 678 | D38: 18 | E38: 1.2 | F38: =(D38-E38)*E38*0.02504 -> 0.5048064 | G38: 1 | H38: =CONCATENATE(D38,E38) -> 181,2 | I38: 3.11 | J38: 1.9 | K38: 2.3 | L38: =I38+J38 -> 5.01 | M38: =I38+K38 -> 5.41 | O38: =((G38*(1-$O$2)+I38+$O$3)*F38*$O$7)*$AB$11 -> 1.7971108 | R38: 0.68904 | S38: =O38+R38*$AB$11 -> 2.4861508 | V38: 1.2474 | W38: =O38+V38*$AB$11 -> 3.0445108 | Z38: =F38*C38 -> 342.25874
C39: 678 | D39: 18 | E39: 1.5 | F39: =(D39-E39)*E39*0.02504 -> 0.61974 | G39: 1 | H39: =CONCATENATE(D39,E39) -> 181,5 | I39: 3.322 | J39: 1.9 | K39: 2.3 | L39: =I39+J39 -> 5.222 | M39: =I39+K39 -> 5.622 | O39: =((G39*(1-$O$2)+I39+$O$3)*F39*$O$7)*$AB$11 -> 2.3376593 | P39: =((G39*(1-$P$2)+I39+J39+$P$3)*F39*$O$7)*$AB$11 -> 3.5151653 | Q39: =((G39*(1-$Q$2)+I39+K39+$Q$3)*F39*$O$7)*$AB$11 -> 3.7630613 | R39: 0.68904 | S39: =O39+R39*$AB$11 -> 3.0266993 | T39: =P39+R39*$AB$11 -> 4.2042053 | U39: =Q39+R39*$AB$11 -> 4.4521013 | V39: 1.2474 | W39: =O39+V39*$AB$11 -> 3.5850593 | X39: =P39+V39*$AB$11 -> 4.7625653 | Y39: =Q39+V39*$AB$11 -> 5.0104613 | Z39: =F39*C39 -> 420.18372
C40: 678 | D40: 18 | E40: 2 | F40: =(D40-E40)*E40*0.02504 -> 0.80128 | G40: 1 | H40: =CONCATENATE(D40,E40) -> 182 | I40: 2.96 | J40: 2.05 | K40: 2.45 | L40: =I40+J40 -> 5.01 | M40: =I40+K40 -> 5.41 | O40: =((G40*(1-$O$2)+I40+$O$3)*F40*$O$7)*$AB$11 -> 2.7323648 | P40: =((G40*(1-$P$2)+I40+J40+$P$3)*F40*$O$7)*$AB$11 -> 4.3749888 | Q40: =((G40*(1-$Q$2)+I40+K40+$Q$3)*F40*$O$7)*$AB$11 -> 4.6955008 | R40: 0.7128 | S40: =O40+R40*$AB$11 -> 3.4451648 | T40: =P40+R40*$AB$11 -> 5.0877888 | U40: =Q40+R40*$AB$11 -> 5.4083008 | V40: 1.2474 | W40: =O40+V40*$AB$11 -> 3.9797648 | X40: =P40+V40*$AB$11 -> 5.6223888 | Y40: =Q40+V40*$AB$11 -> 5.9429008 | Z40: =F40*C40 -> 543.26784
C41: 678 | D41: 19 | E41: 1.2 | F41: =(D41-E41)*E41*0.02504 -> 0.5348544 | G41: 1 | H41: =CONCATENATE(D41,E41) -> 191,2 | I41: 3.11 | J41: 1.9 | K41: 2.3 | L41: =I41+J41 -> 5.01 | M41: =I41+K41 -> 5.41 | O41: =((G41*(1-$O$2)+I41+$O$3)*F41*$O$7)*$AB$11 -> 1.9040817 | R41: 0.68904 | S41: =O41+R41*$AB$11 -> 2.5931217 | V41: 1.2474 | W41: =O41+V41*$AB$11 -> 3.1514817 | Z41: =F41*C41 -> 362.63128
C42: 678 | D42: 19 | E42: 1.5 | F42: =(D42-E42)*E42*0.02504 -> 0.6573 | G42: 1 | H42: =CONCATENATE(D42,E42) -> 191,5 | I42: 3.272 | J42: 1.9 | K42: 2.3 | L42: =I42+J42 -> 5.172 | M42: =I42+K42 -> 5.572 | O42: =((G42*(1-$O$2)+I42+$O$3)*F42*$O$7)*$AB$11 -> 2.4464706 | P42: =((G42*(1-$P$2)+I42+J42+$P$3)*F42*$O$7)*$AB$11 -> 3.6953406 | Q42: =((G42*(1-$Q$2)+I42+K42+$Q$3)*F42*$O$7)*$AB$11 -> 3.9582606 | R42: 0.68904 | S42: =O42+R42*$AB$11 -> 3.1355106 | T42: =P42+R42*$AB$11 -> 4.3843806 | U42: =Q42+R42*$AB$11 -> 4.6473006 | V42: 1.2474 | W42: =O42+V42*$AB$11 -> 3.6938706 | X42: =P42+V42*$AB$11 -> 4.9427406 | Y42: =Q42+V42*$AB$11 -> 5.2056606 | Z42: =F42*C42 -> 445.6494
C43: 678 | D43: 20 | E43: 1 | F43: =(D43-E43)*E43*0.02504 -> 0.47576 | G43: 1 | H43: =CONCATENATE(D43,E43) -> 201 | I43: 3.182 | J43: 1.9 | K43: 2.3 | L43: =I43+J43 -> 5.082 | M43: =I43+K43 -> 5.482 | O43: =((G43*(1-$O$2)+I43+$O$3)*F43*$O$7)*$AB$11 -> 1.7279603 | R43: 0.68904 | S43: =O43+R43*$AB$11 -> 2.4170003 | V43: 1.2474 | W43: =O43+V43*$AB$11 -> 2.9753603 | Z43: =F43*C43 -> 322.56528
C44: 678 | D44: 20 | E44: 1.2 | F44: =(D44-E44)*E44*0.02504 -> 0.5649024 | G44: 1 | H44: =CONCATENATE(D44,E44) -> 201,2 | I44: 3.06 | J44: 1.9 | K44: 2.3 | L44: =I44+J44 -> 4.96 | M44: =I44+K44 -> 5.36 | O44: =((G44*(1-$O$2)+I44+$O$3)*F44*$O$7)*$AB$11 -> 1.9828074 | R44: 0.68904 | S44: =O44+R44*$AB$11 -> 2.6718474 | V44: 1.2474 | W44: =O44+V44*$AB$11 -> 3.2302074 | Z44: =F44*C44 -> 383.00383
C45: 678 | D45: 20 | E45: 1.5 | F45: =(D45-E45)*E45*0.02504 -> 0.69486 | G45: 1 | H45: =CONCATENATE(D45,E45) -> 201,5 | I45: 3.142 | J45: 1.9 | K45: 2.3 | L45: =I45+J45 -> 5.042 | M45: =I45+K45 -> 5.442 | O45: =((G45*(1-$O$2)+I45+$O$3)*F45*$O$7)*$AB$11 -> 2.4959371 | P45: =((G45*(1-$P$2)+I45+J45+$P$3)*F45*$O$7)*$AB$11 -> 3.8161711 | R45: 0.68904 | S45: =O45+R45*$AB$11 -> 3.1849771 | T45: =P45+R45*$AB$11 -> 4.5052111 | V45: 1.2474 | W45: =O45+V45*$AB$11 -> 3.7433371 | X45: =P45+V45*$AB$11 -> 5.0635711 | Z45: =F45*C45 -> 471.11508
C46: 678 | D46: 20 | E46: 2 | F46: =(D46-E46)*E46*0.02504 -> 0.90144 | G46: 1 | H46: =CONCATENATE(D46,E46) -> 202 | I46: 2.862 | J46: 2.05 | K46: 2.45 | L46: =I46+J46 -> 4.912 | M46: =I46+K46 -> 5.312 | O46: =((G46*(1-$O$2)+I46+$O$3)*F46*$O$7)*$AB$11 -> 2.9855693 | P46: =((G46*(1-$P$2)+I46+J46+$P$3)*F46*$O$7)*$AB$11 -> 4.8335213 | Q46: =((G46*(1-$Q$2)+I46+K46+$Q$3)*F46*$O$7)*$AB$11 -> 5.1940973 | R46: 0.7128 | S46: =O46+R46*$AB$11 -> 3.6983693 | T46: =P46+R46*$AB$11 -> 5.5463213 | U46: =Q46+R46*$AB$11 -> 5.9068973 | V46: 1.2474 | W46: =O46+V46*$AB$11 -> 4.2329693 | X46: =P46+V46*$AB$11 -> 6.0809213 | Y46: =Q46+V46*$AB$11 -> 6.4414973 | Z46: =F46*C46 -> 611.17632
C47: 678 | D47: 20 | E47: 2.5 | F47: =(D47-E47)*E47*0.02504 -> 1.0955 | G47: 1 | H47: =CONCATENATE(D47,E47) -> 202,5 | I47: 2.9 | J47: 1.9 | K47: 2.3 | L47: =I47+J47 -> 4.8 | M47: =I47+K47 -> 5.2 | O47: =((G47*(1-$O$2)+I47+$O$3)*F47*$O$7)*$AB$11 -> 3.669925 | R47: 0.86 | S47: =O47+R47*$AB$11 -> 4.529925 | V47: 1.72 | W47: =O47+V47*$AB$11 -> 5.389925 | Z47: =F47*C47 -> 742.749
A48: 15 | B48: 1/2" | C48: 678 | D48: 21.3 | E48: 1.2 | F48: =(D48-E48)*E48*0.02504 -> 0.6039648 | G48: 1 | H48: =CONCATENATE(D48,E48) -> 21,31,2 | I48: 3.182 | J48: 1.9 | K48: 2.3 | L48: =I48+J48 -> 5.082 | M48: =I48+K48 -> 5.482 | O48: =((G48*(1-$O$2)+I48+$O$3)*F48*$O$7)*$AB$11 -> 2.1936002 | R48: 0.69 | S48: =O48+R48*$AB$11 -> 2.8836002 | V48: 1.25 | W48: =O48+V48*$AB$11 -> 3.4436002 | Z48: =F48*C48 -> 409.48813
C49: 678 | D49: 21.3 | E49: 1.5 | F49: =(D49-E49)*E49*0.02504 -> 0.743688 | G49: 1 | H49: =CONCATENATE(D49,E49) -> 21,31,5 | I49: 3.092 | J49: 1.9 | K49: 2.3 | L49: =I49+J49 -> 4.992 | M49: =I49+K49 -> 5.392 | O49: =((G49*(1-$O$2)+I49+$O$3)*F49*$O$7)*$AB$11 -> 2.6341429 | P49: =((G49*(1-$P$2)+I49+J49+$P$3)*F49*$O$7)*$AB$11 -> 4.0471501 | R49: 0.68904 | S49: =O49+R49*$AB$11 -> 3.3231829 | T49: =P49+R49*$AB$11 -> 4.7361901 | V49: 1.2474 | W49: =O49+V49*$AB$11 -> 3.8815429 | X49: =P49+V49*$AB$11 -> 5.2945501 | Z49: =F49*C49 -> 504.22046
C50: 678 | D50: 21.3 | E50: 1.6 | F50: =(D50-E50)*E50*0.02504 -> 0.7892608 | G50: 1 | H50: =CONCATENATE(D50,E50) -> 21,31,6 | I50: 3.092 | J50: 1.9 | K50: 2.3 | L50: =I50+J50 -> 4.992 | M50: =I50+K50 -> 5.392 | O50: =((G50*(1-$O$2)+I50+$O$3)*F50*$O$7)*$AB$11 -> 2.7955618 | P50: =((G50*(1-$P$2)+I50+J50+$P$3)*F50*$O$7)*$AB$11 -> 4.2951573 | R50: 0.68904 | S50: =O50+R50*$AB$11 -> 3.4846018 | T50: =P50+R50*$AB$11 -> 4.9841973 | V50: 1.2474 | W50: =O50+V50*$AB$11 -> 4.0429618 | X50: =P50+V50*$AB$11 -> 5.5425573 | Z50: =F50*C50 -> 535.11882
C51: 678 | D51: 21.3 | E51: 2 | F51: =(D51-E51)*E51*0.02504 -> 0.966544 | G51: 1 | H51: =CONCATENATE(D51,E51) -> 21,32 | I51: 2.762 | J51: 2.05 | K51: 2.45 | L51: =I51+J51 -> 4.812 | M51: =I51+K51 -> 5.212 | O51: =((G51*(1-$O$2)+I51+$O$3)*F51*$O$7)*$AB$11 -> 3.1045393 | P51: =((G51*(1-$P$2)+I51+J51+$P$3)*F51*$O$7)*$AB$11 -> 5.0859545 | Q51: =((G51*(1-$Q$2)+I51+K51+$Q$3)*F51*$O$7)*$AB$11 -> 5.4725721 | R51: 0.73656 | S51: =O51+R51*$AB$11 -> 3.8410993 | T51: =P51+R51*$AB$11 -> 5.8225145 | U51: =Q51+R51*$AB$11 -> 6.2091321 | V51: 1.2474 | W51: =O51+V51*$AB$11 -> 4.3519393 | X51: =P51+V51*$AB$11 -> 6.3333545 | Y51: =Q51+V51*$AB$11 -> 6.7199721 | Z51: =F51*C51 -> 655.31683
C52: 678 | D52: 21.3 | E52: 2.5 | F52: =(D52-E52)*E52*0.02504 -> 1.17688 | G52: 1 | H52: =CONCATENATE(D52,E52) -> 21,32,5 | I52: 2.85 | J52: 1.9 | K52: 2.3 | L52: =I52+J52 -> 4.75 | M52: =I52+K52 -> 5.15 | O52: =((G52*(1-$O$2)+I52+$O$3)*F52*$O$7)*$AB$11 -> 3.883704 | P52: =((G52*(1-$P$2)+I52+J52+$P$3)*F52*$O$7)*$AB$11 -> 6.119776 | R52: 0.85536 | S52: =O52+R52*$AB$11 -> 4.739064 | T52: =P52+R52*$AB$11 -> 6.975136 | V52: 1.7226 | W52: =O52+V52*$AB$11 -> 5.606304 | X52: =P52+V52*$AB$11 -> 7.842376 | Z52: =F52*C52 -> 797.92464
C53: 678 | D53: 21.3 | E53: 2.6 | F53: =(D53-E53)*E53*0.02504 -> 1.2174448 | G53: 1 | H53: =CONCATENATE(D53,E53) -> 21,32,6 | I53: 2.832 | J53: 1.9 | K53: 2.3 | L53: =I53+J53 -> 4.732 | M53: =I53+K53 -> 5.132 | O53: =((G53*(1-$O$2)+I53+$O$3)*F53*$O$7)*$AB$11 -> 3.9956538 | P53: =((G53*(1-$P$2)+I53+J53+$P$3)*F53*$O$7)*$AB$11 -> 6.308799 | R53: 0.85536 | S53: =O53+R53*$AB$11 -> 4.8510138 | T53: =P53+R53*$AB$11 -> 7.164159 | V53: 1.7226 | W53: =O53+V53*$AB$11 -> 5.7182538 | X53: =P53+V53*$AB$11 -> 8.031399 | Z53: =F53*C53 -> 825.42757
C54: 678 | D54: 21.3 | E54: 3 | F54: =(D54-E54)*E54*0.02504 -> 1.374696 | G54: 1 | H54: =CONCATENATE(D54,E54) -> 21,33 | I54: 2.965 | J54: 1.9 | K54: 2.3 | L54: =I54+J54 -> 4.865 | M54: =I54+K54 -> 5.265 | O54: =((G54*(1-$O$2)+I54+$O$3)*F54*$O$7)*$AB$11 -> 4.6945868 | P54: =((G54*(1-$P$2)+I54+J54+$P$3)*F54*$O$7)*$AB$11 -> 7.3065092 | R54: 0.90288 | S54: =O54+R54*$AB$11 -> 5.5974668 | T54: =P54+R54*$AB$11 -> 8.2093892 | V54: 1.79388 | W54: =O54+V54*$AB$11 -> 6.4884668 | X54: =P54+V54*$AB$11 -> 9.1003892 | Z54: =F54*C54 -> 932.04389
C55: 678 | D55: 22 | E55: 1 | F55: =(D55-E55)*E55*0.02504 -> 0.52584 | G55: 1 | H55: =CONCATENATE(D55,E55) -> 221 | I55: 3.212 | J55: 1.9 | K55: 2.3 | L55: =I55+J55 -> 5.112 | M55: =I55+K55 -> 5.512 | O55: =((G55*(1-$O$2)+I55+$O$3)*F55*$O$7)*$AB$11 -> 1.9256261 | R55: 0.68904 | S55: =O55+R55*$AB$11 -> 2.6146661 | V55: 1.2474 | W55: =O55+V55*$AB$11 -> 3.1730261 | Z55: =F55*C55 -> 356.51952
C56: 678 | D56: 22 | E56: 1.2 | F56: =(D56-E56)*E56*0.02504 -> 0.6249984 | G56: 1 | H56: =CONCATENATE(D56,E56) -> 221,2 | I56: 3.01 | J56: 1.9 | K56: 2.3 | L56: =I56+J56 -> 4.91 | M56: =I56+K56 -> 5.31 | O56: =((G56*(1-$O$2)+I56+$O$3)*F56*$O$7)*$AB$11 -> 2.1624945 | R56: 0.68904 | S56: =O56+R56*$AB$11 -> 2.8515345 | V56: 1.2474 | W56: =O56+V56*$AB$11 -> 3.4098945 | Z56: =F56*C56 -> 423.74892
C57: 678 | D57: 22 | E57: 1.5 | F57: =(D57-E57)*E57*0.02504 -> 0.76998 | G57: 1 | H57: =CONCATENATE(D57,E57) -> 221,5 | I57: 3.182 | J57: 1.9 | K57: 2.3 | L57: =I57+J57 -> 5.082 | M57: =I57+K57 -> 5.482 | O57: =((G57*(1-$O$2)+I57+$O$3)*F57*$O$7)*$AB$11 -> 2.7965674 | P57: =((G57*(1-$P$2)+I57+J57+$P$3)*F57*$O$7)*$AB$11 -> 4.2595294 | Q57: =((G57*(1-$Q$2)+I57+K57+$Q$3)*F57*$O$7)*$AB$11 -> 4.5675214 | R57: 0.68904 | S57: =O57+R57*$AB$11 -> 3.4856074 | T57: =P57+R57*$AB$11 -> 4.9485694 | U57: =Q57+R57*$AB$11 -> 5.2565614 | V57: 1.2474 | W57: =O57+V57*$AB$11 -> 4.0439674 | X57: =P57+V57*$AB$11 -> 5.5069294 | Y57: =Q57+V57*$AB$11 -> 5.8149214 | Z57: =F57*C57 -> 522.04644
C58: 678 | D58: 22 | E58: 2 | F58: =(D58-E58)*E58*0.02504 -> 1.0016 | G58: 1 | H58: =CONCATENATE(D58,E58) -> 222 | I58: 2.832 | J58: 2.05 | K58: 2.45 | L58: =I58+J58 -> 4.882 | M58: =I58+K58 -> 5.282 | O58: =((G58*(1-$O$2)+I58+$O$3)*F58*$O$7)*$AB$11 -> 3.2872512 | P58: =((G58*(1-$P$2)+I58+J58+$P$3)*F58*$O$7)*$AB$11 -> 5.3405312 | Q58: =((G58*(1-$Q$2)+I58+K58+$Q$3)*F58*$O$7)*$AB$11 -> 5.7411712 | R58: 0.74844 | S58: =O58+R58*$AB$11 -> 4.0356912 | T58: =P58+R58*$AB$11 -> 6.0889712 | U58: =Q58+R58*$AB$11 -> 6.4896112 | V58: 1.2474 | W58: =O58+V58*$AB$11 -> 4.5346512 | X58: =P58+V58*$AB$11 -> 6.5879312 | Y58: =Q58+V58*$AB$11 -> 6.9885712 | Z58: =F58*C58 -> 679.0848
C59: 678 | D59: 23 | E59: 1.5 | F59: =(D59-E59)*E59*0.02504 -> 0.80754 | G59: 1 | H59: =CONCATENATE(D59,E59) -> 231,5 | I59: 3.342 | J59: 1.9 | K59: 2.3 | L59: =I59+J59 -> 5.242 | M59: =I59+K59 -> 5.642 | O59: =((G59*(1-$O$2)+I59+$O$3)*F59*$O$7)*$AB$11 -> 3.0621917 | P59: =((G59*(1-$P$2)+I59+J59+$P$3)*F59*$O$7)*$AB$11 -> 4.5965177 | Q59: =((G59*(1-$Q$2)+I59+K59+$Q$3)*F59*$O$7)*$AB$11 -> 4.9195337 | R59: 0.68904 | S59: =O59+R59*$AB$11 -> 3.7512317 | T59: =P59+R59*$AB$11 -> 5.2855577 | U59: =Q59+R59*$AB$11 -> 5.6085737 | V59: 1.2474 | W59: =O59+V59*$AB$11 -> 4.3095917 | X59: =P59+V59*$AB$11 -> 5.8439177 | Y59: =Q59+V59*$AB$11 -> 6.1669337 | Z59: =F59*C59 -> 547.51212
C60: 678 | D60: 23 | E60: 2 | F60: =(D60-E60)*E60*0.02504 -> 1.05168 | G60: 1 | H60: =CONCATENATE(D60,E60) -> 232 | I60: 3.182 | J60: 2.05 | K60: 2.45 | L60: =I60+J60 -> 5.232 | M60: =I60+K60 -> 5.632 | O60: =((G60*(1-$O$2)+I60+$O$3)*F60*$O$7)*$AB$11 -> 3.8197018 | P60: =((G60*(1-$P$2)+I60+J60+$P$3)*F60*$O$7)*$AB$11 -> 5.9756458 | R60: 0.82 | S60: =O60+R60*$AB$11 -> 4.6397018 | V60: 1.25 | W60: =O60+V60*$AB$11 -> 5.0697018 | Z60: =F60*C60 -> 713.03904
C61: 678 | D61: 25 | E61: 1 | F61: =(D61-E61)*E61*0.02504 -> 0.60096 | G61: 1 | H61: =CONCATENATE(D61,E61) -> 251 | I61: 3.122 | J61: 1.9 | K61: 2.3 | L61: =I61+J61 -> 5.022 | M61: =I61+K61 -> 5.422 | O61: =((G61*(1-$O$2)+I61+$O$3)*F61*$O$7)*$AB$11 -> 2.1466291 | R61: 0.7128 | S61: =O61+R61*$AB$11 -> 2.8594291 | V61: 1.2474 | W61: =O61+V61*$AB$11 -> 3.3940291 | Z61: =F61*C61 -> 407.45088
C62: 678 | D62: 25 | E62: 1.2 | F62: =(D62-E62)*E62*0.02504 -> 0.7151424 | G62: 1 | H62: =CONCATENATE(D62,E62) -> 251,2 | I62: 2.96 | J62: 1.9 | K62: 2.3 | L62: =I62+J62 -> 4.86 | M62: =I62+K62 -> 5.26 | O62: =((G62*(1-$O$2)+I62+$O$3)*F62*$O$7)*$AB$11 -> 2.4386356 | R62: 0.7128 | S62: =O62+R62*$AB$11 -> 3.1514356 | V62: 1.2474 | W62: =O62+V62*$AB$11 -> 3.6860356 | Z62: =F62*C62 -> 484.86655
C63: 678 | D63: 25 | E63: 1.5 | F63: =(D63-E63)*E63*0.02504 -> 0.88266 | G63: 1 | H63: =CONCATENATE(D63,E63) -> 251,5 | I63: 3.022 | J63: 1.9 | K63: 2.3 | L63: =I63+J63 -> 4.922 | M63: =I63+K63 -> 5.322 | O63: =((G63*(1-$O$2)+I63+$O$3)*F63*$O$7)*$AB$11 -> 3.0645955 | P63: =((G63*(1-$P$2)+I63+J63+$P$3)*F63*$O$7)*$AB$11 -> 4.7416495 | R63: 0.7128 | S63: =O63+R63*$AB$11 -> 3.7773955 | T63: =P63+R63*$AB$11 -> 5.4544495 | V63: 1.2474 | W63: =O63+V63*$AB$11 -> 4.3119955 | X63: =P63+V63*$AB$11 -> 5.9890495 | Z63: =F63*C63 -> 598.44348
C64: 678 | D64: 25 | E64: 2 | F64: =(D64-E64)*E64*0.02504 -> 1.15184 | G64: 1 | H64: =CONCATENATE(D64,E64) -> 252 | I64: 2.722 | J64: 2.05 | K64: 2.45 | L64: =I64+J64 -> 4.772 | M64: =I64+K64 -> 5.172 | O64: =((G64*(1-$O$2)+I64+$O$3)*F64*$O$7)*$AB$11 -> 3.6536365 | P64: =((G64*(1-$P$2)+I64+J64+$P$3)*F64*$O$7)*$AB$11 -> 6.0149085 | Q64: =((G64*(1-$Q$2)+I64+K64+$Q$3)*F64*$O$7)*$AB$11 -> 6.4756445 | R64: 0.81972 | S64: =O64+R64*$AB$11 -> 4.4733565 | T64: =P64+R64*$AB$11 -> 6.8346285 | U64: =Q64+R64*$AB$11 -> 7.2953645 | V64: 1.2474 | W64: =O64+V64*$AB$11 -> 4.9010365 | X64: =P64+V64*$AB$11 -> 7.2623085 | Y64: =Q64+V64*$AB$11 -> 7.7230445 | Z64: =F64*C64 -> 780.94752
C65: 474 | D65: 25 | E65: 2.5 | F65: =(D65-E65)*E65*0.02504 -> 1.4085 | G65: 1 | H65: =CONCATENATE(D65,E65) -> 252,5 | I65: 2.81 | J65: 1.9 | K65: 2.3 | L65: =I65+J65 -> 4.71 | M65: =I65+K65 -> 5.11 | O65: =((G65*(1-$O$2)+I65+$O$3)*F65*$O$7)*$AB$11 -> 4.59171 | P65: =((G65*(1-$P$2)+I65+J65+$P$3)*F65*$O$7)*$AB$11 -> 7.26786 | R65: 0.93852 | S65: =O65+R65*$AB$11 -> 5.53023 | T65: =P65+R65*$AB$11 -> 8.20638 | V65: 1.7226 | W65: =O65+V65*$AB$11 -> 6.31431 | X65: =P65+V65*$AB$11 -> 8.99046 | Z65: =F65*C65 -> 667.629
C66: 474 | D66: 25 | E66: 3 | F66: =(D66-E66)*E66*0.02504 -> 1.65264 | G66: 1 | H66: =CONCATENATE(D66,E66) -> 253 | I66: 2.965 | J66: 1.9 | K66: 2.3 | L66: =I66+J66 -> 4.865 | M66: =I66+K66 -> 5.265 | O66: =((G66*(1-$O$2)+I66+$O$3)*F66*$O$7)*$AB$11 -> 5.6437656 | P66: =((G66*(1-$P$2)+I66+J66+$P$3)*F66*$O$7)*$AB$11 -> 8.7837816 | R66: 1.05732 | S66: =O66+R66*$AB$11 -> 6.7010856 | T66: =P66+R66*$AB$11 -> 9.8411016 | V66: 1.99584 | W66: =O66+V66*$AB$11 -> 7.6396056 | X66: =P66+V66*$AB$11 -> 10.779622 | Z66: =F66*C66 -> 783.35136
C67: 678 | D67: 25.4 | E67: 1.5 | F67: =(D67-E67)*E67*0.02504 -> 0.897684 | G67: 1 | H67: =CONCATENATE(D67,E67) -> 25,41,5 | I67: 3.102 | J67: 1.9 | K67: 2.3 | L67: =I67+J67 -> 5.002 | M67: =I67+K67 -> 5.402 | O67: =((G67*(1-$O$2)+I67+$O$3)*F67*$O$7)*$AB$11 -> 3.1885736 | P67: =((G67*(1-$P$2)+I67+J67+$P$3)*F67*$O$7)*$AB$11 -> 4.8941732 | Q67: =((G67*(1-$Q$2)+I67+K67+$Q$3)*F67*$O$7)*$AB$11 -> 5.2532468 | R67: 0.72468 | S67: =O67+R67*$AB$11 -> 3.9132536 | T67: =P67+R67*$AB$11 -> 5.6188532 | U67: =Q67+R67*$AB$11 -> 5.9779268 | V67: 1.2474 | W67: =O67+V67*$AB$11 -> 4.4359736 | Y67: =Q67+V67*$AB$11 -> 6.5006468 | Z67: =F67*C67 -> 608.62975
C68: 678 | D68: 25.4 | E68: 2 | F68: =(D68-E68)*E68*0.02504 -> 1.171872 | G68: 1 | H68: =CONCATENATE(D68,E68) -> 25,42 | I68: 2.722 | J68: 2.05 | K68: 2.45 | L68: =I68+J68 -> 4.772 | M68: =I68+K68 -> 5.172 | O68: =((G68*(1-$O$2)+I68+$O$3)*F68*$O$7)*$AB$11 -> 3.717178 | P68: =((G68*(1-$P$2)+I68+J68+$P$3)*F68*$O$7)*$AB$11 -> 6.1195156 | Q68: =((G68*(1-$Q$2)+I68+K68+$Q$3)*F68*$O$7)*$AB$11 -> 6.5882644 | R68: 0.8316 | S68: =O68+R68*$AB$11 -> 4.548778 | T68: =P68+R68*$AB$11 -> 6.9511156 | U68: =Q68+R68*$AB$11 -> 7.4198644 | V68: 1.2474 | Y68: =Q68+V68*$AB$11 -> 7.8356644 | Z68: =F68*C68 -> 794.52922
A69: 20 | B69: 3/4" | C69: 678 | D69: 26.9 | E69: 1.2 | F69: =(D69-E69)*E69*0.02504 -> 0.7722336 | G69: 1 | H69: =CONCATENATE(D69,E69) -> 26,91,2 | I69: 2.91 | J69: 1.9 | K69: 2.3 | L69: =I69+J69 -> 4.81 | M69: =I69+K69 -> 5.21 | O69: =((G69*(1-$O$2)+I69+$O$3)*F69*$O$7)*$AB$11 -> 2.5947049 | R69: 0.68904 | S69: =O69+R69*$AB$11 -> 3.2837449 | V69: 1.2474 | W69: =O69+V69*$AB$11 -> 3.8421049 | Z69: =F69*C69 -> 523.57438
C70: 678 | D70: 26.9 | E70: 1.5 | F70: =(D70-E70)*E70*0.02504 -> 0.954024 | G70: 1 | H70: =CONCATENATE(D70,E70) -> 26,91,5 | I70: 2.992 | J70: 1.9 | K70: 2.3 | L70: =I70+J70 -> 4.892 | M70: =I70+K70 -> 5.292 | O70: =((G70*(1-$O$2)+I70+$O$3)*F70*$O$7)*$AB$11 -> 3.2837506 | P70: =((G70*(1-$P$2)+I70+J70+$P$3)*F70*$O$7)*$AB$11 -> 5.0963962 | Q70: =((G70*(1-$Q$2)+I70+K70+$Q$3)*F70*$O$7)*$AB$11 -> 5.4780058 | R70: 0.68904 | S70: =O70+R70*$AB$11 -> 3.9727906 | T70: =P70+R70*$AB$11 -> 5.7854362 | U70: =Q70+R70*$AB$11 -> 6.1670458 | V70: 1.2474 | W70: =O70+V70*$AB$11 -> 4.5311506 | X70: =P70+V70*$AB$11 -> 6.3437962 | Y70: =Q70+V70*$AB$11 -> 6.7254058 | Z70: =F70*C70 -> 646.82827
C71: 678 | D71: 26.9 | E71: 1.6 | F71: =(D71-E71)*E71*0.02504 -> 1.0136192 | G71: 1 | H71: =CONCATENATE(D71,E71) -> 26,91,6 | I71: 2.992 | J71: 1.9 | K71: 2.3 | L71: =I71+J71 -> 4.892 | M71: =I71+K71 -> 5.292 | O71: =((G71*(1-$O$2)+I71+$O$3)*F71*$O$7)*$AB$11 -> 3.4888773 | P71: =((G71*(1-$P$2)+I71+J71+$P$3)*F71*$O$7)*$AB$11 -> 5.4147538 | R71: 0.68904 | S71: =O71+R71*$AB$11 -> 4.1779173 | T71: =P71+R71*$AB$11 -> 6.1037938 | V71: 1.2474 | W71: =O71+V71*$AB$11 -> 4.7362773 | Z71: =F71*C71 -> 687.23382
C72: 678 | D72: 26.9 | E72: 2 | F72: =(D72-E72)*E72*0.02504 -> 1.246992 | G72: 1 | H72: =CONCATENATE(D72,E72) -> 26,92 | I72: 2.612 | J72: 2.05 | K72: 2.45 | L72: =I72+J72 -> 4.662 | M72: =I72+K72 -> 5.062 | O72: =((G72*(1-$O$2)+I72+$O$3)*F72*$O$7)*$AB$11 -> 3.8182895 | P72: =((G72*(1-$P$2)+I72+J72+$P$3)*F72*$O$7)*$AB$11 -> 6.3746231 | Q72: =((G72*(1-$Q$2)+I72+K72+$Q$3)*F72*$O$7)*$AB$11 -> 6.8734199 | R72: 0.79596 | S72: =O72+R72*$AB$11 -> 4.6142495 | T72: =P72+R72*$AB$11 -> 7.1705831 | U72: =Q72+R72*$AB$11 -> 7.6693799 | V72: 1.2474 | W72: =O72+V72*$AB$11 -> 5.0656895 | X72: =P72+V72*$AB$11 -> 7.6220231 | Y72: =Q72+V72*$AB$11 -> 8.1208199 | Z72: =F72*C72 -> 845.46058
C73: 366 | D73: 26.9 | E73: 2.5 | F73: =(D73-E73)*E73*0.02504 -> 1.52744 | G73: 1 | H73: =CONCATENATE(D73,E73) -> 26,92,5 | I73: 2.76 | J73: 1.9 | K73: 2.3 | L73: =I73+J73 -> 4.66 | M73: =I73+K73 -> 5.06 | O73: =((G73*(1-$O$2)+I73+$O$3)*F73*$O$7)*$AB$11 -> 4.9030824 | P73: =((G73*(1-$P$2)+I73+J73+$P$3)*F73*$O$7)*$AB$11 -> 7.8052184 | Q73: =((G73*(1-$Q$2)+I73+K73+$Q$3)*F73*$O$7)*$AB$11 -> 8.4161944 | R73: 0.92664 | S73: =O73+R73*$AB$11 -> 5.8297224 | T73: =P73+R73*$AB$11 -> 8.7318584 | U73: =Q73+R73*$AB$11 -> 9.3428344 | V73: 1.7226 | W73: =O73+V73*$AB$11 -> 6.6256824 | X73: =P73+V73*$AB$11 -> 9.5278184 | Y73: =Q73+V73*$AB$11 -> 10.138794 | Z73: =F73*C73 -> 559.04304
C74: 366 | D74: 26.9 | E74: 2.6 | F74: =(D74-E74)*E74*0.02504 -> 1.5820272 | G74: 1 | H74: =CONCATENATE(D74,E74) -> 26,92,6 | I74: 2.74 | J74: 1.9 | K74: 2.3 | L74: =I74+J74 -> 4.64 | M74: =I74+K74 -> 5.04 | O74: =((G74*(1-$O$2)+I74+$O$3)*F74*$O$7)*$AB$11 -> 5.0466668 | P74: =((G74*(1-$P$2)+I74+J74+$P$3)*F74*$O$7)*$AB$11 -> 8.0525184 | R74: 0.92664 | S74: =O74+R74*$AB$11 -> 5.9733068 | V74: 1.7226 | Z74: =F74*C74 -> 579.02196
C75: 366 | D75: 26.9 | E75: 3 | F75: =(D75-E75)*E75*0.02504 -> 1.795368 | G75: 1 | H75: =CONCATENATE(D75,E75) -> 26,93 | I75: 2.965 | J75: 1.9 | K75: 2.3 | L75: =I75+J75 -> 4.865 | M75: =I75+K75 -> 5.265 | O75: =((G75*(1-$O$2)+I75+$O$3)*F75*$O$7)*$AB$11 -> 6.1311817 | P75: =((G75*(1-$P$2)+I75+J75+$P$3)*F75*$O$7)*$AB$11 -> 9.5423809 | Q75: =((G75*(1-$Q$2)+I75+K75+$Q$3)*F75*$O$7)*$AB$11 -> 10.260528 | R75: 1.0692 | S75: =O75+R75*$AB$11 -> 7.2003817 | T75: =P75+R75*$AB$11 -> 10.611581 | U75: =Q75+R75*$AB$11 -> 11.329728 | V75: 2.04336 | W75: =O75+V75*$AB$11 -> 8.1745417 | X75: =P75+V75*$AB$11 -> 11.585741 | Y75: =Q75+V75*$AB$11 -> 12.303888 | Z75: =F75*C75 -> 657.10469
C76: 366 | D76: 28 | E76: 1 | F76: =(D76-E76)*E76*0.02504 -> 0.67608 | G76: 1 | H76: =CONCATENATE(D76,E76) -> 281 | I76: 3.152 | J76: 1.9 | K76: 2.3 | L76: =I76+J76 -> 5.052 | M76: =I76+K76 -> 5.452 | O76: =((G76*(1-$O$2)+I76+$O$3)*F76*$O$7)*$AB$11 -> 2.4352402 | R76: 0.7128 | S76: =O76+R76*$AB$11 -> 3.1480402 | V76: 1.2474 | W76: =O76+V76*$AB$11 -> 3.6826402 | Z76: =F76*C76 -> 247.44528
C77: 366 | D77: 28 | E77: 1.2 | F77: =(D77-E77)*E77*0.02504 -> 0.8052864 | G77: 1 | H77: =CONCATENATE(D77,E77) -> 281,2 | I77: 2.91 | J77: 1.9 | K77: 2.3 | L77: =I77+J77 -> 4.81 | M77: =I77+K77 -> 5.21 | O77: =((G77*(1-$O$2)+I77+$O$3)*F77*$O$7)*$AB$11 -> 2.7057623 | R77: 0.7128 | S77: =O77+R77*$AB$11 -> 3.4185623 | V77: 1.2474 | W77: =O77+V77*$AB$11 -> 3.9531623 | Z77: =F77*C77 -> 294.73482
C78: 366 | D78: 28 | E78: 1.5 | F78: =(D78-E78)*E78*0.02504 -> 0.99534 | G78: 1 | H78: =CONCATENATE(D78,E78) -> 281,5 | I78: 3.202 | J78: 1.9 | K78: 2.3 | L78: =I78+J78 -> 5.102 | M78: =I78+K78 -> 5.502 | O78: =((G78*(1-$O$2)+I78+$O$3)*F78*$O$7)*$AB$11 -> 3.6349817 | P78: =((G78*(1-$P$2)+I78+J78+$P$3)*F78*$O$7)*$AB$11 -> 5.5261277 | R78: 0.7128 | S78: =O78+R78*$AB$11 -> 4.3477817 | T78: =P78+R78*$AB$11 -> 6.2389277 | V78: 1.2474 | W78: =O78+V78*$AB$11 -> 4.8823817 | X78: =P78+V78*$AB$11 -> 6.7735277 | Z78: =F78*C78 -> 364.29444
C79: 366 | D79: 28 | E79: 2 | F79: =(D79-E79)*E79*0.02504 -> 1.30208 | G79: 1 | H79: =CONCATENATE(D79,E79) -> 282 | I79: 2.722 | J79: 2.05 | K79: 2.45 | L79: =I79+J79 -> 4.772 | M79: =I79+K79 -> 5.172 | O79: =((G79*(1-$O$2)+I79+$O$3)*F79*$O$7)*$AB$11 -> 4.1301978 | P79: =((G79*(1-$P$2)+I79+J79+$P$3)*F79*$O$7)*$AB$11 -> 6.7994618 | R79: 0.80784 | S79: =O79+R79*$AB$11 -> 4.9380378 | T79: =P79+R79*$AB$11 -> 7.6073018 | V79: 1.2474 | W79: =O79+V79*$AB$11 -> 5.3775978 | X79: =P79+V79*$AB$11 -> 8.0468618 | Z79: =F79*C79 -> 476.56128
C80: 366 | D80: 28 | E80: 2.5 | F80: =(D80-E80)*E80*0.02504 -> 1.5963 | G80: 1 | H80: =CONCATENATE(D80,E80) -> 282,5 | I80: 2.822 | J80: 1.9 | K80: 2.3 | L80: =I80+J80 -> 4.722 | M80: =I80+K80 -> 5.122 | O80: =((G80*(1-$O$2)+I80+$O$3)*F80*$O$7)*$AB$11 -> 5.2230936 | R80: 1.03 | S80: =O80+R80*$AB$11 -> 6.2530936 | V80: 1.89 | W80: =O80+V80*$AB$11 -> 7.1130936 | Z80: =F80*C80 -> 584.2458
C81: 366 | D81: 30 | E81: 1 | F81: =(D81-E81)*E81*0.02504 -> 0.72616 | G81: 1 | H81: =CONCATENATE(D81,E81) -> 301 | I81: 3.052 | J81: 1.9 | K81: 2.3 | L81: =I81+J81 -> 4.952 | M81: =I81+K81 -> 5.352 | O81: =((G81*(1-$O$2)+I81+$O$3)*F81*$O$7)*$AB$11 -> 2.5430123 | R81: 0.73656 | S81: =O81+R81*$AB$11 -> 3.2795723 | V81: 1.2474 | W81: =O81+V81*$AB$11 -> 3.7904123 | Z81: =F81*C81 -> 265.77456
C82: 366 | D82: 30 | E82: 1.2 | F82: =(D82-E82)*E82*0.02504 -> 0.8653824 | G82: 1 | H82: =CONCATENATE(D82,E82) -> 301,2 | I82: 2.89 | J82: 1.9 | K82: 2.3 | L82: =I82+J82 -> 4.79 | M82: =I82+K82 -> 5.19 | O82: =((G82*(1-$O$2)+I82+$O$3)*F82*$O$7)*$AB$11 -> 2.8903772 | R82: 0.73656 | S82: =O82+R82*$AB$11 -> 3.6269372 | V82: 1.2474 | W82: =O82+V82*$AB$11 -> 4.1377772 | Z82: =F82*C82 -> 316.72996
C83: 366 | D83: 30 | E83: 1.5 | F83: =(D83-E83)*E83*0.02504 -> 1.07046 | G83: 1 | H83: =CONCATENATE(D83,E83) -> 301,5 | I83: 3.012 | J83: 1.9 | K83: 2.3 | L83: =I83+J83 -> 4.912 | M83: =I83+K83 -> 5.312 | O83: =((G83*(1-$O$2)+I83+$O$3)*F83*$O$7)*$AB$11 -> 3.7059325 | P83: =((G83*(1-$P$2)+I83+J83+$P$3)*F83*$O$7)*$AB$11 -> 5.7398065 | Q83: =((G83*(1-$Q$2)+I83+K83+$Q$3)*F83*$O$7)*$AB$11 -> 6.1679905 | R83: 0.73656 | S83: =O83+R83*$AB$11 -> 4.4424925 | T83: =P83+R83*$AB$11 -> 6.4763665 | U83: =Q83+R83*$AB$11 -> 6.9045505 | V83: 1.2474 | W83: =O83+V83*$AB$11 -> 4.9533325 | X83: =P83+V83*$AB$11 -> 6.9872065 | Y83: =Q83+V83*$AB$11 -> 7.4153905 | Z83: =F83*C83 -> 391.78836
C84: 366 | D84: 30 | E84: 2 | F84: =(D84-E84)*E84*0.02504 -> 1.40224 | G84: 1 | H84: =CONCATENATE(D84,E84) -> 302 | I84: 2.662 | J84: 2.05 | K84: 2.45 | L84: =I84+J84 -> 4.712 | M84: =I84+K84 -> 5.112 | O84: =((G84*(1-$O$2)+I84+$O$3)*F84*$O$7)*$AB$11 -> 4.3637709 | P84: =((G84*(1-$P$2)+I84+J84+$P$3)*F84*$O$7)*$AB$11 -> 7.2383629 | Q84: =((G84*(1-$Q$2)+I84+K84+$Q$3)*F84*$O$7)*$AB$11 -> 7.7992589 | R84: 0.8316 | S84: =O84+R84*$AB$11 -> 5.1953709 | T84: =P84+R84*$AB$11 -> 8.0699629 | U84: =Q84+R84*$AB$11 -> 8.6308589 | V84: 1.2474 | W84: =O84+V84*$AB$11 -> 5.6111709 | X84: =P84+V84*$AB$11 -> 8.4857629 | Y84: =Q84+V84*$AB$11 -> 9.0466589 | Z84: =F84*C84 -> 513.21984
C85: 366 | D85: 30 | E85: 2.5 | F85: =(D85-E85)*E85*0.02504 -> 1.7215 | G85: 1 | H85: =CONCATENATE(D85,E85) -> 302,5 | I85: 2.76 | J85: 1.9 | K85: 2.3 | L85: =I85+J85 -> 4.66 | M85: =I85+K85 -> 5.06 | O85: =((G85*(1-$O$2)+I85+$O$3)*F85*$O$7)*$AB$11 -> 5.526015 | P85: =((G85*(1-$P$2)+I85+J85+$P$3)*F85*$O$7)*$AB$11 -> 8.796865 | Q85: =((G85*(1-$Q$2)+I85+K85+$Q$3)*F85*$O$7)*$AB$11 -> 9.485465 | R85: 1.03356 | S85: =O85+R85*$AB$11 -> 6.559575 | T85: =P85+R85*$AB$11 -> 9.830425 | U85: =Q85+R85*$AB$11 -> 10.519025 | V85: 1.88892 | W85: =O85+V85*$AB$11 -> 7.414935 | X85: =P85+V85*$AB$11 -> 10.685785 | Y85: =Q85+V85*$AB$11 -> 11.374385 | Z85: =F85*C85 -> 630.069
C86: 366 | D86: 30 | E86: 3 | F86: =(D86-E86)*E86*0.02504 -> 2.02824 | G86: 1 | H86: =CONCATENATE(D86,E86) -> 303 | I86: 2.97 | J86: 1.9 | K86: 2.3 | L86: =I86+J86 -> 4.87 | M86: =I86+K86 -> 5.27 | O86: =((G86*(1-$O$2)+I86+$O$3)*F86*$O$7)*$AB$11 -> 6.9365808 | P86: =((G86*(1-$P$2)+I86+J86+$P$3)*F86*$O$7)*$AB$11 -> 10.790237 | Q86: =((G86*(1-$Q$2)+I86+K86+$Q$3)*F86*$O$7)*$AB$11 -> 11.601533 | R86: 1.03356 | S86: =O86+R86*$AB$11 -> 7.9701408 | T86: =P86+R86*$AB$11 -> 11.823797 | U86: =Q86+R86*$AB$11 -> 12.635093 | V86: 1.98396 | W86: =O86+V86*$AB$11 -> 8.9205408 | X86: =P86+V86*$AB$11 -> 12.774197 | Y86: =Q86+V86*$AB$11 -> 13.585493 | Z86: =F86*C86 -> 742.33584
C87: 366 | D87: 32 | E87: 1 | F87: =(D87-E87)*E87*0.02504 -> 0.77624 | G87: 1 | H87: =CONCATENATE(D87,E87) -> 321 | I87: 3.012 | J87: 1.9 | K87: 2.3 | L87: =I87+J87 -> 4.912 | M87: =I87+K87 -> 5.312 | O87: =((G87*(1-$O$2)+I87+$O$3)*F87*$O$7)*$AB$11 -> 2.6873429 | R87: 0.78408 | S87: =O87+R87*$AB$11 -> 3.4714229 | V87: 1.33056 | W87: =O87+V87*$AB$11 -> 4.0179029 | Z87: =F87*C87 -> 284.10384
C88: 366 | D88: 32 | E88: 1.2 | F88: =(D88-E88)*E88*0.02504 -> 0.9254784 | G88: 1 | H88: =CONCATENATE(D88,E88) -> 321,2 | I88: 2.86 | J88: 1.9 | K88: 2.3 | L88: =I88+J88 -> 4.76 | M88: =I88+K88 -> 5.16 | O88: =((G88*(1-$O$2)+I88+$O$3)*F88*$O$7)*$AB$11 -> 3.0633335 | R88: 0.78408 | S88: =O88+R88*$AB$11 -> 3.8474135 | V88: 1.33056 | W88: =O88+V88*$AB$11 -> 4.3938935 | Z88: =F88*C88 -> 338.72509
C89: 366 | D89: 32 | E89: 1.5 | F89: =(D89-E89)*E89*0.02504 -> 1.14558 | G89: 1 | H89: =CONCATENATE(D89,E89) -> 321,5 | I89: 2.922 | J89: 1.9 | K89: 2.3 | L89: =I89+J89 -> 4.822 | M89: =I89+K89 -> 5.222 | O89: =((G89*(1-$O$2)+I89+$O$3)*F89*$O$7)*$AB$11 -> 3.8628958 | P89: =((G89*(1-$P$2)+I89+J89+$P$3)*F89*$O$7)*$AB$11 -> 6.0394978 | Q89: =((G89*(1-$Q$2)+I89+K89+$Q$3)*F89*$O$7)*$AB$11 -> 6.4977298 | R89: 0.78408 | S89: =O89+R89*$AB$11 -> 4.6469758 | T89: =P89+R89*$AB$11 -> 6.8235778 | U89: =Q89+R89*$AB$11 -> 7.2818098 | V89: 1.33056 | W89: =O89+V89*$AB$11 -> 5.1934558 | X89: =P89+V89*$AB$11 -> 7.3700578 | Y89: =Q89+V89*$AB$11 -> 7.8282898 | Z89: =F89*C89 -> 419.28228
C90: 366 | D90: 32 | E90: 2 | F90: =(D90-E90)*E90*0.02504 -> 1.5024 | G90: 1 | H90: =CONCATENATE(D90,E90) -> 322 | I90: 2.562 | J90: 2.05 | K90: 2.45 | L90: =I90+J90 -> 4.612 | M90: =I90+K90 -> 5.012 | O90: =((G90*(1-$O$2)+I90+$O$3)*F90*$O$7)*$AB$11 -> 4.5252288 | P90: =((G90*(1-$P$2)+I90+J90+$P$3)*F90*$O$7)*$AB$11 -> 7.6051488 | Q90: =((G90*(1-$Q$2)+I90+K90+$Q$3)*F90*$O$7)*$AB$11 -> 8.2061088 | R90: 0.85536 | S90: =O90+R90*$AB$11 -> 5.3805888 | T90: =P90+R90*$AB$11 -> 8.4605088 | U90: =Q90+R90*$AB$11 -> 9.0614688 | V90: 1.33056 | W90: =O90+V90*$AB$11 -> 5.8557888 | X90: =P90+V90*$AB$11 -> 8.9357088 | Y90: =Q90+V90*$AB$11 -> 9.5366688 | Z90: =F90*C90 -> 549.8784
C91: 366 | D91: 32 | E91: 2.5 | F91: =(D91-E91)*E91*0.02504 -> 1.8467 | G91: 1 | H91: =CONCATENATE(D91,E91) -> 322,5 | I91: 2.71 | J91: 1.9 | K91: 2.3 | L91: =I91+J91 -> 4.61 | M91: =I91+K91 -> 5.01 | O91: =((G91*(1-$O$2)+I91+$O$3)*F91*$O$7)*$AB$11 -> 5.835572 | P91: =((G91*(1-$P$2)+I91+J91+$P$3)*F91*$O$7)*$AB$11 -> 9.344302 | Q91: =((G91*(1-$Q$2)+I91+K91+$Q$3)*F91*$O$7)*$AB$11 -> 10.082982 | R91: 0.99792 | S91: =O91+R91*$AB$11 -> 6.833492 | T91: =P91+R91*$AB$11 -> 10.342222 | U91: =Q91+R91*$AB$11 -> 11.080902 | V91: 1.8414 | W91: =O91+V91*$AB$11 -> 7.676972 | X91: =P91+V91*$AB$11 -> 11.185702 | Y91: =Q91+V91*$AB$11 -> 11.924382 | Z91: =F91*C91 -> 675.8922
C92: 366 | D92: 32 | E92: 3 | F92: =(D92-E92)*E92*0.02504 -> 2.17848 | G92: 1 | H92: =CONCATENATE(D92,E92) -> 323 | I92: 2.8 | J92: 1.9 | K92: 2.3 | L92: =I92+J92 -> 4.7 | M92: =I92+K92 -> 5.1 | O92: =((G92*(1-$O$2)+I92+$O$3)*F92*$O$7)*$AB$11 -> 7.08006 | P92: =((G92*(1-$P$2)+I92+J92+$P$3)*F92*$O$7)*$AB$11 -> 11.219172 | Q92: =((G92*(1-$Q$2)+I92+K92+$Q$3)*F92*$O$7)*$AB$11 -> 12.090564 | R92: 1.21176 | S92: =O92+R92*$AB$11 -> 8.29182 | T92: =P92+R92*$AB$11 -> 12.430932 | U92: =Q92+R92*$AB$11 -> 13.302324 | V92: 2.30472 | W92: =O92+V92*$AB$11 -> 9.38478 | X92: =P92+V92*$AB$11 -> 13.523892 | Y92: =Q92+V92*$AB$11 -> 14.395284 | Z92: =F92*C92 -> 797.32368
C93: 366 | D93: 33 | E93: 1.5 | F93: =(D93-E93)*E93*0.02504 -> 1.18314 | G93: 1 | H93: =CONCATENATE(D93,E93) -> 331,5 | I93: 2.882 | J93: 1.9 | K93: 2.3 | L93: =I93+J93 -> 4.782 | M93: =I93+K93 -> 5.182 | O93: =((G93*(1-$O$2)+I93+$O$3)*F93*$O$7)*$AB$11 -> 3.9422225 | P93: =((G93*(1-$P$2)+I93+J93+$P$3)*F93*$O$7)*$AB$11 -> 6.1901885 | Q93: =((G93*(1-$Q$2)+I93+K93+$Q$3)*F93*$O$7)*$AB$11 -> 6.6634445 | R93: 0.80784 | S93: =O93+R93*$AB$11 -> 4.7500625 | T93: =P93+R93*$AB$11 -> 6.9980285 | U93: =Q93+R93*$AB$11 -> 7.4712845 | V93: 1.3662 | Y93: =Q93+V93*$AB$11 -> 8.0296445 | Z93: =F93*C93 -> 433.02924
A94: 25 | B94: 1" | C94: 366 | D94: 33.7 | E94: 1.2 | F94: =(D94-E94)*E94*0.02504 -> 0.97656 | G94: 1 | H94: =CONCATENATE(D94,E94) -> 33,71,2 | I94: 2.832 | J94: 1.9 | K94: 2.3 | L94: =I94+J94 -> 4.732 | M94: =I94+K94 -> 5.132 | O94: =((G94*(1-$O$2)+I94+$O$3)*F94*$O$7)*$AB$11 -> 3.2050699 | R94: 0.8316 | S94: =O94+R94*$AB$11 -> 4.0366699 | V94: 1.40184 | W94: =O94+V94*$AB$11 -> 4.6069099 | Z94: =F94*C94 -> 357.42096
C95: 366 | D95: 33.7 | E95: 1.5 | F95: =(D95-E95)*E95*0.02504 -> 1.209432 | G95: 1 | H95: =CONCATENATE(D95,E95) -> 33,71,5 | I95: 2.802 | J95: 1.9 | K95: 2.3 | L95: =I95+J95 -> 4.702 | M95: =I95+K95 -> 5.102 | O95: =((G95*(1-$O$2)+I95+$O$3)*F95*$O$7)*$AB$11 -> 3.9330729 | P95: =((G95*(1-$P$2)+I95+J95+$P$3)*F95*$O$7)*$AB$11 -> 6.2309937 | Q95: =((G95*(1-$Q$2)+I95+K95+$Q$3)*F95*$O$7)*$AB$11 -> 6.7147665 | R95: 0.8316 | S95: =O95+R95*$AB$11 -> 4.7646729 | T95: =P95+R95*$AB$11 -> 7.0625937 | U95: =Q95+R95*$AB$11 -> 7.5463665 | V95: 1.40184 | W95: =O95+V95*$AB$11 -> 5.3349129 | X95: =P95+V95*$AB$11 -> 7.6328337 | Y95: =Q95+V95*$AB$11 -> 8.1166065 | Z95: =F95*C95 -> 442.65211
C96: 366 | D96: 33.7 | E96: 1.6 | F96: =(D96-E96)*E96*0.02504 -> 1.2860544 | G96: 1 | H96: =CONCATENATE(D96,E96) -> 33,71,6 | I96: 2.802 | J96: 1.9 | K96: 2.3 | L96: =I96+J96 -> 4.702 | M96: =I96+K96 -> 5.102 | O96: =((G96*(1-$O$2)+I96+$O$3)*F96*$O$7)*$AB$11 -> 4.1822489 | P96: =((G96*(1-$P$2)+I96+J96+$P$3)*F96*$O$7)*$AB$11 -> 6.6257523 | R96: 0.8316 | S96: =O96+R96*$AB$11 -> 5.0138489 | T96: =P96+R96*$AB$11 -> 7.4573523 | V96: 1.40184 | Z96: =F96*C96 -> 470.69591
C97: 366 | D97: 33.7 | E97: 2 | F97: =(D97-E97)*E97*0.02504 -> 1.587536 | G97: 1 | H97: =CONCATENATE(D97,E97) -> 33,72 | I97: 2.532 | J97: 2.05 | K97: 2.45 | L97: =I97+J97 -> 4.582 | M97: =I97+K97 -> 4.982 | O97: =((G97*(1-$O$2)+I97+$O$3)*F97*$O$7)*$AB$11 -> 4.7340324 | P97: =((G97*(1-$P$2)+I97+J97+$P$3)*F97*$O$7)*$AB$11 -> 7.9884812 | Q97: =((G97*(1-$Q$2)+I97+K97+$Q$3)*F97*$O$7)*$AB$11 -> 8.6234956 | R97: 0.86724 | S97: =O97+R97*$AB$11 -> 5.6012724 | T97: =P97+R97*$AB$11 -> 8.8557212 | U97: =Q97+R97*$AB$11 -> 9.4907356 | V97: 1.40184 | W97: =O97+V97*$AB$11 -> 6.1358724 | X97: =P97+V97*$AB$11 -> 9.3903212 | Y97: =Q97+V97*$AB$11 -> 10.025336 | Z97: =F97*C97 -> 581.03818
C98: 366 | D98: 33.7 | E98: 2.5 | F98: =(D98-E98)*E98*0.02504 -> 1.95312 | G98: 1 | H98: =CONCATENATE(D98,E98) -> 33,72,5 | I98: 2.512 | J98: 1.9 | K98: 2.3 | L98: =I98+J98 -> 4.412 | M98: =I98+K98 -> 4.812 | O98: =((G98*(1-$O$2)+I98+$O$3)*F98*$O$7)*$AB$11 -> 5.7851414 | P98: =((G98*(1-$P$2)+I98+J98+$P$3)*F98*$O$7)*$AB$11 -> 9.4960694 | Q98: =((G98*(1-$Q$2)+I98+K98+$Q$3)*F98*$O$7)*$AB$11 -> 10.277317 | R98: 0.93852 | S98: =O98+R98*$AB$11 -> 6.7236614 | T98: =P98+R98*$AB$11 -> 10.434589 | U98: =Q98+R98*$AB$11 -> 11.215837 | V98: 1.93644 | W98: =O98+V98*$AB$11 -> 7.7215814 | X98: =P98+V98*$AB$11 -> 11.432509 | Y98: =Q98+V98*$AB$11 -> 12.213757 | Z98: =F98*C98 -> 714.84192
C99: 366 | D99: 33.7 | E99: 2.6 | F99: =(D99-E99)*E99*0.02504 -> 2.0247344 | G99: 1 | H99: =CONCATENATE(D99,E99) -> 33,72,6 | I99: 2.492 | J99: 1.9 | K99: 2.3 | L99: =I99+J99 -> 4.392 | M99: =I99+K99 -> 4.792 | O99: =((G99*(1-$O$2)+I99+$O$3)*F99*$O$7)*$AB$11 -> 5.9567686 | P99: =((G99*(1-$P$2)+I99+J99+$P$3)*F99*$O$7)*$AB$11 -> 9.803764 | R99: 0.93852 | S99: =O99+R99*$AB$11 -> 6.8952886 | V99: 1.93644 | Z99: =F99*C99 -> 741.05279
C100: 366 | D100: 33.7 | E100: 3 | F100: =(D100-E100)*E100*0.02504 -> 2.306184 | G100: 1 | H100: =CONCATENATE(D100,E100) -> 33,73 | I100: 2.502 | J100: 1.9 | K100: 2.3 | L100: =I100+J100 -> 4.402 | M100: =I100+K100 -> 4.802 | O100: =((G100*(1-$O$2)+I100+$O$3)*F100*$O$7)*$AB$11 -> 6.8078552 | P100: =((G100*(1-$P$2)+I100+J100+$P$3)*F100*$O$7)*$AB$11 -> 11.189605 | Q100: =((G100*(1-$Q$2)+I100+K100+$Q$3)*F100*$O$7)*$AB$11 -> 12.112078 | R100: 0.97416 | S100: =O100+R100*$AB$11 -> 7.7820152 | T100: =P100+R100*$AB$11 -> 12.163765 | U100: =Q100+R100*$AB$11 -> 13.086238 | V100: 2.0196 | W100: =O100+V100*$AB$11 -> 8.8274552 | X100: =P100+V100*$AB$11 -> 13.209205 | Y100: =Q100+V100*$AB$11 -> 14.131678 | Z100: =F100*C100 -> 844.06334
...

Sheet MARCEGAGLIA
A1: Marcegaglia Divisione Inox | L1: PRICE LIST 2013 ( Ed. 11 / 03 / 2013 )
A2: DISCOUNT | K2: 27 | P2: CORROSION
K3: EN 4301 EN 4307 | L3: EN 4541 | M3: EN 4404 EN 4571
AC4: Cross Rate | AD4: 41334
A5: Alloy Surcharge €/KG | K5: 2.5 | L5: 0 | M5: 3.7
A6: extra 1 €/KG | K6: 0 | AC6: €ur | AD6: 1
A7: extra 2 €/KG | K7: 0 | AC7: GBP | AD7: 0.863
A8: extra 3 €/KG | K8: 0 | AC8: USD | AD8: 1.308
A9: extra percentage | K9: 1 | R9: DAIRY ITEMS - COLD FINISHED 2B
A10: Currency | K10: eur
K11: Not Annealed Mill Finish | P11: POLISHED G.240/320 | X11: MIRROR POLISHED
K12: €ur / mtr | P12: €ur / mtr | X12: €ur / mtr
A13: Dimension | D13: CRUDO EUR/KG | G13: CRUDO EUR/MTR PIENO | K13: 1.4301 1.4307 | L13: 1.4541 | M13: 1.4404 1.4571 | P13: 1.4301 1.4307 | Q13: 1.4306 1.4541 | R13: 1.4404 1.4571 | X13: 1.4301 1.4307 | Y13: 1.4306 1.4541 | Z13: 1.4404 1.4571 | AC13: IN USO | AD13: =VLOOKUP(K10,$AC$2:$AD$9,2) -> 1
A14: Ø Diam. | B14: Thk. | C14: kg/mt | D14: 304 | E14: extra 321 | F14: extra 316 | G14: 304 | H14: extra 321 | I14: extra 316 | K14: 304 / 304 L | L14: 321 | M14: 316 L / Ti | N14: sat | P14: 304 / 304 L | Q14: 321 | R14: 316 L / Ti | V14: pol | X14: 304 / 304 L | Y14: 321 | Z14: 316 L / Ti
A15: 6 | B15: 1 | C15: =(A15-B15)*B15*0.02504 -> 0.1252 | D15: 5.6191667 | E15: 0.25 | F15: 0.45 | G15: =D15*C15 -> 0.70351967 | H15: =+E15*C15 -> 0.0313 | I15: =+F15*C15 -> 0.05634 | K15: =(((G15-G15*$K$2/100)+0.35*C15+($K$5*C15)+($K$6*C15)+($K$7*C15)+($K$8*C15))*$K$9)*$AD$13 -> 0.87038936 | L15: =(((G15-G15*$K$2/100+H15)+0.35*C15+($L$5*C15)+($K$6*C15)+($K$7*C15)+($K$8*C15))*$K$9)*$AD$13 -> 0.58868936 | M15: =(((G15-G15*$K$2/100+I15)+0.35*C15+($M$5*C15)+($K$6*C15)+($K$7*C15)+($K$8*C15))*$K$9)*$AD$13 -> 1.0769694 | AA15: 1200
A16: 8 | B16: 1 | C16: =(A16-B16)*B16*0.02504 -> 0.17528 | D16: 4.3816667 | E16: 0.25 | F16: 0.45 | G16: =D16*C16 -> 0.76801853 | H16: =+E16*C16 -> 0.04382 | I16: =+F16*C16 -> 0.078876 | K16: =(((G16-G16*$K$2/100)+0.35*C16+($K$5*C16)+($K$6*C16)+($K$7*C16)+($K$8*C16))*$K$9)*$AD$13 -> 1.0602015 | L16: =(((G16-G16*$K$2/100+H16)+0.35*C16+($L$5*C16)+($K$6*C16)+($K$7*C16)+($K$8*C16))*$K$9)*$AD$13 -> 0.66582153 | M16: =(((G16-G16*$K$2/100+I16)+0.35*C16+($M$5*C16)+($K$6*C16)+($K$7*C16)+($K$8*C16))*$K$9)*$AD$13 -> 1.3494135 | AA16: 1302
A17: 10 | B17: 1 | C17: =(A17-B17)*B17*0.02504 -> 0.22536 | D17: 3.6922024 | E17: 0.25 | F17: 0.45 | G17: =D17*C17 -> 0.83207473 | H17: =+E17*C17 -> 0.05634 | I17: =+F17*C17 -> 0.101412 | K17: =(((G17-G17*$K$2/100)+0.35*C17+($K$5*C17)+($K$6*C17)+($K$7*C17)+($K$8*C17))*$K$9)*$AD$13 -> 1.2496906 | L17: =(((G17-G17*$K$2/100+H17)+0.35*C17+($L$5*C17)+($K$6*C17)+($K$7*C17)+($K$8*C17))*$K$9)*$AD$13 -> 0.74263055 | M17: =(((G17-G17*$K$2/100+I17)+0.35*C17+($M$5*C17)+($K$6*C17)+($K$7*C17)+($K$8*C17))*$K$9)*$AD$13 -> 1.6215346 | AA17: 1302
A18: 10 | B18: 1.5 | C18: =(A18-B18)*B18*0.02504 -> 0.31926 | D18: 3.8754167 | E18: 0.25 | F18: 0.45 | G18: =D18*C18 -> 1.2372655 | H18: =+E18*C18 -> 0.079815 | I18: =+F18*C18 -> 0.143667 | K18: =(((G18-G18*$K$2/100)+0.35*C18+($K$5*C18)+($K$6*C18)+($K$7*C18)+($K$8*C18))*$K$9)*$AD$13 -> 1.8130948 | L18: =(((G18-G18*$K$2/100+H18)+0.35*C18+($L$5*C18)+($K$6*C18)+($K$7*C18)+($K$8*C18))*$K$9)*$AD$13 -> 1.0947598 | M18: =(((G18-G18*$K$2/100+I18)+0.35*C18+($M$5*C18)+($K$6*C18)+($K$7*C18)+($K$8*C18))*$K$9)*$AD$13 -> 2.3398738 | AA18: 1302
A19: 12 | B19: 1 | C19: =(A19-B19)*B19*0.02504 -> 0.27544 | D19: 3.6320833 | E19: 0.25 | F19: 0.45 | G19: =D19*C19 -> 1.000421 | H19: =+E19*C19 -> 0.06886 | I19: =+F19*C19 -> 0.123948 | K19: =(((G19-G19*$K$2/100)+0.35*C19+($K$5*C19)+($K$6*C19)+($K$7*C19)+($K$8*C19))*$K$9)*$AD$13 -> 1.5153114 | L19: =(((G19-G19*$K$2/100+H19)+0.35*C19+($L$5*C19)+($K$6*C19)+($K$7*C19)+($K$8*C19))*$K$9)*$AD$13 -> 0.89557135 | M19: =(((G19-G19*$K$2/100+I19)+0.35*C19+($M$5*C19)+($K$6*C19)+($K$7*C19)+($K$8*C19))*$K$9)*$AD$13 -> 1.9697874 | N19: 0.36151983 | P19: =K19+N19*$AD$13 -> 1.8768312 | Q19: =L19+N19*$AD$13 -> 1.2570912 | R19: =M19+N19*$AD$13 -> 2.3313072 | V19: 0.61959334 | AA19: 1626
A20: 12 | B20: 1.5 | C20: =(A20-B20)*B20*0.02504 -> 0.39438 | D20: 3.7980655 | E20: 0.25 | F20: 0.45 | G20: =D20*C20 -> 1.4978811 | H20: =+E20*C20 -> 0.098595 | I20: =+F20*C20 -> 0.177471 | K20: =(((G20-G20*$K$2/100)+0.35*C20+($K$5*C20)+($K$6*C20)+($K$7*C20)+($K$8*C20))*$K$9)*$AD$13 -> 2.2174362 | L20: =(((G20-G20*$K$2/100+H20)+0.35*C20+($L$5*C20)+($K$6*C20)+($K$7*C20)+($K$8*C20))*$K$9)*$AD$13 -> 1.3300812 | M20: =(((G20-G20*$K$2/100+I20)+0.35*C20+($M$5*C20)+($K$6*C20)+($K$7*C20)+($K$8*C20))*$K$9)*$AD$13 -> 2.8681632 | N20: 0.36151983 | P20: =K20+N20*$AD$13 -> 2.578956 | Q20: =L20+N20*$AD$13 -> 1.691601 | R20: =M20+N20*$AD$13 -> 3.229683 | V20: 0.61959334 | X20: =K20+V20*$AD$13 -> 2.8370295 | Y20: =L20+V20*$AD$13 -> 1.9496745 | Z20: =M20+V20*$AD$13 -> 3.4877565 | AA20: 1626
A21: 13 | B21: 1 | C21: =(A21-B21)*B21*0.02504 -> 0.30048 | D21: 3.6038095 | E21: 0.25 | F21: 0.45 | G21: =D21*C21 -> 1.0828727 | H21: =+E21*C21 -> 0.07512 | I21: =+F21*C21 -> 0.135216 | K21: =(((G21-G21*$K$2/100)+0.35*C21+($K$5*C21)+($K$6*C21)+($K$7*C21)+($K$8*C21))*$K$9)*$AD$13 -> 1.6468651 | L21: =(((G21-G21*$K$2/100+H21)+0.35*C21+($L$5*C21)+($K$6*C21)+($K$7*C21)+($K$8*C21))*$K$9)*$AD$13 -> 0.97078506 | M21: =(((G21-G21*$K$2/100+I21)+0.35*C21+($M$5*C21)+($K$6*C21)+($K$7*C21)+($K$8*C21))*$K$9)*$AD$13 -> 2.1426571 | N21: 0.36151983 | P21: =K21+N21*$AD$13 -> 2.0083849 | Q21: =L21+N21*$AD$13 -> 1.3323049 | R21: =M21+N21*$AD$13 -> 2.5041769 | V21: 0.61959334 | X21: =K21+V21*$AD$13 -> 2.2664584 | Y21: =L21+V21*$AD$13 -> 1.5903784 | Z21: =M21+V21*$AD$13 -> 2.7622504 | AA21: 1626
A22: 14 | B22: 1 | C22: =(A22-B22)*B22*0.02504 -> 0.32552 | D22: 2.9850595 | E22: 0.25 | F22: 0.45 | G22: =D22*C22 -> 0.97169658 | H22: =+E22*C22 -> 0.08138 | I22: =+F22*C22 -> 0.146484 | K22: =(((G22-G22*$K$2/100)+0.35*C22+($K$5*C22)+($K$6*C22)+($K$7*C22)+($K$8*C22))*$K$9)*$AD$13 -> 1.6370705 | L22: =(((G22-G22*$K$2/100+H22)+0.35*C22+($L$5*C22)+($K$6*C22)+($K$7*C22)+($K$8*C22))*$K$9)*$AD$13 -> 0.9046505 | M22: =(((G22-G22*$K$2/100+I22)+0.35*C22+($M$5*C22)+($K$6*C22)+($K$7*C22)+($K$8*C22))*$K$9)*$AD$13 -> 2.1741785 | N22: 0.36151983 | P22: =K22+N22*$AD$13 -> 1.9985903 | Q22: =L22+N22*$AD$13 -> 1.2661703 | R22: =M22+N22*$AD$13 -> 2.5356983 | V22: 0.61959334 | X22: =K22+V22*$AD$13 -> 2.2566638 | Y22: =L22+V22*$AD$13 -> 1.5242438 | Z22: =M22+V22*$AD$13 -> 2.7937718 | AA22: 1626
A23: 14 | B23: 1.5 | C23: =(A23-B23)*B23*0.02504 -> 0.4695 | D23: 3.0999702 | E23: 0.25 | F23: 0.45 | G23: =D23*C23 -> 1.455436 | H23: =+E23*C23 -> 0.117375 | I23: =+F23*C23 -> 0.211275 | K23: =(((G23-G23*$K$2/100)+0.35*C23+($K$5*C23)+($K$6*C23)+($K$7*C23)+($K$8*C23))*$K$9)*$AD$13 -> 2.4005433 | L23: =(((G23-G23*$K$2/100+H23)+0.35*C23+($L$5*C23)+($K$6*C23)+($K$7*C23)+($K$8*C23))*$K$9)*$AD$13 -> 1.3441683 | M23: =(((G23-G23*$K$2/100+I23)+0.35*C23+($M$5*C23)+($K$6*C23)+($K$7*C23)+($K$8*C23))*$K$9)*$AD$13 -> 3.1752183 | N23: 0.36151983 | P23: =K23+N23*$AD$13 -> 2.7620631 | Q23: =L23+N23*$AD$13 -> 1.7056881 | R23: =M23+N23*$AD$13 -> 3.5367381 | V23: 0.61959334 | X23: =K23+V23*$AD$13 -> 3.0201366 | Y23: =L23+V23*$AD$13 -> 1.9637616 | Z23: =M23+V23*$AD$13 -> 3.7948116 | AA23: 1626
A24: 14 | B24: 2 | C24: =(A24-B24)*B24*0.02504 -> 0.60096 | D24: 3.1559524 | E24: 0.25 | F24: 0.55 | G24: =D24*C24 -> 1.8966011 | H24: =+E24*C24 -> 0.15024 | I24: =+F24*C24 -> 0.330528 | K24: =(((G24-G24*$K$2/100)+0.35*C24+($K$5*C24)+($K$6*C24)+($K$7*C24)+($K$8*C24))*$K$9)*$AD$13 -> 3.0972548 | L24: =(((G24-G24*$K$2/100+H24)+0.35*C24+($L$5*C24)+($K$6*C24)+($K$7*C24)+($K$8*C24))*$K$9)*$AD$13 -> 1.7450948 | M24: =(((G24-G24*$K$2/100+I24)+0.35*C24+($M$5*C24)+($K$6*C24)+($K$7*C24)+($K$8*C24))*$K$9)*$AD$13 -> 4.1489348 | N24: 0.36151983 | P24: =K24+N24*$AD$13 -> 3.4587747 | Q24: =L24+N24*$AD$13 -> 2.1066147 | R24: =M24+N24*$AD$13 -> 4.5104547 | V24: 0.61959334 | X24: =K24+V24*$AD$13 -> 3.7168482 | Y24: =L24+V24*$AD$13 -> 2.3646882 | Z24: =M24+V24*$AD$13 -> 4.7685282 | AA24: 1014
A25: 15 | B25: 1 | C25: =(A25-B25)*B25*0.02504 -> 0.35056 | D25: 2.905506 | E25: 0.25 | F25: 0.45 | G25: =D25*C25 -> 1.0185542 | H25: =+E25*C25 -> 0.08764 | I25: =+F25*C25 -> 0.157752 | K25: =(((G25-G25*$K$2/100)+0.35*C25+($K$5*C25)+($K$6*C25)+($K$7*C25)+($K$8*C25))*$K$9)*$AD$13 -> 1.7426405 | L25: =(((G25-G25*$K$2/100+H25)+0.35*C25+($L$5*C25)+($K$6*C25)+($K$7*C25)+($K$8*C25))*$K$9)*$AD$13 -> 0.95388054 | M25: =(((G25-G25*$K$2/100+I25)+0.35*C25+($M$5*C25)+($K$6*C25)+($K$7*C25)+($K$8*C25))*$K$9)*$AD$13 -> 2.3210645 | N25: 0.36151983 | P25: =K25+N25*$AD$13 -> 2.1041604 | Q25: =L25+N25*$AD$13 -> 1.3154004 | R25: =M25+N25*$AD$13 -> 2.6825844 | V25: 0.61959334 | X25: =K25+V25*$AD$13 -> 2.3622339 | Y25: =L25+V25*$AD$13 -> 1.5734739 | Z25: =M25+V25*$AD$13 -> 2.9406579 | AA25: 1626
A26: 15 | B26: 1.5 | C26: =(A26-B26)*B26*0.02504 -> 0.50706 | D26: 3.0115774 | E26: 0.25 | F26: 0.45 | G26: =D26*C26 -> 1.5270504 | H26: =+E26*C26 -> 0.126765 | I26: =+F26*C26 -> 0.228177 | K26: =(((G26-G26*$K$2/100)+0.35*C26+($K$5*C26)+($K$6*C26)+($K$7*C26)+($K$8*C26))*$K$9)*$AD$13 -> 2.5598678 | L26: =(((G26-G26*$K$2/100+H26)+0.35*C26+($L$5*C26)+($K$6*C26)+($K$7*C26)+($K$8*C26))*$K$9)*$AD$13 -> 1.4189828 | M26: =(((G26-G26*$K$2/100+I26)+0.35*C26+($M$5*C26)+($K$6*C26)+($K$7*C26)+($K$8*C26))*$K$9)*$AD$13 -> 3.3965168 | N26: 0.36151983 | P26: =K26+N26*$AD$13 -> 2.9213876 | Q26: =L26+N26*$AD$13 -> 1.7805026 | R26: =M26+N26*$AD$13 -> 3.7580366 | V26: 0.61959334 | X26: =K26+V26*$AD$13 -> 3.1794612 | Y26: =L26+V26*$AD$13 -> 2.0385762 | Z26: =M26+V26*$AD$13 -> 4.0161102 | AA26: 1626
A27: 15 | B27: 2 | C27: =(A27-B27)*B27*0.02504 -> 0.65104 | D27: 2.9988095 | E27: 0.25 | F27: 0.55 | G27: =D27*C27 -> 1.952345 | H27: =+E27*C27 -> 0.16276 | I27: =+F27*C27 -> 0.358072 | K27: =(((G27-G27*$K$2/100)+0.35*C27+($K$5*C27)+($K$6*C27)+($K$7*C27)+($K$8*C27))*$K$9)*$AD$13 -> 3.2806758 | L27: =(((G27-G27*$K$2/100+H27)+0.35*C27+($L$5*C27)+($K$6*C27)+($K$7*C27)+($K$8*C27))*$K$9)*$AD$13 -> 1.8158358 | M27: =(((G27-G27*$K$2/100+I27)+0.35*C27+($M$5*C27)+($K$6*C27)+($K$7*C27)+($K$8*C27))*$K$9)*$AD$13 -> 4.4199958 | N27: 0.36151983 | P27: =K27+N27*$AD$13 -> 3.6421956 | Q27: =L27+N27*$AD$13 -> 2.1773556 | R27: =M27+N27*$AD$13 -> 4.7815156 | V27: 0.61959334 | X27: =K27+V27*$AD$13 -> 3.9002692 | Y27: =L27+V27*$AD$13 -> 2.4354292 | Z27: =M27+V27*$AD$13 -> 5.0395892 | AA27: 1014
A28: 16 | B28: 1 | C28: =(A28-B28)*B28*0.02504 -> 0.3756 | D28: 2.7463988 | E28: 0.25 | F28: 0.45 | G28: =D28*C28 -> 1.0315474 | H28: =+E28*C28 -> 0.0939 | I28: =+F28*C28 -> 0.16902 | K28: =(((G28-G28*$K$2/100)+0.35*C28+($K$5*C28)+($K$6*C28)+($K$7*C28)+($K$8*C28))*$K$9)*$AD$13 -> 1.8234896 | L28: =(((G28-G28*$K$2/100+H28)+0.35*C28+($L$5*C28)+($K$6*C28)+($K$7*C28)+($K$8*C28))*$K$9)*$AD$13 -> 0.9783896 | M28: =(((G28-G28*$K$2/100+I28)+0.35*C28+($M$5*C28)+($K$6*C28)+($K$7*C28)+($K$8*C28))*$K$9)*$AD$13 -> 2.4432296 | N28: 0.36151983 | O28: =N28*1936/A28 -> 43.743899 | P28: =K28+N28*$AD$13 -> 2.1850094 | Q28: =L28+N28*$AD$13 -> 1.3399094 | R28: =M28+N28*$AD$13 -> 2.8047494 | V28: 0.61959334 | W28: =V28*1936.27/A28 -> 74.98125 | X28: =K28+V28*$AD$13 -> 2.4430829 | Y28: =L28+V28*$AD$13 -> 1.5979829 | Z28: =M28+V28*$AD$13 -> 3.0628229 | AA28: 1626
A29: 16 | B29: 1.2 | C29: =(A29-B29)*B29*0.02504 -> 0.4447104 | D29: 2.6845238 | E29: 0.25 | F29: 0.45 | G29: =D29*C29 -> 1.1938357 | H29: =+E29*C29 -> 0.1111776 | I29: =+F29*C29 -> 0.20011968 | K29: =(((G29-G29*$K$2/100)+0.35*C29+($K$5*C29)+($K$6*C29)+($K$7*C29)+($K$8*C29))*$K$9)*$AD$13 -> 2.1389247 | L29: =(((G29-G29*$K$2/100+H29)+0.35*C29+($L$5*C29)+($K$6*C29)+($K$7*C29)+($K$8*C29))*$K$9)*$AD$13 -> 1.1383263 | M29: =(((G29-G29*$K$2/100+I29)+0.35*C29+($M$5*C29)+($K$6*C29)+($K$7*C29)+($K$8*C29))*$K$9)*$AD$13 -> 2.8726968 | N29: 0.36151983 | O29: =N29*1936/A29 -> 43.743899 | P29: =K29+N29*$AD$13 -> 2.5004445 | Q29: =L29+N29*$AD$13 -> 1.4998461 | R29: =M29+N29*$AD$13 -> 3.2342167 | V29: 0.61959334 | W29: =V29*1936.27/A29 -> 74.98125 | X29: =K29+V29*$AD$13 -> 2.758518 | Y29: =L29+V29*$AD$13 -> 1.7579196 | Z29: =M29+V29*$AD$13 -> 3.4922902 | AA29: 1626
A30: 16 | B30: 1.5 | C30: =(A30-B30)*B30*0.02504 -> 0.54462 | D30: 2.6314881 | E30: 0.25 | F30: 0.45 | G30: =D30*C30 -> 1.433161 | H30: =+E30*C30 -> 0.136155 | I30: =+F30*C30 -> 0.245079 | K30: =(((G30-G30*$K$2/100)+0.35*C30+($K$5*C30)+($K$6*C30)+($K$7*C30)+($K$8*C30))*$K$9)*$AD$13 -> 2.5983746 | L30: =(((G30-G30*$K$2/100+H30)+0.35*C30+($L$5*C30)+($K$6*C30)+($K$7*C30)+($K$8*C30))*$K$9)*$AD$13 -> 1.3729796 | M30: =(((G30-G30*$K$2/100+I30)+0.35*C30+($M$5*C30)+($K$6*C30)+($K$7*C30)+($K$8*C30))*$K$9)*$AD$13 -> 3.4969976 | N30: 0.36151983 | O30: =N30*1936/A30 -> 43.743899 | P30: =K30+N30*$AD$13 -> 2.9598944 | Q30: =L30+N30*$AD$13 -> 1.7344994 | R30: =M30+N30*$AD$13 -> 3.8585174 | V30: 0.61959334 | W30: =V30*1936.27/A30 -> 74.98125 | X30: =K30+V30*$AD$13 -> 3.2179679 | Y30: =L30+V30*$AD$13 -> 1.9925729 | Z30: =M30+V30*$AD$13 -> 4.1165909 | AA30: 1626
A31: 16 | B31: 2 | C31: =(A31-B31)*B31*0.02504 -> 0.70112 | D31: 2.6874702 | E31: 0.25 | F31: 0.55 | G31: =D31*C31 -> 1.8842391 | H31: =+E31*C31 -> 0.17528 | I31: =+F31*C31 -> 0.385616 | K31: =(((G31-G31*$K$2/100)+0.35*C31+($K$5*C31)+($K$6*C31)+($K$7*C31)+($K$8*C31))*$K$9)*$AD$13 -> 3.3736866 | L31: =(((G31-G31*$K$2/100+H31)+0.35*C31+($L$5*C31)+($K$6*C31)+($K$7*C31)+($K$8*C31))*$K$9)*$AD$13 -> 1.7961666 | M31: =(((G31-G31*$K$2/100+I31)+0.35*C31+($M$5*C31)+($K$6*C31)+($K$7*C31)+($K$8*C31))*$K$9)*$AD$13 -> 4.6006466 | N31: 0.36151983 | O31: =N31*1936/A31 -> 43.743899 | P31: =K31+N31*$AD$13 -> 3.7352064 | Q31: =L31+N31*$AD$13 -> 2.1576864 | R31: =M31+N31*$AD$13 -> 4.9621664 | V31: 0.61959334 | W31: =V31*1936.27/A31 -> 74.98125 | X31: =K31+V31*$AD$13 -> 3.9932799 | Y31: =L31+V31*$AD$13 -> 2.4157599 | Z31: =M31+V31*$AD$13 -> 5.2202399 | AA31: 1014
A32: 17.2 | B32: 1 | C32: =(A32-B32)*B32*0.02504 -> 0.405648 | D32: 2.5254167 | E32: 0.25 | F32: 0.45 | G32: =D32*C32 -> 1.0244302 | H32: =+E32*C32 -> 0.101412 | I32: =+F32*C32 -> 0.1825416 | K32: =(((G32-G32*$K$2/100)+0.35*C32+($K$5*C32)+($K$6*C32)+($K$7*C32)+($K$8*C32))*$K$9)*$AD$13 -> 1.9039309 | L32: =(((G32-G32*$K$2/100+H32)+0.35*C32+($L$5*C32)+($K$6*C32)+($K$7*C32)+($K$8*C32))*$K$9)*$AD$13 -> 0.99122286 | M32: =(((G32-G32*$K$2/100+I32)+0.35*C32+($M$5*C32)+($K$6*C32)+($K$7*C32)+($K$8*C32))*$K$9)*$AD$13 -> 2.5732501 | N32: 0.36151983 | O32: =N32*1936/A32 -> 40.691999 | P32: =K32+N32*$AD$13 -> 2.2654507 | Q32: =L32+N32*$AD$13 -> 1.3527427 | R32: =M32+N32*$AD$13 -> 2.9347699 | V32: 0.61959334 | W32: =V32*1936.27/A32 -> 69.75 | X32: =K32+V32*$AD$13 -> 2.5235242 | Y32: =L32+V32*$AD$13 -> 1.6108162 | Z32: =M32+V32*$AD$13 -> 3.1928434 | AA32: 1626
A33: 17.2 | B33: 1.2 | C33: =(A33-B33)*B33*0.02504 -> 0.480768 | D33: 2.3928274 | E33: 0.25 | F33: 0.45 | G33: =D33*C33 -> 1.1503948 | H33: =+E33*C33 -> 0.120192 | I33: =+F33*C33 -> 0.2163456 | K33: =(((G33-G33*$K$2/100)+0.35*C33+($K$5*C33)+($K$6*C33)+($K$7*C33)+($K$8*C33))*$K$9)*$AD$13 -> 2.209977 | L33: =(((G33-G33*$K$2/100+H33)+0.35*C33+($L$5*C33)+($K$6*C33)+($K$7*C33)+($K$8*C33))*$K$9)*$AD$13 -> 1.128249 | M33: =(((G33-G33*$K$2/100+I33)+0.35*C33+($M$5*C33)+($K$6*C33)+($K$7*C33)+($K$8*C33))*$K$9)*$AD$13 -> 3.0032442 | N33: 0.36151983 | O33: =N33*1936/A33 -> 40.691999 | P33: =K33+N33*$AD$13 -> 2.5714969 | Q33: =L33+N33*$AD$13 -> 1.4897689 | R33: =M33+N33*$AD$13 -> 3.3647641 | V33: 0.61959334 | W33: =V33*1936.27/A33 -> 69.75 | X33: =K33+V33*$AD$13 -> 2.8295704 | Y33: =L33+V33*$AD$13 -> 1.7478424 | Z33: =M33+V33*$AD$13 -> 3.6228376 | AA33: 1626
A34: 17.2 | B34: 1.5 | C34: =(A34-B34)*B34*0.02504 -> 0.589692 | D34: 2.2425595 | E34: 0.25 | F34: 0.45 | G34: =D34*C34 -> 1.3224194 | H34: =+E34*C34 -> 0.147423 | I34: =+F34*C34 -> 0.2653614 | K34: =(((G34-G34*$K$2/100)+0.35*C34+($K$5*C34)+($K$6*C34)+($K$7*C34)+($K$8*C34))*$K$9)*$AD$13 -> 2.6459884 | L34: =(((G34-G34*$K$2/100+H34)+0.35*C34+($L$5*C34)+($K$6*C34)+($K$7*C34)+($K$8*C34))*$K$9)*$AD$13 -> 1.3191814 | M34: =(((G34-G34*$K$2/100+I34)+0.35*C34+($M$5*C34)+($K$6*C34)+($K$7*C34)+($K$8*C34))*$K$9)*$AD$13 -> 3.6189802 | N34: 0.36151983 | O34: =N34*1936/A34 -> 40.691999 | P34: =K34+N34*$AD$13 -> 3.0075082 | Q34: =L34+N34*$AD$13 -> 1.6807012 | R34: =M34+N34*$AD$13 -> 3.9805 | V34: 0.61959334 | W34: =V34*1936.27/A34 -> 69.75 | X34: =K34+V34*$AD$13 -> 3.2655817 | Y34: =L34+V34*$AD$13 -> 1.9387747 | Z34: =M34+V34*$AD$13 -> 4.2385735 | AA34: 1626
A35: 17.2 | B35: 1.6 | C35: =(A35-B35)*B35*0.02504 -> 0.6249984 | D35: 2.2425595 | E35: 0.25 | F35: 0.45 | G35: =D35*C35 -> 1.4015961 | H35: =+E35*C35 -> 0.1562496 | I35: =+F35*C35 -> 0.28124928 | K35: =(((G35-G35*$K$2/100)+0.35*C35+($K$5*C35)+($K$6*C35)+($K$7*C35)+($K$8*C35))*$K$9)*$AD$13 -> 2.8044106 | L35: =(((G35-G35*$K$2/100+H35)+0.35*C35+($L$5*C35)+($K$6*C35)+($K$7*C35)+($K$8*C35))*$K$9)*$AD$13 -> 1.3981642 | M35: =(((G35-G35*$K$2/100+I35)+0.35*C35+($M$5*C35)+($K$6*C35)+($K$7*C35)+($K$8*C35))*$K$9)*$AD$13 -> 3.835658 | N35: 0.36151983 | O35: =N35*1936/A35 -> 40.691999 | P35: =K35+N35*$AD$13 -> 3.1659304 | Q35: =L35+N35*$AD$13 -> 1.759684 | R35: =M35+N35*$AD$13 -> 4.1971778 | V35: 0.61959334 | W35: =V35*1936.27/A35 -> 69.75 | X35: =K35+V35*$AD$13 -> 3.4240039 | Y35: =L35+V35*$AD$13 -> 2.0177575 | Z35: =M35+V35*$AD$13 -> 4.4552513 | AA35: 1626
A36: 17.2 | B36: 2 | C36: =(A36-B36)*B36*0.02504 -> 0.761216 | D36: 2.204256 | E36: 0.25 | F36: 0.55 | G36: =D36*C36 -> 1.6779149 | H36: =+E36*C36 -> 0.190304 | I36: =+F36*C36 -> 0.4186688 | K36: =(((G36-G36*$K$2/100)+0.35*C36+($K$5*C36)+($K$6*C36)+($K$7*C36)+($K$8*C36))*$K$9)*$AD$13 -> 3.3943435 | L36: =(((G36-G36*$K$2/100+H36)+0.35*C36+($L$5*C36)+($K$6*C36)+($K$7*C36)+($K$8*C36))*$K$9)*$AD$13 -> 1.6816075 | M36: =(((G36-G36*$K$2/100+I36)+0.35*C36+($M$5*C36)+($K$6*C36)+($K$7*C36)+($K$8*C36))*$K$9)*$AD$13 -> 4.7264715 | N36: 0.36151983 | O36: =N36*1936/A36 -> 40.691999 | P36: =K36+N36*$AD$13 -> 3.7558633 | Q36: =L36+N36*$AD$13 -> 2.0431273 | R36: =M36+N36*$AD$13 -> 5.0879913 | V36: 0.61959334 | W36: =V36*1936.27/A36 -> 69.75 | X36: =K36+V36*$AD$13 -> 4.0139368 | Y36: =L36+V36*$AD$13 -> 2.3012008 | Z36: =M36+V36*$AD$13 -> 5.3460648 | AA36: 1014
A37: 17.2 | B37: 2.3 | C37: =(A37-B37)*B37*0.02504 -> 0.8581208 | D37: 2.4841667 | E37: 0.25 | F37: 0.55 | G37: =D37*C37 -> 2.1317151 | H37: =+E37*C37 -> 0.2145302 | I37: =+F37*C37 -> 0.47196644 | K37: =(((G37-G37*$K$2/100)+0.35*C37+($K$5*C37)+($K$6*C37)+($K$7*C37)+($K$8*C37))*$K$9)*$AD$13 -> 4.0017963 | L37: =(((G37-G37*$K$2/100+H37)+0.35*C37+($L$5*C37)+($K$6*C37)+($K$7*C37)+($K$8*C37))*$K$9)*$AD$13 -> 2.0710245 | M37: =(((G37-G37*$K$2/100+I37)+0.35*C37+($M$5*C37)+($K$6*C37)+($K$7*C37)+($K$8*C37))*$K$9)*$AD$13 -> 5.5035077 | N37: 0.36151983 | O37: =N37*1936/A37 -> 40.691999 | P37: =K37+N37*$AD$13 -> 4.3633161 | Q37: =L37+N37*$AD$13 -> 2.4325443 | R37: =M37+N37*$AD$13 -> 5.8650275 | V37: 0.61959334 | W37: =V37*1936.27/A37 -> 69.75 | X37: =K37+V37*$AD$13 -> 4.6213896 | Y37: =L37+V37*$AD$13 -> 2.6906178 | Z37: =M37+V37*$AD$13 -> 6.123101 | AA37: 1014
A38: 18 | B38: 1 | C38: =(A38-B38)*B38*0.02504 -> 0.42568 | D38: 2.5360119 | E38: 0.25 | F38: 0.45 | G38: =D38*C38 -> 1.0795295 | H38: =+E38*C38 -> 0.10642 | I38: =+F38*C38 -> 0.191556 | K38: =(((G38-G38*$K$2/100)+0.35*C38+($K$5*C38)+($K$6*C38)+($K$7*C38)+($K$8*C38))*$K$9)*$AD$13 -> 2.0012446 | L38: =(((G38-G38*$K$2/100+H38)+0.35*C38+($L$5*C38)+($K$6*C38)+($K$7*C38)+($K$8*C38))*$K$9)*$AD$13 -> 1.0434646 | M38: =(((G38-G38*$K$2/100+I38)+0.35*C38+($M$5*C38)+($K$6*C38)+($K$7*C38)+($K$8*C38))*$K$9)*$AD$13 -> 2.7036166 | N38: 0.36151983 | O38: =N38*1936/A38 -> 38.883466 | P38: =K38+N38*$AD$13 -> 2.3627644 | Q38: =L38+N38*$AD$13 -> 1.4049844 | R38: =M38+N38*$AD$13 -> 3.0651364 | V38: 0.61959334 | W38: =V38*1936.27/A38 -> 66.65 | X38: =K38+V38*$AD$13 -> 2.6208379 | Y38: =L38+V38*$AD$13 -> 1.6630579 | Z38: =M38+V38*$AD$13 -> 3.3232099 | AA38: 1014
A39: 18 | B39: 1.2 | C39: =(A39-B39)*B39*0.02504 -> 0.5048064 | D39: 2.2779167 | E39: 0.25 | F39: 0.45 | G39: =D39*C39 -> 1.1499069 | H39: =+E39*C39 -> 0.1262016 | I39: =+F39*C39 -> 0.22716288 | K39: =(((G39-G39*$K$2/100)+0.35*C39+($K$5*C39)+($K$6*C39)+($K$7*C39)+($K$8*C39))*$K$9)*$AD$13 -> 2.2781303 | L39: =(((G39-G39*$K$2/100+H39)+0.35*C39+($L$5*C39)+($K$6*C39)+($K$7*C39)+($K$8*C39))*$K$9)*$AD$13 -> 1.1423159 | M39: =(((G39-G39*$K$2/100+I39)+0.35*C39+($M$5*C39)+($K$6*C39)+($K$7*C39)+($K$8*C39))*$K$9)*$AD$13 -> 3.1110608 | N39: 0.36151983 | O39: =N39*1936/A39 -> 38.883466 | P39: =K39+N39*$AD$13 -> 2.6396501 | Q39: =L39+N39*$AD$13 -> 1.5038357 | R39: =M39+N39*$AD$13 -> 3.4725807 | V39: 0.61959334 | W39: =V39*1936.27/A39 -> 66.65 | X39: =K39+V39*$AD$13 -> 2.8977236 | Y39: =L39+V39*$AD$13 -> 1.7619092 | Z39: =M39+V39*$AD$13 -> 3.7306542 | AA39: 1014
... A56: 21.3 | B56: 2 | C56: =(A56-B56)*B56*0.02504 -> 0.966544 | D56: 1.7789881 | E56: 0.25 | F56: 0.55 | G56: =D56*C56 -> 1.7194703 | H56: =+E56*C56 -> 0.241636 | I56: =+F56*C56 -> 0.5315992 | K56: =(((G56-G56*$K$2/100)+0.35*C56+($K$5*C56)+($K$6*C56)+($K$7*C56)+($K$8*C56))*$K$9)*$AD$13 -> 4.0098637 | L56: =(((G56-G56*$K$2/100+H56)+0.35*C56+($L$5*C56)+($K$6*C56)+($K$7*C56)+($K$8*C56))*$K$9)*$AD$13 -> 1.8351397 | M56: =(((G56-G56*$K$2/100+I56)+0.35*C56+($M$5*C56)+($K$6*C56)+($K$7*C56)+($K$8*C56))*$K$9)*$AD$13 -> 5.7013157 | N56: 0.37401809 | O56: =N56*1936/A56 -> 33.995259 | P56: =K56+N56*$AD$13 -> 4.3838818 | Q56: =L56+N56*$AD$13 -> 2.2091578 | R56: =M56+N56*$AD$13 -> 6.0753338 | V56: 0.61959334 | W56: =V56*1936.27/A56 -> 56.323944 | X56: =K56+V56*$AD$13 -> 4.629457 | Y56: =L56+V56*$AD$13 -> 2.454733 | Z56: =M56+V56*$AD$13 -> 6.320909 | AA56: 762
A57: 21.3 | B57: 2.5 | C57: =(A57-B57)*B57*0.02504 -> 1.17688 | D57: 1.8980425 | E57: 0.25 | F57: 0.55 | G57: =+G58 -> 2.2303879 | H57: =+H58 -> 0.3043612 | I57: =+I58 -> 0.66959464 | K57: =(((G57-G57*$K$2/100)+0.35*C57+($K$5*C57)+($K$6*C57)+($K$7*C57)+($K$8*C57))*$K$9)*$AD$13 -> 4.9822911 | L57: =(((G57-G57*$K$2/100+H57)+0.35*C57+($L$5*C57)+($K$6*C57)+($K$7*C57)+($K$8*C57))*$K$9)*$AD$13 -> 2.3444523 | M57: =(((G57-G57*$K$2/100+I57)+0.35*C57+($M$5*C57)+($K$6*C57)+($K$7*C57)+($K$8*C57))*$K$9)*$AD$13 -> 7.0641418 | N57: 0.39601915 | O57: =N57*1936/A57 -> 35.99498 | P57: =K57+N57*$AD$13 -> 5.3783103 | Q57: =L57+N57*$AD$13 -> 2.7404715 | R57: =M57+N57*$AD$13 -> 7.4601609 | V57: 0.61959334 | W57: =V57*1936.27/A57 -> 56.323944 | X57: =K57+V57*$AD$13 -> 5.6018845 | Y57: =L57+V57*$AD$13 -> 2.9640457 | Z57: =M57+V57*$AD$13 -> 7.6837351 | AA57: 762
A58: 21.3 | B58: 2.6 | C58: =(A58-B58)*B58*0.02504 -> 1.2174448 | D58: 1.8320238 | E58: 0.25 | F58: 0.55 | G58: =D58*C58 -> 2.2303879 | H58: =+E58*C58 -> 0.3043612 | I58: =+F58*C58 -> 0.66959464 | K58: =(((G58-G58*$K$2/100)+0.35*C58+($K$5*C58)+($K$6*C58)+($K$7*C58)+($K$8*C58))*$K$9)*$AD$13 -> 5.0979008 | L58: =(((G58-G58*$K$2/100+H58)+0.35*C58+($L$5*C58)+($K$6*C58)+($K$7*C58)+($K$8*C58))*$K$9)*$AD$13 -> 2.35865 | M58: =(((G58-G58*$K$2/100+I58)+0.35*C58+($M$5*C58)+($K$6*C58)+($K$7*C58)+($K$8*C58))*$K$9)*$AD$13 -> 7.2284292 | N58: 0.39601915 | O58: =N58*1936/A58 -> 35.99498 | P58: =K58+N58*$AD$13 -> 5.49392 | Q58: =L58+N58*$AD$13 -> 2.7546692 | R58: =M58+N58*$AD$13 -> 7.6244484 | V58: 0.61959334 | W58: =V58*1936.27/A58 -> 56.323944 | X58: =K58+V58*$AD$13 -> 5.7174942 | Y58: =L58+V58*$AD$13 -> 2.9782434 | Z58: =M58+V58*$AD$13 -> 7.8480226 | AA58: 762
A59: 21.3 | B59: 3 | C59: =(A59-B59)*B59*0.02504 -> 1.374696 | D59: 1.9184524 | E59: 0.25 | F59: 0.45 | G59: =D59*C59 -> 2.6372888 | H59: =+E59*C59 -> 0.343674 | I59: =+F59*C59 -> 0.6186132 | K59: =(((G59-G59*$K$2/100)+0.35*C59+($K$5*C59)+($K$6*C59)+($K$7*C59)+($K$8*C59))*$K$9)*$AD$13 -> 5.8431044 | L59: =(((G59-G59*$K$2/100+H59)+0.35*C59+($L$5*C59)+($K$6*C59)+($K$7*C59)+($K$8*C59))*$K$9)*$AD$13 -> 2.7500384 | M59: =(((G59-G59*$K$2/100+I59)+0.35*C59+($M$5*C59)+($K$6*C59)+($K$7*C59)+($K$8*C59))*$K$9)*$AD$13 -> 8.1113528 | N59: 0.41802021 | O59: =N59*1936/A59 -> 37.994701 | P59: =K59+N59*$AD$13 -> 6.2611246 | Q59: =L59+N59*$AD$13 -> 3.1680586 | R59: =M59+N59*$AD$13 -> 8.529373 | V59: 0.61959334 | W59: =V59*1936.27/A59 -> 56.323944 | X59: =K59+V59*$AD$13 -> 6.4626978 | Y59: =L59+V59*$AD$13 -> 3.3696318 | Z59: =M59+V59*$AD$13 -> 8.7309462 | AA59: 762
A60: 22 | B60: 0.8 | C60: =(A60-B60)*B60*0.02504 -> 0.4246784 | D60: 2.410506 | E60: 0.25 | F60: 0.45 | G60: =D60*C60 -> 1.0236898 | H60: =+E60*C60 -> 0.1061696 | I60: =+F60*C60 -> 0.19110528 | K60: =(((G60-G60*$K$2/100)+0.35*C60+($K$5*C60)+($K$6*C60)+($K$7*C60)+($K$8*C60))*$K$9)*$AD$13 -> 1.957627 | L60: =(((G60-G60*$K$2/100+H60)+0.35*C60+($L$5*C60)+($K$6*C60)+($K$7*C60)+($K$8*C60))*$K$9)*$AD$13 -> 1.0021006 | M60: =(((G60-G60*$K$2/100+I60)+0.35*C60+($M$5*C60)+($K$6*C60)+($K$7*C60)+($K$8*C60))*$K$9)*$AD$13 -> 2.6583464 | N60: 0.36151983 | O60: =N60*1936/A60 -> 31.813745 | P60: =K60+N60*$AD$13 -> 2.3191468 | Q60: =L60+N60*$AD$13 -> 1.3636204 | R60: =M60+N60*$AD$13 -> 3.0198662 | V60: 0.61959334 | W60: =V60*1936.27/A60 -> 54.531818 | X60: =K60+V60*$AD$13 -> 2.5772203 | Y60: =L60+V60*$AD$13 -> 1.6216939 | Z60: =M60+V60*$AD$13 -> 3.2779397 | AA60: 762
A61: 22 | B61: 1 | C61: =(A61-B61)*B61*0.02504 -> 0.52584 | D61: 2.261994 | E61: 0.25 | F61: 0.45 | G61: =D61*C61 -> 1.189447 | H61: =+E61*C61 -> 0.13146 | I61: =+F61*C61 -> 0.236628 | K61: =(((G61-G61*$K$2/100)+0.35*C61+($K$5*C61)+($K$6*C61)+($K$7*C61)+($K$8*C61))*$K$9)*$AD$13 -> 2.3669403 | L61: =(((G61-G61*$K$2/100+H61)+0.35*C61+($L$5*C61)+($K$6*C61)+($K$7*C61)+($K$8*C61))*$K$9)*$AD$13 -> 1.1838003 | M61: =(((G61-G61*$K$2/100+I61)+0.35*C61+($M$5*C61)+($K$6*C61)+($K$7*C61)+($K$8*C61))*$K$9)*$AD$13 -> 3.2345763 | N61: 0.36151983 | O61: =N61*1936/A61 -> 31.813745 | P61: =K61+N61*$AD$13 -> 2.7284601 | Q61: =L61+N61*$AD$13 -> 1.5453201 | R61: =M61+N61*$AD$13 -> 3.5960961 | V61: 0.61959334 | W61: =V61*1936.27/A61 -> 54.531818 | X61: =K61+V61*$AD$13 -> 2.9865336 | Y61: =L61+V61*$AD$13 -> 1.8033936 | Z61: =M61+V61*$AD$13 -> 3.8541696 | AA61: 762
A62: 22 | B62: 1.2 | C62: =(A62-B62)*B62*0.02504 -> 0.6249984 | D62: 2.0127381 | E62: 0.25 | F62: 0.45 | G62: =D62*C62 -> 1.2579581 | H62: =+E62*C62 -> 0.1562496 | I62: =+F62*C62 -> 0.28124928 | K62: =(((G62-G62*$K$2/100)+0.35*C62+($K$5*C62)+($K$6*C62)+($K$7*C62)+($K$8*C62))*$K$9)*$AD$13 -> 2.6995548 | L62: =(((G62-G62*$K$2/100+H62)+0.35*C62+($L$5*C62)+($K$6*C62)+($K$7*C62)+($K$8*C62))*$K$9)*$AD$13 -> 1.2933084 | M62: =(((G62-G62*$K$2/100+I62)+0.35*C62+($M$5*C62)+($K$6*C62)+($K$7*C62)+($K$8*C62))*$K$9)*$AD$13 -> 3.7308022 | N62: 0.36151983 | O62: =N62*1936/A62 -> 31.813745 | P62: =K62+N62*$AD$13 -> 3.0610747 | Q62: =L62+N62*$AD$13 -> 1.6548283 | R62: =M62+N62*$AD$13 -> 4.092322 | V62: 0.61959334 | W62: =V62*1936.27/A62 -> 54.531818 | X62: =K62+V62*$AD$13 -> 3.3191482 | Y62: =L62+V62*$AD$13 -> 1.9129018 | Z62: =M62+V62*$AD$13 -> 4.3503955 | AA62: 762
A63: 22 | B63: 1.5 | C63: =(A63-B63)*B63*0.02504 -> 0.76998 | D63: 2.1824405 | E63: 0.25 | F63: 0.45 | G63: =D63*C63 -> 1.6804355 | H63: =+E63*C63 -> 0.192495 | I63: =+F63*C63 -> 0.346491 | K63: =(((G63-G63*$K$2/100)+0.35*C63+($K$5*C63)+($K$6*C63)+($K$7*C63)+($K$8*C63))*$K$9)*$AD$13 -> 3.4211609 | L63: =(((G63-G63*$K$2/100+H63)+0.35*C63+($L$5*C63)+($K$6*C63)+($K$7*C63)+($K$8*C63))*$K$9)*$AD$13 -> 1.6887059 | M63: =(((G63-G63*$K$2/100+I63)+0.35*C63+($M$5*C63)+($K$6*C63)+($K$7*C63)+($K$8*C63))*$K$9)*$AD$13 -> 4.6916279 | N63: 0.36151983 | O63: =N63*1936/A63 -> 31.813745 | P63: =K63+N63*$AD$13 -> 3.7826808 | Q63: =L63+N63*$AD$13 -> 2.0502258 | R63: =M63+N63*$AD$13 -> 5.0531478 | V63: 0.61959334 | W63: =V63*1936.27/A63 -> 54.531818 | X63: =K63+V63*$AD$13 -> 4.0407543 | Y63: =L63+V63*$AD$13 -> 2.3082993 | Z63: =M63+V63*$AD$13 -> 5.3112213 | AA63: 762
A64: 22 | B64: 2 | C64: =(A64-B64)*B64*0.02504 -> 1.0016 | D64: 1.9184524 | E64: 0.25 | F64: 0.55 | G64: =D64*C64 -> 1.9215219 | H64: =+E64*C64 -> 0.2504 | I64: =+F64*C64 -> 0.55088 | K64: =(((G64-G64*$K$2/100)+0.35*C64+($K$5*C64)+($K$6*C64)+($K$7*C64)+($K$8*C64))*$K$9)*$AD$13 -> 4.257271 | L64: =(((G64-G64*$K$2/100+H64)+0.35*C64+($L$5*C64)+($K$6*C64)+($K$7*C64)+($K$8*C64))*$K$9)*$AD$13 -> 2.003671 | M64: =(((G64-G64*$K$2/100+I64)+0.35*C64+($M$5*C64)+($K$6*C64)+($K$7*C64)+($K$8*C64))*$K$9)*$AD$13 -> 6.010071 | N64: 0.37494771 | O64: =N64*1936/A64 -> 32.995398 | P64: =K64+N64*$AD$13 -> 4.6322187 | Q64: =L64+N64*$AD$13 -> 2.3786187 | R64: =M64+N64*$AD$13 -> 6.3850187 | V64: 0.61959334 | W64: =V64*1936.27/A64 -> 54.531818 | X64: =K64+V64*$AD$13 -> 4.8768643 | Y64: =L64+V64*$AD$13 -> 2.6232643 | Z64: =M64+V64*$AD$13 -> 6.6296643 | AA64: 762
A65: 23 | B65: 1.5 | C65: =(A65-B65)*B65*0.02504 -> 0.80754 | D65: 2.3061905 | E65: 0.25 | F65: 0.45 | G65: =D65*C65 -> 1.8623411 | H65: =+E65*C65 -> 0.201885 | I65: =+F65*C65 -> 0.363393 | K65: =(((G65-G65*$K$2/100)+0.35*C65+($K$5*C65)+($K$6*C65)+($K$7*C65)+($K$8*C65))*$K$9)*$AD$13 -> 3.660998 | L65: =(((G65-G65*$K$2/100+H65)+0.35*C65+($L$5*C65)+($K$6*C65)+($K$7*C65)+($K$8*C65))*$K$9)*$AD$13 -> 1.844033 | M65: =(((G65-G65*$K$2/100+I65)+0.35*C65+($M$5*C65)+($K$6*C65)+($K$7*C65)+($K$8*C65))*$K$9)*$AD$13 -> 4.993439 | N65: 0.36151983 | O65: =N65*1936/A65 -> 30.430539 | P65: =K65+N65*$AD$13 -> 4.0225178 | Q65: =L65+N65*$AD$13 -> 2.2055528 | R65: =M65+N65*$AD$13 -> 5.3549588 | V65: 0.61959334 | W65: =V65*1936.27/A65 -> 52.16087 | X65: =K65+V65*$AD$13 -> 4.2805913 | Y65: =L65+V65*$AD$13 -> 2.4636263 | Z65: =M65+V65*$AD$13 -> 5.6130323 | AA65: 762
A66: 25 | B66: 0.8 | C66: =(A66-B66)*B66*0.02504 -> 0.4847744 | D66: 2.3309524 | E66: 0.25 | F66: 0.45 | G66: =D66*C66 -> 1.129986 | H66: =+E66*C66 -> 0.1211936 | I66: =+F66*C66 -> 0.21814848 | K66: =(((G66-G66*$K$2/100)+0.35*C66+($K$5*C66)+($K$6*C66)+($K$7*C66)+($K$8*C66))*$K$9)*$AD$13 -> 2.2064969 | L66: =(((G66-G66*$K$2/100+H66)+0.35*C66+($L$5*C66)+($K$6*C66)+($K$7*C66)+($K$8*C66))*$K$9)*$AD$13 -> 1.1157545 | M66: =(((G66-G66*$K$2/100+I66)+0.35*C66+($M$5*C66)+($K$6*C66)+($K$7*C66)+($K$8*C66))*$K$9)*$AD$13 -> 3.0063746 | N66: 0.37443125 | O66: =N66*1936/A66 -> 28.995956 | P66: =K66+N66*$AD$13 -> 2.5809281 | Q66: =L66+N66*$AD$13 -> 1.4901857 | R66: =M66+N66*$AD$13 -> 3.3808059 | V66: 0.61959334 | W66: =V66*1936.27/A66 -> 47.988 | X66: =K66+V66*$AD$13 -> 2.8260902 | Y66: =L66+V66*$AD$13 -> 1.7353478 | Z66: =M66+V66*$AD$13 -> 3.625968 | AA66: 762
A67: 25 | B67: 1 | C67: =(A67-B67)*B67*0.02504 -> 0.60096 | D67: 2.0657738 | E67: 0.25 | F67: 0.45 | G67: =D67*C67 -> 1.2414474 | H67: =+E67*C67 -> 0.15024 | I67: =+F67*C67 -> 0.270432 | K67: =(((G67-G67*$K$2/100)+0.35*C67+($K$5*C67)+($K$6*C67)+($K$7*C67)+($K$8*C67))*$K$9)*$AD$13 -> 2.6189926 | L67: =(((G67-G67*$K$2/100+H67)+0.35*C67+($L$5*C67)+($K$6*C67)+($K$7*C67)+($K$8*C67))*$K$9)*$AD$13 -> 1.2668326 | M67: =(((G67-G67*$K$2/100+I67)+0.35*C67+($M$5*C67)+($K$6*C67)+($K$7*C67)+($K$8*C67))*$K$9)*$AD$13 -> 3.6105766 | N67: 0.37443125 | O67: =N67*1936/A67 -> 28.995956 | P67: =K67+N67*$AD$13 -> 2.9934239 | Q67: =L67+N67*$AD$13 -> 1.6412639 | R67: =M67+N67*$AD$13 -> 3.9850079 | V67: 0.61959334 | W67: =V67*1936.27/A67 -> 47.988 | X67: =K67+V67*$AD$13 -> 3.238586 | Y67: =L67+V67*$AD$13 -> 1.886426 | Z67: =M67+V67*$AD$13 -> 4.23017 | AA67: 762
A68: 25 | B68: 1.2 | C68: =(A68-B68)*B68*0.02504 -> 0.7151424 | D68: 1.977381 | E68: 0.25 | F68: 0.45 | G68: =D68*C68 -> 1.414109 | H68: =+E68*C68 -> 0.1787856 | I68: =+F68*C68 -> 0.32181408 | K68: =(((G68-G68*$K$2/100)+0.35*C68+($K$5*C68)+($K$6*C68)+($K$7*C68)+($K$8*C68))*$K$9)*$AD$13 -> 3.0704554 | L68: =(((G68-G68*$K$2/100+H68)+0.35*C68+($L$5*C68)+($K$6*C68)+($K$7*C68)+($K$8*C68))*$K$9)*$AD$13 -> 1.461385 | M68: =(((G68-G68*$K$2/100+I68)+0.35*C68+($M$5*C68)+($K$6*C68)+($K$7*C68)+($K$8*C68))*$K$9)*$AD$13 -> 4.2504403 | N68: 0.37443125 | O68: =N68*1936/A68 -> 28.995956 | P68: =K68+N68*$AD$13 -> 3.4448866 | Q68: =L68+N68*$AD$13 -> 1.8358162 | R68: =M68+N68*$AD$13 -> 4.6248716 | V68: 0.61959334 | W68: =V68*1936.27/A68 -> 47.988 | X68: =K68+V68*$AD$13 -> 3.6900487 | Y68: =L68+V68*$AD$13 -> 2.0809783 | Z68: =M68+V68*$AD$13 -> 4.8700337 | AA68: 762
A69: 25 | B69: 1.5 | C69: =(A69-B69)*B69*0.02504 -> 0.88266 | D69: 1.8624702 | E69: 0.25 | F69: 0.45 | G69: =D69*C69 -> 1.643928 | H69: =+E69*C69 -> 0.220665 | I69: =+F69*C69 -> 0.397197 | K69: =(((G69-G69*$K$2/100)+0.35*C69+($K$5*C69)+($K$6*C69)+($K$7*C69)+($K$8*C69))*$K$9)*$AD$13 -> 3.7156484 | L69: =(((G69-G69*$K$2/100+H69)+0.35*C69+($L$5*C69)+($K$6*C69)+($K$7*C69)+($K$8*C69))*$K$9)*$AD$13 -> 1.7296634 | M69: =(((G69-G69*$K$2/100+I69)+0.35*C69+($M$5*C69)+($K$6*C69)+($K$7*C69)+($K$8*C69))*$K$9)*$AD$13 -> 5.1720374 | N69: 0.37443125 | O69: =N69*1936/A69 -> 28.995956 | P69: =K69+N69*$AD$13 -> 4.0900797 | Q69: =L69+N69*$AD$13 -> 2.1040947 | R69: =M69+N69*$AD$13 -> 5.5464687 | V69: 0.61959334 | W69: =V69*1936.27/A69 -> 47.988 | X69: =K69+V69*$AD$13 -> 4.3352418 | Y69: =L69+V69*$AD$13 -> 2.3492568 | Z69: =M69+V69*$AD$13 -> 5.7916308 | AA69: 762
... A84: 26.9 | B84: 2 | C84: =(A84-B84)*B84*0.02504 -> 1.246992 | D84: 1.5088988 | E84: 0.25 | F84: 0.55 | G84: =D84*C84 -> 1.8815847 | H84: =+E84*C84 -> 0.311748 | I84: =+F84*C84 -> 0.6858456 | K84: =(((G84-G84*$K$2/100)+0.35*C84+($K$5*C84)+($K$6*C84)+($K$7*C84)+($K$8*C84))*$K$9)*$AD$13 -> 4.9274841 | L84: =(((G84-G84*$K$2/100+H84)+0.35*C84+($L$5*C84)+($K$6*C84)+($K$7*C84)+($K$8*C84))*$K$9)*$AD$13 -> 2.1217521 | M84: =(((G84-G84*$K$2/100+I84)+0.35*C84+($M$5*C84)+($K$6*C84)+($K$7*C84)+($K$8*C84))*$K$9)*$AD$13 -> 7.1097201 | N84: 0.40288803 | O84: =N84*1936/A84 -> 28.995956 | P84: =K84+N84*$AD$13 -> 5.3303721 | Q84: =L84+N84*$AD$13 -> 2.5246401 | R84: =M84+N84*$AD$13 -> 7.5126081 | V84: 0.61959334 | W84: =V84*1936.27/A84 -> 44.598513 | X84: =K84+V84*$AD$13 -> 5.5470774 | Y84: =L84+V84*$AD$13 -> 2.7413454 | Z84: =M84+V84*$AD$13 -> 7.7293134 | AA84: 762
A85: 26.9 | B85: 2.5 | C85: =(A85-B85)*B85*0.02504 -> 1.52744 | D85: 1.6024223 | E85: 0.25 | F85: 0.55 | G85: =+G86 -> 2.4430549 | H85: =+H86 -> 0.3955068 | I85: =+I86 -> 0.87011496 | K85: =(((G85-G85*$K$2/100)+0.35*C85+($K$5*C85)+($K$6*C85)+($K$7*C85)+($K$8*C85))*$K$9)*$AD$13 -> 6.1366341 | L85: =(((G85-G85*$K$2/100+H85)+0.35*C85+($L$5*C85)+($K$6*C85)+($K$7*C85)+($K$8*C85))*$K$9)*$AD$13 -> 2.7135409 | M85: =(((G85-G85*$K$2/100+I85)+0.35*C85+($M$5*C85)+($K$6*C85)+($K$7*C85)+($K$8*C85))*$K$9)*$AD$13 -> 8.8396771 | N85: 0.43067341 | O85: =N85*1936/A85 -> 30.995677 | P85: =K85+N85*$AD$13 -> 6.5673075 | Q85: =L85+N85*$AD$13 -> 3.1442143 | R85: =M85+N85*$AD$13 -> 9.2703505 | V85: 0.61959334 | W85: =V85*1936.27/A85 -> 44.598513 | X85: =K85+V85*$AD$13 -> 6.7562274 | Y85: =L85+V85*$AD$13 -> 3.3331342 | Z85: =M85+V85*$AD$13 -> 9.4592704 | AA85: 546
A86: 26.9 | B86: 2.6 | C86: =(A86-B86)*B86*0.02504 -> 1.5820272 | D86: 1.544256 | E86: 0.25 | F86: 0.55 | G86: =D86*C86 -> 2.4430549 | H86: =+E86*C86 -> 0.3955068 | I86: =+F86*C86 -> 0.87011496 | K86: =(((G86-G86*$K$2/100)+0.35*C86+($K$5*C86)+($K$6*C86)+($K$7*C86)+($K$8*C86))*$K$9)*$AD$13 -> 6.2922076 | L86: =(((G86-G86*$K$2/100+H86)+0.35*C86+($L$5*C86)+($K$6*C86)+($K$7*C86)+($K$8*C86))*$K$9)*$AD$13 -> 2.7326464 | M86: =(((G86-G86*$K$2/100+I86)+0.35*C86+($M$5*C86)+($K$6*C86)+($K$7*C86)+($K$8*C86))*$K$9)*$AD$13 -> 9.0607552 | N86: 0.43067341 | O86: =N86*1936/A86 -> 30.995677 | P86: =K86+N86*$AD$13 -> 6.722881 | Q86: =L86+N86*$AD$13 -> 3.1633198 | R86: =M86+N86*$AD$13 -> 9.4914286 | V86: 0.61959334 | W86: =V86*1936.27/A86 -> 44.598513 | X86: =K86+V86*$AD$13 -> 6.911801 | Y86: =L86+V86*$AD$13 -> 3.3522398 | Z86: =M86+V86*$AD$13 -> 9.6803486 | AA86: 546
A87: 26.9 | B87: 3 | C87: =(A87-B87)*B87*0.02504 -> 1.795368 | D87: 1.7082738 | E87: 0.25 | F87: 0.45 | G87: =D87*C87 -> 3.0669801 | H87: =+E87*C87 -> 0.448842 | I87: =+F87*C87 -> 0.8079156 | K87: =(((G87-G87*$K$2/100)+0.35*C87+($K$5*C87)+($K$6*C87)+($K$7*C87)+($K$8*C87))*$K$9)*$AD$13 -> 7.3556943 | L87: =(((G87-G87*$K$2/100+H87)+0.35*C87+($L$5*C87)+($K$6*C87)+($K$7*C87)+($K$8*C87))*$K$9)*$AD$13 -> 3.3161163 | M87: =(((G87-G87*$K$2/100+I87)+0.35*C87+($M$5*C87)+($K$6*C87)+($K$7*C87)+($K$8*C87))*$K$9)*$AD$13 -> 10.318051 | N87: 0.50013686 | O87: =N87*1936/A87 -> 35.99498 | P87: =K87+N87*$AD$13 -> 7.8558312 | Q87: =L87+N87*$AD$13 -> 3.8162532 | R87: =M87+N87*$AD$13 -> 10.818188 | V87: 0.70372035 | W87: =V87*1936.27/A87 -> 50.654 | X87: =K87+V87*$AD$13 -> 8.0594146 | Y87: =L87+V87*$AD$13 -> 4.0198366 | Z87: =M87+V87*$AD$13 -> 11.021772 | AA87: 546
A88: 28 | B88: 1 | C88: =(A88-B88)*B88*0.02504 -> 0.67608 | D88: 2.1117262 | E88: 0.25 | F88: 0.45 | G88: =D88*C88 -> 1.4276958 | H88: =+E88*C88 -> 0.16902 | I88: =+F88*C88 -> 0.304236 | K88: =(((G88-G88*$K$2/100)+0.35*C88+($K$5*C88)+($K$6*C88)+($K$7*C88)+($K$8*C88))*$K$9)*$AD$13 -> 2.969046 | L88: =(((G88-G88*$K$2/100+H88)+0.35*C88+($L$5*C88)+($K$6*C88)+($K$7*C88)+($K$8*C88))*$K$9)*$AD$13 -> 1.447866 | M88: =(((G88-G88*$K$2/100+I88)+0.35*C88+($M$5*C88)+($K$6*C88)+($K$7*C88)+($K$8*C88))*$K$9)*$AD$13 -> 4.084578 | N88: 0.37598062 | O88: =N88*1936/A88 -> 25.996374 | P88: =K88+N88*$AD$13 -> 3.3450266 | Q88: =L88+N88*$AD$13 -> 1.8238466 | R88: =M88+N88*$AD$13 -> 4.4605586 | V88: 0.61959334 | W88: =V88*1936.27/A88 -> 42.846429 | X88: =K88+V88*$AD$13 -> 3.5886393 | Y88: =L88+V88*$AD$13 -> 2.0674593 | Z88: =M88+V88*$AD$13 -> 4.7041713 | AA88: 546
A89: 28 | B89: 1.2 | C89: =(A89-B89)*B89*0.02504 -> 0.8052864 | D89: 1.8624702 | E89: 0.25 | F89: 0.45 | G89: =D89*C89 -> 1.499822 | H89: =+E89*C89 -> 0.2013216 | I89: =+F89*C89 -> 0.36237888 | K89: =(((G89-G89*$K$2/100)+0.35*C89+($K$5*C89)+($K$6*C89)+($K$7*C89)+($K$8*C89))*$K$9)*$AD$13 -> 3.3899363 | L89: =(((G89-G89*$K$2/100+H89)+0.35*C89+($L$5*C89)+($K$6*C89)+($K$7*C89)+($K$8*C89))*$K$9)*$AD$13 -> 1.5780419 | M89: =(((G89-G89*$K$2/100+I89)+0.35*C89+($M$5*C89)+($K$6*C89)+($K$7*C89)+($K$8*C89))*$K$9)*$AD$13 -> 4.7186588 | N89: 0.37598062 | O89: =N89*1936/A89 -> 25.996374 | P89: =K89+N89*$AD$13 -> 3.7659169 | Q89: =L89+N89*$AD$13 -> 1.9540225 | R89: =M89+N89*$AD$13 -> 5.0946394 | V89: 0.61959334 | W89: =V89*1936.27/A89 -> 42.846429 | X89: =K89+V89*$AD$13 -> 4.0095296 | Y89: =L89+V89*$AD$13 -> 2.1976352 | Z89: =M89+V89*$AD$13 -> 5.3382522 | AA89: 546
A90: 28 | B90: 1.5 | C90: =(A90-B90)*B90*0.02504 -> 0.99534 | D90: 2.0410119 | E90: 0.25 | F90: 0.45 | G90: =D90*C90 -> 2.0315008 | H90: =+E90*C90 -> 0.248835 | I90: =+F90*C90 -> 0.447903 | K90: =(((G90-G90*$K$2/100)+0.35*C90+($K$5*C90)+($K$6*C90)+($K$7*C90)+($K$8*C90))*$K$9)*$AD$13 -> 4.3197146 | L90: =(((G90-G90*$K$2/100+H90)+0.35*C90+($L$5*C90)+($K$6*C90)+($K$7*C90)+($K$8*C90))*$K$9)*$AD$13 -> 2.0801996 | M90: =(((G90-G90*$K$2/100+I90)+0.35*C90+($M$5*C90)+($K$6*C90)+($K$7*C90)+($K$8*C90))*$K$9)*$AD$13 -> 5.9620256 | N90: 0.37598062 | O90: =N90*1936/A90 -> 25.996374 | P90: =K90+N90*$AD$13 -> 4.6956952 | Q90: =L90+N90*$AD$13 -> 2.4561802 | R90: =M90+N90*$AD$13 -> 6.3380062 | V90: 0.61959334 | W90: =V90*1936.27/A90 -> 42.846429 | X90: =K90+V90*$AD$13 -> 4.9393079 | Y90: =L90+V90*$AD$13 -> 2.6997929 | Z90: =M90+V90*$AD$13 -> 6.5816189 | AA90: 546
A91: 28 | B91: 2 | C91: =(A91-B91)*B91*0.02504 -> 1.30208 | D91: 1.7082738 | E91: 0.25 | F91: 0.55 | G91: =D91*C91 -> 2.2243092 | H91: =+E91*C91 -> 0.32552 | I91: =+F91*C91 -> 0.716144 | K91: =(((G91-G91*$K$2/100)+0.35*C91+($K$5*C91)+($K$6*C91)+($K$7*C91)+($K$8*C91))*$K$9)*$AD$13 -> 5.3346737 | L91: =(((G91-G91*$K$2/100+H91)+0.35*C91+($L$5*C91)+($K$6*C91)+($K$7*C91)+($K$8*C91))*$K$9)*$AD$13 -> 2.4049937 | M91: =(((G91-G91*$K$2/100+I91)+0.35*C91+($M$5*C91)+($K$6*C91)+($K$7*C91)+($K$8*C91))*$K$9)*$AD$13 -> 7.6133137 | N91: 0.40490221 | O91: =N91*1936/A91 -> 27.996096 | P91: =K91+N91*$AD$13 -> 5.7395759 | Q91: =L91+N91*$AD$13 -> 2.8098959 | R91: =M91+N91*$AD$13 -> 8.0182159 | V91: 0.61959334 | W91: =V91*1936.27/A91 -> 42.846429 | X91: =K91+V91*$AD$13 -> 5.954267 | Y91: =L91+V91*$AD$13 -> 3.024587 | Z91: =M91+V91*$AD$13 -> 8.232907 | AA91: 546
A92: 29 | B92: 1.5 | C92: =(A92-B92)*B92*0.02504 -> 1.0329 | D92: 2.1824405 | E92: 0.25 | F92: 0.45 | G92: =D92*C92 -> 2.2542428 | H92: =+E92*C92 -> 0.258225 | I92: =+F92*C92 -> 0.464805 | K92: =(((G92-G92*$K$2/100)+0.35*C92+($K$5*C92)+($K$6*C92)+($K$7*C92)+($K$8*C92))*$K$9)*$AD$13 -> 4.5893622 | L92: =(((G92-G92*$K$2/100+H92)+0.35*C92+($L$5*C92)+($K$6*C92)+($K$7*C92)+($K$8*C92))*$K$9)*$AD$13 -> 2.2653372 | M92: =(((G92-G92*$K$2/100+I92)+0.35*C92+($M$5*C92)+($K$6*C92)+($K$7*C92)+($K$8*C92))*$K$9)*$AD$13 -> 6.2936472 | N92: 0.3894085 | O92: =N92*1936/A92 -> 25.996374 | P92: =K92+N92*$AD$13 -> 4.9787707 | Q92: =L92+N92*$AD$13 -> 2.6547457 | R92: =M92+N92*$AD$13 -> 6.6830557 | V92: 0.61959334 | W92: =V92*1936.27/A92 -> 41.368966 | X92: =K92+V92*$AD$13 -> 5.2089556 | Y92: =L92+V92*$AD$13 -> 2.8849306 | Z92: =M92+V92*$AD$13 -> 6.9132406 | AA92: 546
A93: 30 | B93: 1 | C93: =(A93-B93)*B93*0.02504 -> 0.72616 | D93: 1.9243452 | E93: 0.25 | F93: 0.45 | G93: =D93*C93 -> 1.3973825 | H93: =+E93*C93 -> 0.18154 | I93: =+F93*C93 -> 0.326772 | K93: =(((G93-G93*$K$2/100)+0.35*C93+($K$5*C93)+($K$6*C93)+($K$7*C93)+($K$8*C93))*$K$9)*$AD$13 -> 3.0896453 | L93: =(((G93-G93*$K$2/100+H93)+0.35*C93+($L$5*C93)+($K$6*C93)+($K$7*C93)+($K$8*C93))*$K$9)*$AD$13 -> 1.4557853 | M93: =(((G93-G93*$K$2/100+I93)+0.35*C93+($M$5*C93)+($K$6*C93)+($K$7*C93)+($K$8*C93))*$K$9)*$AD$13 -> 4.2878093 | N93: 0.38734267 | O93: =N93*1936/A93 -> 24.996514 | P93: =K93+N93*$AD$13 -> 3.4769879 | Q93: =L93+N93*$AD$13 -> 1.8431279 | R93: =M93+N93*$AD$13 -> 4.6751519 | V93: 0.61959334 | W93: =V93*1936.27/A93 -> 39.99 | X93: =K93+V93*$AD$13 -> 3.7092386 | Y93: =L93+V93*$AD$13 -> 2.0753786 | Z93: =M93+V93*$AD$13 -> 4.9074026 | AA93: 546
A94: 30 | B94: 1.2 | C94: =(A94-B94)*B94*0.02504 -> 0.8653824 | D94: 1.8624702 | E94: 0.25 | F94: 0.45 | G94: =D94*C94 -> 1.611749 | H94: =+E94*C94 -> 0.2163456 | I94: =+F94*C94 -> 0.38942208 | K94: =(((G94-G94*$K$2/100)+0.35*C94+($K$5*C94)+($K$6*C94)+($K$7*C94)+($K$8*C94))*$K$9)*$AD$13 -> 3.6429166 | L94: =(((G94-G94*$K$2/100+H94)+0.35*C94+($L$5*C94)+($K$6*C94)+($K$7*C94)+($K$8*C94))*$K$9)*$AD$13 -> 1.6958062 | M94: =(((G94-G94*$K$2/100+I94)+0.35*C94+($M$5*C94)+($K$6*C94)+($K$7*C94)+($K$8*C94))*$K$9)*$AD$13 -> 5.0707975 | N94: 0.38734267 | O94: =N94*1936/A94 -> 24.996514 | P94: =K94+N94*$AD$13 -> 4.0302593 | Q94: =L94+N94*$AD$13 -> 2.0831489 | R94: =M94+N94*$AD$13 -> 5.4581402 | V94: 0.61959334 | W94: =V94*1936.27/A94 -> 39.99 | X94: =K94+V94*$AD$13 -> 4.2625099 | Y94: =L94+V94*$AD$13 -> 2.3153995 | Z94: =M94+V94*$AD$13 -> 5.6903909 | AA94: 546
A95: 30 | B95: 1.5 | C95: =(A95-B95)*B95*0.02504 -> 1.07046 | D95: 1.8359524 | E95: 0.25 | F95: 0.45 | G95: =D95*C95 -> 1.9653136 | H95: =+E95*C95 -> 0.267615 | I95: =+F95*C95 -> 0.481707 | K95: =(((G95-G95*$K$2/100)+0.35*C95+($K$5*C95)+($K$6*C95)+($K$7*C95)+($K$8*C95))*$K$9)*$AD$13 -> 4.4854899 | L95: =(((G95-G95*$K$2/100+H95)+0.35*C95+($L$5*C95)+($K$6*C95)+($K$7*C95)+($K$8*C95))*$K$9)*$AD$13 -> 2.0769549 | M95: =(((G95-G95*$K$2/100+I95)+0.35*C95+($M$5*C95)+($K$6*C95)+($K$7*C95)+($K$8*C95))*$K$9)*$AD$13 -> 6.2517489 | N95: 0.38734267 | O95: =N95*1936/A95 -> 24.996514 | P95: =K95+N95*$AD$13 -> 4.8728326 | Q95: =L95+N95*$AD$13 -> 2.4642976 | R95: =M95+N95*$AD$13 -> 6.6390916 | V95: 0.61959334 | W95: =V95*1936.27/A95 -> 39.99 | X95: =K95+V95*$AD$13 -> 5.1050833 | Y95: =L95+V95*$AD$13 -> 2.6965483 | Z95: =M95+V95*$AD$13 -> 6.8713423 | AA95: 546
A96: 30 | B96: 2 | C96: =(A96-B96)*B96*0.02504 -> 1.40224 | D96: 1.5707738 | E96: 0.25 | F96: 0.55 | G96: =D96*C96 -> 2.2026019 | H96: =+E96*C96 -> 0.35056 | I96: =+F96*C96 -> 0.771232 | K96: =(((G96-G96*$K$2/100)+0.35*C96+($K$5*C96)+($K$6*C96)+($K$7*C96)+($K$8*C96))*$K$9)*$AD$13 -> 5.6042834 | L96: =(((G96-G96*$K$2/100+H96)+0.35*C96+($L$5*C96)+($K$6*C96)+($K$7*C96)+($K$8*C96))*$K$9)*$AD$13 -> 2.4492434 | M96: =(((G96-G96*$K$2/100+I96)+0.35*C96+($M$5*C96)+($K$6*C96)+($K$7*C96)+($K$8*C96))*$K$9)*$AD$13 -> 8.0582034 | N96: 0.41833009 | O96: =N96*1936/A96 -> 26.996235 | P96: =K96+N96*$AD$13 -> 6.0226135 | Q96: =L96+N96*$AD$13 -> 2.8675735 | R96: =M96+N96*$AD$13 -> 8.4765335 | V96: 0.61959334 | W96: =V96*1936.27/A96 -> 39.99 | X96: =K96+V96*$AD$13 -> 6.2238767 | Y96: =L96+V96*$AD$13 -> 3.0688367 | Z96: =M96+V96*$AD$13 -> 8.6777967 | AA96: 546
A97: 30 | B97: 2.5 | C97: =(A97-B97)*B97*0.02504 -> 1.7215 | D97: 1.7033631 | E97: 0.25 | F97: 0.55 | G97: =D97*C97 -> 2.9323396 | H97: =+E97*C97 -> 0.430375 | I97: =+F97*C97 -> 0.946825 | K97: =(((G97-G97*$K$2/100)+0.35*C97+($K$5*C97)+($K$6*C97)+($K$7*C97)+($K$8*C97))*$K$9)*$AD$13 -> 7.0468829 | L97: =(((G97-G97*$K$2/100+H97)+0.35*C97+($L$5*C97)+($K$6*C97)+($K$7*C97)+($K$8*C97))*$K$9)*$AD$13 -> 3.1735079 | M97: =(((G97-G97*$K$2/100+I97)+0.35*C97+($M$5*C97)+($K$6*C97)+($K$7*C97)+($K$8*C97))*$K$9)*$AD$13 -> 10.059508 | N97: 0.48030492 | O97: =N97*1936/A97 -> 30.995677 | P97: =K97+N97*$AD$13 -> 7.5271878 | Q97: =L97+N97*$AD$13 -> 3.6538128 | R97: =M97+N97*$AD$13 -> 10.539813 | V97: 0.68155268 | W97: =V97*1936.27/A97 -> 43.989 | X97: =K97+V97*$AD$13 -> 7.7284356 | Y97: =L97+V97*$AD$13 -> 3.8550606 | Z97: =M97+V97*$AD$13 -> 10.741061 | AA97: 366
... A111: 33.7 | B111: 2 | C111: =(A111-B111)*B111*0.02504 -> 1.587536 | D111: 1.3055952 | E111: 0.25 | F111: 0.55 | G111: =D111*C111 -> 2.0726794 | H111: =+E111*C111 -> 0.396884 | I111: =+F111*C111 -> 0.8731448 | K111: =(((G111-G111*$K$2/100)+0.35*C111+($K$5*C111)+($K$6*C111)+($K$7*C111)+($K$8*C111))*$K$9)*$AD$13 -> 6.0375336 | L111: =(((G111-G111*$K$2/100+H111)+0.35*C111+($L$5*C111)+($K$6*C111)+($K$7*C111)+($K$8*C111))*$K$9)*$AD$13 -> 2.4655776 | M111: =(((G111-G111*$K$2/100+I111)+0.35*C111+($M$5*C111)+($K$6*C111)+($K$7*C111)+($K$8*C111))*$K$9)*$AD$13 -> 8.8157216 | N111: 0.43511494 | O111: =N111*1936/A111 -> 24.996514 | P111: =K111+N111*$AD$13 -> 6.4726485 | Q111: =L111+N111*$AD$13 -> 2.9006925 | R111: =M111+N111*$AD$13 -> 9.2508365 | V111: 0.69600985 | W111: =V111*1936.27/A111 -> 39.99 | X111: =K111+V111*$AD$13 -> 6.7335434 | Y111: =L111+V111*$AD$13 -> 3.1615874 | Z111: =M111+V111*$AD$13 -> 9.5117314 | AA111: 546
A112: 33.7 | B112: 2.5 | C112: =(A112-B112)*B112*0.02504 -> 1.95312 | D112: 1.2923789 | E112: 0.25 | F112: 0.55 | G112: =+G113 -> 2.5182032 | H112: =+H113 -> 0.5061836 | I112: =+I113 -> 1.1136039 | K112: =(((G112-G112*$K$2/100)+0.35*C112+($K$5*C112)+($K$6*C112)+($K$7*C112)+($K$8*C112))*$K$9)*$AD$13 -> 7.4046803 | L112: =(((G112-G112*$K$2/100+H112)+0.35*C112+($L$5*C112)+($K$6*C112)+($K$7*C112)+($K$8*C112))*$K$9)*$AD$13 -> 3.0280639 | M112: =(((G112-G112*$K$2/100+I112)+0.35*C112+($M$5*C112)+($K$6*C112)+($K$7*C112)+($K$8*C112))*$K$9)*$AD$13 -> 10.862028 | N112: 0.43511494 | O112: =N112*1936/A112 -> 24.996514 | P112: =K112+N112*$AD$13 -> 7.8397952 | Q112: =L112+N112*$AD$13 -> 3.4631788 | R112: =M112+N112*$AD$13 -> 11.297143 | V112: 0.69600985 | W112: =V112*1936.27/A112 -> 39.99 | X112: =K112+V112*$AD$13 -> 8.1006902 | Y112: =L112+V112*$AD$13 -> 3.7240738 | Z112: =M112+V112*$AD$13 -> 11.558038 | AA112: 366
